{
  "7532034656590367806": {
    "err": "failed after retries",
    "bookId": "7532034656590367806"
  },
  "7636894338433174552": {
    "err": "failed after retries",
    "bookId": "7636894338433174552"
  },
  "7635504565827161112": {
    "err": "failed after retries",
    "bookId": "7635504565827161112"
  },
  "7636786866406034456": {
    "err": "failed after retries",
    "bookId": "7636786866406034456"
  },
  "7646959026944609305": {
    "err": "failed after retries",
    "bookId": "7646959026944609305"
  },
  "7641780820503448601": {
    "err": "failed after retries",
    "bookId": "7641780820503448601"
  },
  "7628889555789171774": {
    "err": "failed after retries",
    "bookId": "7628889555789171774"
  },
  "7646360547536948248": {
    "err": "failed after retries",
    "bookId": "7646360547536948248"
  },
  "7648308824670997528": {
    "err": "failed after retries",
    "bookId": "7648308824670997528"
  },
  "7635631070448192537": {
    "err": "failed after retries",
    "bookId": "7635631070448192537"
  },
  "7645885784267951166": {
    "err": "failed after retries",
    "bookId": "7645885784267951166"
  },
  "7570729668664364094": {
    "bookId": "7570729668664364094",
    "bookName": "禁止侵入",
    "authorName": "橦肆",
    "abstract": "黑帮太子爷vs黑道千金\n纯恨的【对抗路】、假到死的【忠犬系】、只想弄死对方的【尾骨】、拉断筋的【极限拉扯】\n人前，相亲相爱\n人后，拿枪互怼\n她拿着枪，瞄准他下半生幸福，毫不犹豫扣下扳机；\n他把她抓去联姻，告诉她“男人关了灯都是一个屌样”。\n宋迦木弯起丹凤眼，笑着说；我们家那位大小姐，很爱“作”。\n宋衾萝扶着快折断的腰，骂道:“呸！明明爱做的人，是他！”\n————\n如果人生是一趟公交车，你坐了一程，最后会在哪个站下车？",
    "creationStatus": 0,
    "wordNumber": 269186,
    "tags": [
      "豪门总裁",
      "现代言情",
      "总裁",
      "大小姐",
      "双洁",
      "1v1"
    ]
  },
  "7611549044116048921": {
    "bookId": "7611549044116048921",
    "bookName": "逃不掉！疯批大佬的囚宠",
    "authorName": "小婉君呀",
    "abstract": "欧美腹黑坏种 VS 华国娇软妹宝\n【男强女弱+跨国恋+强制爱+体型差+强取豪夺+绝对掌控者+男主纯坏种+1v1 结局He】\n欧美盛传，蒙西家族权势滔天，而坐镇权力之巅的那位掌权者，神秘莫测。\n蒂凯恩.蒙西，是整个欧美权贵圈中，人人敬畏的顶级大佬。仅凭一个名字，便足以令人闻风丧胆。\n楚绵绵有一个小秘密，她偷偷喜欢着一位学长，他叫裴孜辛。\n学长生日那天 ，他特意邀她去参加派对，女孩满心欢喜，又紧张又期待。\n只因一次误闯，楚绵绵进错了包厢，招惹到了那个狠戾嗜血的男人，从此被他牢牢盯上。\n从相遇那一刻起，她便成了他势在必得的猎物。\n*\n“对…对不起…我、我走错包厢了！”\n“慢着！”\n楚绵绵不由得停下脚步，颤巍巍地转身。\n男人微微俯身，指尖勾起她的下巴，目光落在她惊慌失措的小脸上，语气戏谑：\n“哪来的小鹿到处乱撞？”\n*\n再一次偷跑被抓回来后，男人将她强势逼近，语气玩味又恶劣：\n“小可怜别哭了，抱紧我。”\n楚绵绵浑身轻颤，泪水模糊了视线，哽咽着哭出声：\n“呜呜呜……蒂凯恩，我讨厌你！”\n*\n曾经杀伐果断、不可一世的男人，从此为她低头。\n“绵绵，爱我吧。我的一切，我的命，都是你的。”",
    "creationStatus": 1,
    "wordNumber": 158866,
    "tags": [
      "豪门总裁",
      "现代言情",
      "腹黑",
      "HE",
      "大佬",
      "1v1"
    ]
  },
  "7639266273104235582": {
    "bookId": "7639266273104235582",
    "bookName": "京婚难离",
    "authorName": "变美变富有",
    "abstract": "【先婚后爱+上位者低头+细水长流小甜文+双洁】\n　　裴砚其人，斯文矜贵，家世优渥，是温知妤这辈子都够不着的人。\n　　直到一场意外，她代替继姐嫁进裴家。\n　　婚礼当天，裴砚看都没看她一眼，直接飞往海市出差。\n　　所有人都说裴砚不喜欢她，离婚是迟早的事。\n　　温知妤也是这么以为的。\n　　所以她很乖，不吵不闹，按时喝药，乖乖睡觉。\n　　相处之后却发现，裴砚这人，表面疏离冷淡，做的事却越来越不像那么回事。\n　　新婚三天回门，他丢下饭局赶来，就为了给她夹一筷子鱼。\n　　她说自己坐地铁上班，第二天车库里就多了台玛莎拉蒂。\n　　出差外地，男人顶着风雪赶来，只因她朋友圈有陌生异性的身影。\n　　温知妤这才意识到，这个男人，好像从来没打算跟她离婚。\n　　后来有人问裴砚：“你不是独身主义吗？”\n　　裴砚看了眼坐在身旁的女孩儿，“遇到她之前是。”\n　　......\n　　最初，他只想要一个乖巧听话的妻子应付家里。\n　　后来，他开始祈求她的爱。",
    "creationStatus": 0,
    "wordNumber": 220979,
    "tags": [
      "豪门总裁",
      "现代言情",
      "先婚后爱",
      "双洁",
      "位尊权重",
      "代嫁代娶"
    ]
  },
  "7604443985309879321": {
    "bookId": "7604443985309879321",
    "bookName": "沈总，你的恋爱脑娇妻不要你喽",
    "authorName": "猫猫不挑食",
    "abstract": "【女主看似娇妻，实则800个心眼子】\n【男主看似薄情，实则妻奴恋爱脑】\n【追妻+双洁】\n人人都知道江虞爱惨了沈承晏。\n结婚五年，她对沈承晏百依百顺，言听计从。\n她是恋爱脑，是冷脸洗内裤的娇妻。\n她这辈子都离不开沈承晏。\n就连沈承晏也这么认为。\n直到他收到了江虞准备的离婚合同。\n-\n分居后的第一天，沈承晏失眠到天亮。\n但他还是傲慢而笃定的认为江虞会回到他身边。\n分居后的第一周，他发现江虞拉黑他了。\n分居后的第一个月，他看到江虞从陌生男人的车里下来。\n男人轻搂着她，她牵着一个小男孩，幸福的就像一家三口。\n沈承晏内心天崩地塌。\n看着蹲在地上傻乐的儿子，他气不打一处出来：“你妈在外面都有小孩了，你还不去一哭二闹三上吊？”\n沈墨白了亲爹一眼：“该上吊的是你吧，你老婆都不要你喽~”",
    "creationStatus": 0,
    "wordNumber": 292668,
    "tags": [
      "豪门总裁",
      "现代言情",
      "萌宝",
      "总裁",
      "追妻火葬场",
      "双洁"
    ]
  },
  "7611356991092427801": {
    "bookId": "7611356991092427801",
    "bookName": "原创乙女向短篇",
    "authorName": "苔隐",
    "abstract": "【纯bg，一切为个人xp服务】\n【较多章节都偏强制，不吃这口的不要看】\n【会有私设，介意的不要看，代不进别勉强】\n【看到含“女主”等词汇的评论会删，有漏掉的欢迎大家艾特我】\n【有其余任意雷点也都不建议阅读，请丢掉大脑观看】\n【喜恶同因，你不喜欢说明不是写给你看的】\n1.邻居是暗恋你已久的阴湿男\n2.……\n3.捡到的失忆男是总裁\n4.丈夫的上司看你的眼神好像有点奇怪\n5.清冷校草甘愿被你\n6.跟体育生竹马共感后\n7.……\n8.丈夫死后\n9.吸血鬼你被人类医生捡到后\n10.霸凌咖怎么变成你的狗了\n11.……\n12.家道中落后\n……",
    "creationStatus": 1,
    "wordNumber": 252592,
    "tags": [
      "豪门总裁",
      "现代言情",
      "甜宠",
      "独宠",
      "HE",
      "忠犬"
    ]
  },
  "7638604338268490814": {
    "bookId": "7638604338268490814",
    "bookName": "宝宝！乖！别紧张，大胆一点！",
    "authorName": "浅夏蔷薇花",
    "abstract": "【黑芝麻心的女主+腹黑八百个心眼的男主+双强+爽文】\r\n夜蘭无意中救了一个男人。\r\n男人醒来，第一句话：“你救了我，又不要钱？要不我把我送给你？”\r\n夜蘭微眯美眸，捏住他的下颚，“不是吧？阿sir，虽然你有那么一点姿色，但我是你永远得不到的女人，不和你玩了，拜拜了您！”\r\n夜蘭一溜烟的逃走了。\r\n男人好看的眸子微眯，得不得到我说了算，葬在哪里我都想好了这辈子你死也只能是我纪冥修的鬼！\r\n宴会上。\r\n夜蘭看着不远处的男人，耳边传来两个人的闲聊：\r\n【那是林茜的未婚夫吗？】\r\n【这男人好像是神秘家族的继承人。】\r\n【听说他很爱林茜，好羡慕。】\r\n未婚夫？夜蘭眼底闪过寒冰，林茜还真会传谣。\r\n夜蘭勾唇，转脸看那两个人说道：“谣言不可信，你们信不信我勾勾手指，姓纪的就乖乖的过来？”\r\n“你谁啊？”\r\n“不信？”夜蘭挑了挑眉，看向纪冥修“姓纪的，过来。”\r\n纪冥修在众目睽睽下，走到了夜蘭的面前，“老婆大人，有什么吩咐？”\r\n大家哗然，这还是那个人人惧怕的活阎王纪冥修？他怎么像只小奶狗？\r\n从此后。\r\n纪冥修夜夜哄着她，“宝贝，别紧张大胆一点。”\r\n夜蘭扶额，自己最经不起他这副勾栏做派的样子！",
    "creationStatus": 1,
    "wordNumber": 288879,
    "tags": [
      "豪门总裁",
      "现代言情",
      "总裁",
      "腹黑",
      "强强",
      "位尊权重"
    ]
  },
  "7645549653651360830": {
    "bookId": "7645549653651360830",
    "bookName": "小穷鬼把京圈太子爷强制圈养后",
    "authorName": "四弯月",
    "abstract": "[偏日常/穷人强制爱/小甜文/女强制男/]\n阮萌对傅砚舟一见钟情。\n大学苦苦追求四年，傅砚舟依然对她爱答不理。\n外界传出傅砚舟和名门千金订婚的消息，阮萌急了。\n她决定把傅砚舟锁起来。\n可问题是，阮萌很穷。\n别人搞囚禁，把人关在豪华大别墅里。\n阮萌搞囚禁，只能把人关在郊外的破出租屋里，还没空调。\n不到一个月，傅砚舟饿瘦了十斤。\n傅砚舟忍无可忍，一把扯掉手腕的铁链：\n“阮萌，我亲自下厨，你离厨房远点！”\n“别买中号的x，买最大号！”\n阮萌惊呆了。\n你能挣脱锁链啊？\n阮萌吓得连夜就跑，岂料被傅砚舟堵在墙角。\n“跑什么？”\n“不是要圈养我？继续。”\n阮萌泪流满面了。\n————\n傅砚舟从小缺爱。\n直到有天，阮萌闯进他的世界，说要养他一辈子，给他全部的爱。\n人生荒芜，他需要一条锁住自己的铁链。\n【PS：两个有病的家伙笨拙地相爱。\n切记，穷鬼别学人搞强制爱(ᗜ ˰ ᗜ) ​】\n【天然呆软萌摄影师X腹黑缺爱京圈太子爷】",
    "creationStatus": 1,
    "wordNumber": 233366,
    "tags": [
      "豪门总裁",
      "现代言情",
      "腹黑",
      "甜宠",
      "暗恋",
      "位尊权重"
    ]
  },
  "7641477597490056254": {
    "bookId": "7641477597490056254",
    "bookName": "领证前失约，未婚夫弟弟趁虚而入",
    "authorName": "茶后",
    "abstract": "【现代言情+弟弟上位+蓄谋已久+宠妻+甜宠+男绿茶+先婚后爱+1v1+独宠+豪门总裁】\n领证前几分钟，未婚夫裴霆深选择推迟领证调转车头去医院看望刚回国的小青梅。\n沈若溪对着电话那头最后一句话。\n“五分钟后不出现，我就在民政局门口随便拉着别的男人领证，以后谁也不羁绊谁。”\n裴霆深只当是玩笑话，毅然去了医院。\n沈若溪气红了眼眶。\n背后突然传来一道熟悉的男人声音。\n“刚才说的五分钟还算数吗？”\n裴慕野，“嫂子不介意的话，考虑考虑我呗。”\n沈若溪就这样糊糊涂涂跟未婚夫的弟弟领了证，刚走出民政局门口就后悔了。\n“裴慕野，我们回去离个婚吧。”\n裴慕野拿着结婚证就跑，“抱歉，不做二婚男。”\n晚上，拿着新鲜出炉的结婚证闯进书房。\n“哥，你的保险柜借我用一下。”\n“干什么？”\n“女朋友送我的礼物，怕弄丢了她会生气。”",
    "creationStatus": 1,
    "wordNumber": 243244,
    "tags": [
      "豪门总裁",
      "现代言情",
      "总裁",
      "宠妻",
      "先婚后爱",
      "1v1"
    ]
  },
  "7636736834541718553": {
    "bookId": "7636736834541718553",
    "bookName": "联姻骄纵千金，偏执大佬宠上天",
    "authorName": "秦厌",
    "abstract": "评分刚出，会涨的～【1v1双洁，先婚后爱，全程高甜，大佬重欲偏执又纯情，生理性喜欢，满心满眼只偏爱小娇娇，他超爱！大黄丫头们，都来看吧～】\n 年上掌控型daddy & 娇纵豪门千金\n　京海人人都知道，霍沈两家联姻，不过是一场明码标价的利益交换。\n\n　　沈舒宜也这么以为。\n\n　　新婚夜，她软声叫了一句“霍先生”。\n\n　　男人背对着她站在落地窗前，周身气场冷得压人。\n\n　　她小心翼翼地问：“今晚……我们睡一间房吗？”\n\n　　男人转过身，眸色深沉：“你怕我？”\n\n　　她诚实点头：“你看起来好凶。”\n\n　　所有人都以为这场联姻注定相敬如“冰”。\n\n　　没人知道这位杀伐果断的霍大总裁，会在新婚夜红了耳根，会在试衣间里失控，会因为一条短信推掉几十亿的会议。\n　\n　　她撒娇，“老公，你会不会有一天不喜欢我了？”\n\n　　他低头吻她，声音低沉而郑重：\n\n　　“小乖，你是我的妻子，是我这辈子唯一想捧在手心里的人。”\n\n　　京海最冷的阎王，把毕生温柔都给了他的小乖",
    "creationStatus": 1,
    "wordNumber": 223053,
    "tags": [
      "豪门总裁",
      "现代言情",
      "先婚后爱",
      "双洁",
      "1v1",
      "位尊权重"
    ]
  },
  "7625274054341053465": {
    "bookId": "7625274054341053465",
    "bookName": "妹妹嫌男友冷淡？但我亲得挺爽",
    "authorName": "百万瓜瓜",
    "abstract": "【豪门太子爷+小甜文+妹妹用男友照片骗我网恋+追妻火葬场+男洁】\n苏浅母胎单身，意外和人网恋。\n好消息：男友188，八块腹肌，冷白皮校草。\n坏消息：他是同父异母的妹妹冒充的。\n好消息：照片是妹妹男友，豪门太子爷江寂。\n传闻这位太子爷性子冷淡，都不让妹妹碰。\n苏浅贪财又好色，又想报复妹妹，干脆主动勾搭江寂。\n太子爷胃疼？她天天送早餐！\n太子爷喝醉？她主动送他回家！\n太子爷口不对心？她依旧把他宠上天。\n——\n后来，苏浅觉得江寂太难追了，打算和豪门相亲对象结婚。\n没想到，太子爷疯了。\n一向冷淡的男人追到港城，红着眼，把她按在了婚纱照前。\n“浅浅，是不是怀了宝宝，你才不会抛弃我？”\n.\n【小剧场】\n妹妹：她是骗你的，她是为了报复我！\n太子爷：她只骗我，说明她爱我。",
    "creationStatus": 0,
    "wordNumber": 297492,
    "tags": [
      "豪门总裁",
      "现代言情",
      "总裁",
      "甜宠",
      "豪门世家",
      "追妻火葬场"
    ]
  },
  "7648178680786586649": {
    "bookId": "7648178680786586649",
    "bookName": "卡他失忆哄离婚，病娇又又失控了",
    "authorName": "灯下不黑黑",
    "abstract": "假乖巧x真病娇\n强取豪夺x火葬场xhe\n路小桥是路家被宠坏的宝。\n谢浔是令人闻风丧胆的爷。\n谢浔说：“娶你是为了让大嫂安心。”\n她乖巧：“我想要两千万～”\n谢浔说：“你不要跟大嫂抢。”\n她眨眼：“那孩子跟我姓哦～”\n心上人变大嫂，都说谢浔娶她是自暴自弃，而她嫁他则是爱惨了他。\n路小桥撇嘴巴。\n这些瞎子。\n—\n大哥意外去世。\n小叔子和大嫂的传言越演越烈。\n背德，禁忌，热闹好大。\n一场婚姻她赚的盆满钵满，路小桥爱这世界缤纷，可她唯独不爱绿色。\n她说：“离婚吧。”\n谢浔拨弄婚戒，睨她：“又缺什么了？”\n啥都不缺。\n她有乖崽，财务自由，人生体验感拉满。\n申请躺平。\n都以为谢浔会顺势应她，然后跟大嫂顺理成章，可一年过去了，丝毫没有进展。\n-\n谢浔车祸失忆了。\n为了救大嫂。\n可惜他不知道，车里的是路小桥，若知道，他的拼命将毫无意义。\n但离婚的机会来了。\n路小桥哄道：“不被爱的才是小三，签了这份协议，我助你们双宿双飞。”\n谢浔头痛欲裂，在她小嘴叭叭时只想吻上去。\n-\n深夜长街，跑车横在中央，谢浔看向光柱里逃跑的姑娘，阴鸷双眸压着猩红隐忍：“方向盘抓稳，脚别抖——”\n“来，撞死我，你就自由了。”",
    "creationStatus": 1,
    "wordNumber": 183348,
    "tags": [
      "豪门总裁",
      "现代言情",
      "总裁",
      "病娇",
      "HE",
      "追妻火葬场"
    ]
  },
  "7624909493817576473": {
    "bookId": "7624909493817576473",
    "bookName": "喂！别让老实人欺辱阴湿男啊！",
    "authorName": "小鸭鸭",
    "abstract": "【老实温软漂亮妹宝❌宠妻型腹黑阴湿继承人】\n【双洁➕自我攻略➕暗恋➕同居掉马➕暧昧甜文】\n看见男人昏倒在路边，温伊念好心报警。\n结果下一秒就被系统绑定。\n【恭喜你救下男主，解锁恶毒女友身份，请获得恶毒值100，不然死翘翘！】\n温伊念：？\n嗨？在吗？她就路过！她不救了！\n—\n从此，温伊念被迫走上一条不归路。\n【请调教本文高冷男主】\n【扇他脸，羞辱他，骂他，让他在床上服侍你…】\n她惊恐捂住衣领：“等一下！还要卖身？！”\n直到某天，系统突然察觉不对劲。\n【坏了！我们救错了！这是最危险的反派！】\n黑暗中，男人察觉到她分心，低头亲吻颈侧，“念念在想什么？”\n温伊念：“…”\n在想现在洗心革面还有用吗？\n—\n失忆后，谢京许刚睁眼就多了个女友。\n女友人傻还好骗。\n她说，他的一切都是她的。\n可后来，看着空荡荡的家里。\n谢京许嘴角笑意消失。\n小骗子。\n知道他身份后跑的比谁都快。\n—\n谁不知道，谢家继承人性情阴狠，城府极深，为达目的不择手段。\n包厢里，男人单手支着头，似笑非笑道：“听说温小姐有个未婚夫。”\n朋友小声提醒她：“谢总以前失忆被女人骗过，厌恶女人，千万别招惹他。”\n那如果…被招惹呢？\n温伊念笑容牵强，耳朵发烫。\n没人知道，餐桌下。\n男人皮鞋正暧昧蹭着她的小腿。",
    "creationStatus": 1,
    "wordNumber": 156980,
    "tags": [
      "豪门总裁",
      "现代言情",
      "宠妻",
      "腹黑",
      "暗恋",
      "双洁"
    ]
  },
  "7623007618532903960": {
    "bookId": "7623007618532903960",
    "bookName": "穿成财阀男主的心机女秘书",
    "authorName": "招财猫喵咪",
    "abstract": "贪财小迷糊x腹黑掌权人（评分还会涨）\n孟静意外穿书，发现自己是一本顶级财阀文中的恶毒女秘书。\n原著中她利用职务之便，屡次陷害女主，并且使出浑身解数勾引男主，甚至多次下药，企图挟子上位。\n事情败露被扔到山区，嫁给了大她二十岁的老光棍，最后夜里起来喂猪的时候不小心摔在猪圈里，被猪咬死了。\n而男女主没了孟静这个最大的障碍，先婚后爱了。\n一朝穿书后，孟静兢兢业业的扮演秘书的角色，疯狂攒钱准备跑路。\n男主工作她递笔，男主感冒她送药，从不越界，被评价为二十四孝好秘书。\n书中年会当天，原剧情会发生孟静下药剧情。\n等等！明明没下药怎么还是被男主压在身下了？\n孟静吓得赶紧提前跑路，却不想被从不失控的男主给彻底盯上了。\n不是说性冷淡吗？怎么一夜七次啊！\n-\n千等万等，终于等到女主高调回国，孟静立刻跑路，在自己的小店喜滋滋的数着卡里的余额，幻想今后夜夜笙歌男模不重样的日子时，被男主堵住了。\n孟静：“你今天不是结婚吗？”\n裴淮京冷笑：“新娘跑路了，我结哪门子婚？”\n人都知道裴淮京最护短，裴淮京也乐意护着孟静，他怜惜她年纪小，格外纵容些。\n即使她多次骗他奢侈品去折现。\n裴淮京：为什么不骗别人只骗我呢？嗯，她爱",
    "creationStatus": 0,
    "wordNumber": 237479,
    "tags": [
      "豪门总裁",
      "现代言情",
      "腹黑",
      "穿书",
      "大佬",
      "位尊权重"
    ]
  },
  "7628290342059527193": {
    "bookId": "7628290342059527193",
    "bookName": "二少爷，你养的娇气包她又哭了",
    "authorName": "空白格777",
    "abstract": "慵懒痞帅退伍特种兵豪门少爷vs听话傻白甜千金小姐\n八年前，京家二少爷考上军校离开了京畿市，按他的要求，从此变成了失踪人口。\n京家三个孩子只有一个不姓京，这位二少爷便是了，他随母亲姓蓝，名京。\n八年后，七月盛夏的某一天，是顾家千金顾蔓依和江家独子江怀忘的婚礼。\n风莱作为顾蔓依的闺蜜兼妹妹被邀请当伴娘。\n“哎，惜惜你可算回来了，快帮我拉一下拉链，这裙子跟我有仇。”\n男人轻笑一声走过去替她拉好了拉链。\n指尖不经意间划过她细嫩的背。\n风莱猛地回过头，一脸不可置信，“蓝，蓝京哥哥，真的是你，你还活着…”\n“怎么？京家给我发丧了？”\n他曾经说过，如果回来，就不会再走了。\n那时候所有人都没有多想过他这句话是什么意思。\n八年后，他回来了，回家的第一天便提出想联姻。\n全家人一脸不可置信:我们京家的二少爷需要联姻？\n京家人懒得搭理蓝京这病娇患者，爱干嘛干嘛吧。\n蓝京说自己被迫退伍，没有收入没有工作，需要个有钱有势的太太，那么风莱，正合适！\n有天，风莱一脸不解，“为什么退伍，那不是你的梦想吗？”\n“嗯，个子太高，开不了战斗机没意思。”\n“那你干点什么工作行？”\n“开你行！”\n【梦想和你，我都要！】",
    "creationStatus": 1,
    "wordNumber": 200112,
    "tags": [
      "豪门总裁",
      "现代言情",
      "总裁",
      "病娇",
      "豪门世家",
      "久别重逢"
    ]
  },
  "7620996087670639641": {
    "bookId": "7620996087670639641",
    "bookName": "我老婆身娇体弱，得宠着",
    "authorName": "执笔其夭",
    "abstract": "[病弱清冷女主*好人男主]\n分低，待涨ing\n（双洁，偏温馨向细水长流小甜文）\n秦婳跳江自杀了，但没死成，她被贺闻舟救了下来。\n贺闻舟是一个刚破产的总裁，为了五千块的见义勇为奖，他救了一个跳江自杀的女人。\n但那女人醒来后张嘴就对他喊老公。\n起初的贺闻舟觉得秦婳是个神经病，嗤笑道：“跳个江把脑子跳没了？”\n后来，贺闻舟觉得有个老婆也不错。\n再后来，他蹲在秦婳面前轻声哄着：“乖乖，你别生我气了好不好？”\n……\n燕州所有人都知道，那位商界新贵贺闻舟又重新回来了。\n跟以往不同的是，他身边多了一位夫人。\n夫人身娇体弱，三步一咳，五步一喘，常常需要拿药娇养着。\n而那位从不信佛的贺总开始常常出入寺院，跪在地上请求上苍护佑夫人安康。\n……\n起初，贺总觉得他家乖乖无父无母，是个需要他宠着的小可怜。\n后来，他被绑架时，他看到他那身娇体弱的老婆一人单挑数十人来到他面前，看向对面，嗓音低冷：“你算个什么东西？”\n第二天，贺总从新闻上看到了他对家破产的消息。\n贺总后知后觉，他老婆好像才是那个霸总。\n再后来，贺总努力保持着微笑：“不是小可怜吗？你怎么是秦家掌权人啊。”",
    "creationStatus": 0,
    "wordNumber": 280752,
    "tags": [
      "豪门总裁",
      "现代言情",
      "总裁",
      "宠妻",
      "大佬",
      "双洁"
    ]
  },
  "7628523770336005144": {
    "bookId": "7628523770336005144",
    "bookName": "姐姐逃婚，姐夫点名要我替嫁",
    "authorName": "作风优良",
    "abstract": "【先婚后爱+替嫁成真+前期纯爱+中期疯批强制爱+后期心机勾引+双向奔赴】\n➕正经文写得好累，下次要写本不正经的奖励自己！\n　　崔书宁是崔家最不起眼的二女儿，从小被丢在乡下。\n\n　　回京后住在佣人房隔壁，穿姐姐的旧衣服，不小心咳嗽一声都要被骂上不得台面。\n\n　　父母偏心姐姐，全家视她为仇敌，她唯一的念想，就是守住姨奶奶的小院，传承那门濒临失传的手艺。\n\n　　姐姐崔书意攀上京市第一掌权人许韩谦，大婚当日却逃婚，只为逼新郎追妻拿捏许韩谦。\n\n　　全场哗然之际，冷漠寡言的许少抬眼，直指角落里的伴娘崔书宁：“换她，婚礼照常。”\n\n　　崔家父母慌不择路，拿她竹叶村房产要挟，逼她顶替姐姐，她战战兢兢替嫁，以为只是临时替身，等待自己的会是无尽的磋磨与报复。\n\n　　却不想新婚夜被男人彻底标记，次日便领了结婚证。\n\n　　崔书宁揣着惶恐度日，随时等着被抛弃。\n结果！\n传闻中冷漠暴戾，不近人情的许韩谦！\n“宝宝，怎么还不开始……”\n“宁宁，用力……”\n“许太太，你可以随便惩罚我……”\n崔书宁拉过眼尾泛红的男人！\n“许韩谦，不许哭……”\n\n　许韩谦治愈崔书宁的苦难，崔书宁温暖许韩谦的余生。",
    "creationStatus": 0,
    "wordNumber": 229496,
    "tags": [
      "豪门总裁",
      "现代言情",
      "先婚后爱",
      "双向奔赴",
      "位尊权重",
      "代嫁代娶"
    ]
  },
  "7625541158973754393": {
    "bookId": "7625541158973754393",
    "bookName": "别叫大哥",
    "authorName": "什洛娘",
    "abstract": "刚开分  所以评分低   保证刺激\n【纯洁女大学生X阴狠年上大哥】\n【强取豪夺】\n--\n许樱桃出身贫寒，唯一拿得出手的，就是交了个豪门男友。\n男友带她回去见家中大哥，好消息是，男方大哥看上了她。\n可也有坏消息———\n男方大哥不仅看上了她，还要抢她。\n",
    "creationStatus": 0,
    "wordNumber": 246523,
    "tags": [
      "豪门总裁",
      "现代言情",
      "总裁",
      "豪门世家",
      "年龄差"
    ]
  },
  "7547958547397495832": {
    "bookId": "7547958547397495832",
    "bookName": "穿越七零！这些香江大佬都有病？",
    "authorName": "森栖燃",
    "abstract": "刚开评分，所以低。\n年上，狼狗，疯狗…强取豪夺，平行位面勿代入现实。\n女主不爱任何男人，只爱国（万人迷女主）狗血\n杜依只是一个平平无奇的富二代，连看小说都只看大女主无CP的。\n只想着不恋爱不结婚，姐要一直独美，哪想一朝穿越到了70年代的港城。\n穿越前：坚定的女权拥护者，就爱在网络上和各路人马互喷。\n穿越后：被各路大佬强取豪夺的小可怜，急需祖国妈妈来打黑除恶…\n在这个鱼龙混杂的年代，这群金字塔尖的大佬，她一个都惹不起，为了远离这群神经病，她只好咬咬牙，装乖、扮弱，瞅准机会跑。\n顶级雄竞修罗场。",
    "creationStatus": 1,
    "wordNumber": 282217,
    "tags": [
      "豪门总裁",
      "现代言情",
      "总裁",
      "穿越",
      "豪门世家",
      "大佬"
    ]
  },
  "7654742513151921177": {
    "bookId": "7654742513151921177",
    "bookName": "温夜潮湿",
    "authorName": "暴富小玲",
    "abstract": "【心机男主诱骗女宝一晌贪欢的故事】\n【双洁+甜宠+一见钟情强制爱+上位者当狗又挣又抢】\n【娇软好欺乖乖女vs腹黑心机太子爷】\n温薏生在一个高知家庭里，父母都是知名教授。\n她是父母长辈眼中的乖乖女，从小到大，几乎从不忤逆父母的想法，父母给她安排联姻，她也乖乖接受。\n直到有一天，喝醉酒的她被闺蜜不小心送到她大哥床上，她的人生，发生了天翻地覆的变化……\n一夜疯狂，温薏醒来时，看到跟闺蜜大哥躺在一张床上，彻底傻了。\n怕被要求负责，她连忙逃走，却不想这男人不仅是她闺蜜大哥，还是她顶头上司。\n隔天就被他叫到办公室，顶着一张祸国殃民的俊脸，对着她笑。\n“温小姐，上了我的床就跑，胆子挺大。”\n她只想把这件事当做一场意外，不负责不追究，可男人并不允许。\n某天深夜，他把她抵在闺房里，薄唇贴着她耳朵咬。\n“乖，再来一次。”\n“放心，我不会让你未婚夫知道。”\n她一时糊涂，被男人得逞了一次又一次，直到再也无法摆脱他……\n韩沐宸，京圈顶级豪门太子爷，毒舌又不近人情，从前清心寡欲的他，因为一次意外，跟亲妹妹的闺蜜一夜贪欢，从此一发不可收。\n亲妹说她有未婚夫，让他别痴心妄想。\n他嗤笑一声，有未婚夫又怎么了，抢过来就是",
    "creationStatus": 1,
    "wordNumber": 146152,
    "tags": [
      "豪门总裁",
      "现代言情",
      "腹黑",
      "甜宠",
      "一见钟情",
      "双洁"
    ]
  },
  "7640366369896156185": {
    "bookId": "7640366369896156185",
    "bookName": "财阀继承人的古董女友",
    "authorName": "二月的大白",
    "abstract": "思想传统才华横溢的江南冰美人VS占有欲极强的财阀继承人\n江南世家嫡女沈词自幼体弱多病，从未踏出过沈宅大门。二十多年的人生，她见过的郎中比见过的外男还要多。\n生命结束后，再醒来时，她穿进话本子里，成了书中那个冒领女主救命之恩、用恩情绑架男主成为自己男朋友的恶毒女配。\n话本子中，原主为了真正上位，无数次作妖，最终落得被退学、父亲生意破产的凄惨下场。\n沈词决定：先稳住男主，不作妖，不争不抢，安静当背景板。等男主主动提分手，等书中真正的女主出现，她就能脱身离开，在这个新世界安安静静地活下去。\n她太擅长等待了。她在深宅大院里等了二十多年，最不缺的就是耐心。\n然而，当书中的真女主终于出现，沈词觉得时机成熟，忍不住小心翼翼地提出了分手。\n房间里，男主喘息着将她死死抵在墙边，眼底翻涌着令人心惊的暗潮，声音沙哑而危险：\n“还敢提分手吗？”\n也是在这一日，沈词与半疯的男主，差点儿无媒而合。\n沈词这才惊恐地意识到——\n她等来的不是解脱。\n而是一个疯子彻底撕开伪装的时刻。",
    "creationStatus": 1,
    "wordNumber": 189547,
    "tags": [
      "青春甜宠",
      "现代言情",
      "总裁",
      "穿越",
      "大佬",
      "位尊权重"
    ]
  },
  "7600899075172486168": {
    "bookId": "7600899075172486168",
    "bookName": "盛夏青苹果",
    "authorName": "桃气乌龙正常糖",
    "abstract": "【校园+借住+双学霸+男暗恋+超绝纯爱】\n在学校里，池遂和季溪闻有着云泥之别。\n他是众人口中的风云人物，年级大榜前三的常客，理科竞赛的种子选手，人缘奇好，一张堪比顶流明星的帅脸更让无数女生趋之若鹜。\n而季溪闻是个不起眼的转校生。\n沉默寡言，穿着廉价的衣服，厚重的刘海遮住了脸。\n在班里默默无闻。\n……\n没人知道。\n每周五晚上，他们都会回到同一个家。\n-\n第一次见到季溪闻，大少爷只看一眼兴致缺缺收回视线。\n并且约法三章。\n1.在学校里不准说我们住在一起\n2.不准跟我打招呼\n3.不要把我的事情告诉家里人\n季溪闻点头应好。\n-\n后来发现有人往季溪闻书里塞情书的时候。\n池遂气急败坏。\n把人堵在家里，警告道：“我家不能早恋，不然我就……”\n季溪闻抿着唇看他：“就什么？”\n对上少女清亮的眼眸，他垂下头无可奈何。\n“我会难过的。”\n—\n暗恋是一颗酸涩青苹果\n天之骄子也会尝到自卑\n*\n超绝钝感学霸软妹vs烂脾气嘴硬混球\n一个猴儿一个拴法ᥫᩣᵕ̈",
    "creationStatus": 1,
    "wordNumber": 255405,
    "tags": [
      "青春甜宠",
      "现代言情",
      "校园",
      "总裁",
      "学霸",
      "暗恋"
    ]
  },
  "7636603807224302617": {
    "bookId": "7636603807224302617",
    "bookName": "在帅哥评论区口嗨掉马后",
    "authorName": "暗中讨饭的三三",
    "abstract": "【外纯内黄  X 冷拽爹系】\n\n林雪纯喜欢在帅哥评论区口嗨。\n最近她盯上了一个抖音博主，ID叫ksmk123。\n对方188、冷白皮、薄肌男。\n精准踩在她审美点上。\n借着网络掩护，她在对方私信里肆无忌惮——\n\n【想看哥哥腹肌。】\n【哇，屁股好翘。】\n【我发现哥哥锁骨下面有颗痣，对了，说到下面……】\n\n奇怪的是，对方似乎并不排斥。\n她要看什么，他就发什么。\n聊天尺度越来越大。\n\n直到她的手机进水送去维修。\n第二天，聊天记录被人挂在校内墙上——\n《惊！传媒学院林XX表面清纯女神，实则在网上跟男人各种撩骚》。\n全校炸裂！\n林雪纯被舆论淹没。\n就在此时，从不发朋友圈的校草郗辰洲破天荒地更新了一条动态：\n“我女朋友跟我的小情趣。有问题？”\n配图是ksmk123的抖音个人主页截图。\n全校再次炸裂！\n\n林雪纯整个人都懵了。\n她每天口嗨的博主竟、竟然是校草郗辰洲？\n救命！\n她羞耻到只想跑路。\n却被某人堵在宿舍门口。\n“宝宝，跑什么？”\n“不是想摸我腹肌，给你摸。”",
    "creationStatus": 1,
    "wordNumber": 245486,
    "tags": [
      "青春甜宠",
      "现代言情",
      "校园"
    ]
  },
  "7646809685168770110": {
    "bookId": "7646809685168770110",
    "bookName": "泥珠",
    "authorName": "毛豆佛爷",
    "abstract": "【木讷自卑山里女孩 x 天龙人坏种少爷】\nㅤ\n虞盼娣十三岁那年，被父母以十万块“托付”给越家。\n越间彻给她改名虞珠。他说是稀世珍珠的珠，心里想的却是蠢笨如猪的猪。ㅤㅤ\n她是秦岭深处来的脏旧山月，沉默、木讷、自卑，从不敢伸手要任何东西。\n他是长安城里养出的漂亮恶犬，温和、矜贵、卑劣、虚伪，施舍和羞辱都像恩赐。\nㅤ\n小时候的虞珠以为，越间彻是天降的神祇，是拯救她的厄尔庇斯。\n长大后她才慢慢发现，他不是希望，是专职毁灭的珀耳塞斯。\n\n*\n注：男主纯坏种，虚伪恶劣且不洁。\n无大纲无存稿，不保证任何剧情走向。\n强取豪夺 / 追妻火葬场 / 烂人真心 / 年龄差 / 不洗白",
    "creationStatus": 1,
    "wordNumber": 238171,
    "tags": [
      "青春甜宠",
      "现代言情",
      "校园",
      "总裁",
      "虐恋情深",
      "追妻火葬场",
      "年龄差"
    ]
  },
  "7636730881519914046": {
    "bookId": "7636730881519914046",
    "bookName": "弟弟用我照片，网恋疯批太子爷",
    "authorName": "莫小兮",
    "abstract": "【网骗掉马+微强制爱+甜宠+双洁】乖乖女重生变坏VS疯批混血天龙人\n上一世，乔书棠的弟弟用她照片网恋，噢不，是网骗，异国财阀继承人凌珩，不曾想对方是个疯批天龙人。掉马后，被他报复性羞辱导致抑郁跳楼。\n在弟弟葬礼上偶遇，乔书棠被凌珩带车队围追堵截，慌乱间把车开进江里……\n重生归来，乔书棠费尽心思改写姐弟命运。\n不就是介意人妖骗感情吗？我顶替弟弟亲自跟你网恋。\n不就是假扮高中生吗？谁还不会装嫩呢？\n不就是花了你几百万吗？等我攒够了钱还你就分手。\n乔书棠自以为马甲捂得很好，直到某天，远在异国的他闪现在她大学宿舍楼下。\n蓝宝石般的眸中只有她：“小骗子，骗我一辈子好不好？”\n乔书棠知道他是人前君子人后疯子，哪敢答应？\n嘴上说好，见机逃跑。\n太子爷疯了般找她，终于成功堵到她。\n不可一世的贵公子低下头，眼尾猩红：“老婆，你不能对我…始乱终弃！”\n乔书棠步步后退：“凌珩，你知道的，我是骗子，我不爱你。”\n他弯唇浅笑：“骗人很费脑细胞的，你为我消耗掉的上亿个脑细胞，都是你爱我的证明！”",
    "creationStatus": 1,
    "wordNumber": 205535,
    "tags": [
      "青春甜宠",
      "现代言情",
      "重生",
      "学霸",
      "甜宠",
      "双洁"
    ]
  },
  "7602919905331006489": {
    "bookId": "7602919905331006489",
    "bookName": "【普女】：我怎么会喜欢她！",
    "authorName": "僵尸开会",
    "abstract": "社恐透明老实人vs各种类型阴湿男\n—\n村里发生了丑闻。暑假时候，马上上五年级江上被迫转学到另一个城市，和爸妈住在城中村的月租房里。\n—\n柯青是她在这里认识的第一个朋友。他皮肤白得近乎病态，身形瘦削得厉害，嘴唇薄而淡，一双眼眶大得突兀，眼珠子却十分的小。\n起初柯青垂着脖颈坐在门口打游戏，全然不理她。她说话说多了，他那双漆黑无机质瞳孔会一点点左移，再慢吞吞抬起，落在她身上，盯——。他想开口要她不要说话，又觉得说话很麻烦，所以脸上非常的纠结。最后，他怕麻烦的没有说话。\n后面，江上在柯青一脸你好烦啊时，冲他一笑。他睫毛轻颤，眼神飘忽落到游戏上。过了几分钟，声音没有情绪含糊道：“江上是笨蛋。”\n—\n转学第一天见到了王林。他眉眼生得明亮，眼型偏圆，一笑弯成月牙，像是天生被太阳偏爱的人。\n她是班里透明边缘人，而王林人缘好到爆，所以他们没有任何的交集。\n……\n张方七靠着江上打游戏。\n远处，身旁李嘉豪问道：“王林，你在看什么？”\n—\n张方七高一转过来，一个超级富二代。原本与她毫无交集，不过一次换座成为同桌后，一切变的不一样。\n“你表情和黄漫上一样色色。”\n“我们试试接吻吧，我真的超想知道这是什么滋味。”",
    "creationStatus": 1,
    "wordNumber": 230774,
    "tags": [
      "青春甜宠",
      "现代言情",
      "校园",
      "学霸",
      "第一人称"
    ]
  },
  "7585498354692394046": {
    "bookId": "7585498354692394046",
    "bookName": "我刻薄不是装的",
    "authorName": "熊猫的珍珠",
    "abstract": "那咋了？喜欢我的人只会觉得我在撒娇。\n-\n【贵族学院+都市】【恶女万人迷】【1v1】【雄竞】【轻松沙雕】\n－\n前世，恶女乔映只是因为嘴损，就被团宠文女主给宰了。\n重生后，乔映反思，觉得还是要有点恶毒手腕，这样才能保护这张好嘴。\n最好的防守就是进攻，所以这一次她把女主的舔狗们全给阴了。\n－\n钟树白这人是个冷脸萌。\n乔映亲他，他只会哼哼一声，说乔映是个坏女人。\n身为男主之一，钟树白没有走上既定的路线被攻略。\n而是在乔映破产后，豢养了她这只美丽的金丝雀。\n不过乔映实在不省心，一个没看住，就被弄死了。\n钟树白坐在凌晨的客厅，开酒刀割破手腕，随她而去。\n－\n既然老公迟早是我的，为什么不能现在就是我的？\n乔映猛追十七岁的钟树白。\n少年抗拒，结果一张嘴。\n“姐姐”两个字脱口而出。\n乔映已被萌晕。",
    "creationStatus": 1,
    "wordNumber": 298380,
    "tags": [
      "青春甜宠",
      "现代言情",
      "校园",
      "重生",
      "搞笑轻松",
      "1v1"
    ]
  },
  "7596380175122566168": {
    "bookId": "7596380175122566168",
    "bookName": "玩弄感情的漂亮妹宝是要被狠狠",
    "authorName": "为什么我像只小猫",
    "abstract": "【万人迷/1vn/训狗/游戏网恋/雄竞修罗场/土土土玛丽苏】\n虞怜的人生除了脸蛋漂亮，没有任何闪光点。\n性格更是一塌糊涂。自私任性软弱懒惰放纵，而且，贪婪。\n想要钱，想上分，享受被追逐被宠爱。对真心爱她的人招之即来挥之即去。\n如果她幸福的话，谁痛苦都没关系。\n—\n宝宝，你说会改，怎么改的是密码> <\n玩弄感情还要嘴硬的小宝宝是注定了要被老公们强制爱的。\n\n阅前排雷：\n1.女主0素质0道德，纯血网络女神，会有网恋圈钱、出g、聊s、快餐恋爱、多线程暧昧、玩弄感情、网络喷子、各种歧视等行为。读者宝宝不可以模仿学习。\n2.会有很多狗男坏男剑男出没，没有完美角色，只能保证主要角色洁，略墙纸爱。\n3.不是大女主。女弱。女嬷。凝女。\n4.本人xp之作，阅读过程中如有任何引起不适的情节请马上停止观看，双向选择。\n\n坏狗集合中（包括但不仅限于）：\n小三上位现任✓\n毒舌冷脸哥✓\n阴湿恨嫁男前任✓\n农村厂弟男闺蜜✓\n萌脸烧男高✓\n偶像剧男主学长✓",
    "creationStatus": 1,
    "wordNumber": 197589,
    "tags": [
      "青春甜宠",
      "现代言情"
    ]
  },
  "7645909593159126078": {
    "bookId": "7645909593159126078",
    "bookName": "萌脸烧冒替姐姐网恋后，夜夜腿软",
    "authorName": "桑易易",
    "abstract": "【萌脸撩人精+混血财阀少爷+双洁+歌姬】熬一通宵醒来，俞知楠发现自己竟成了书中恶毒拜金女配！天塌了！\n女配读着一所不入流大学，专门在网上勾搭有钱男人骗钱，女主姐姐则是从小被豪门抱养的名校校花。\n并且姐姐网恋的对象还是顶级财阀继承者谢昼川。\n女配知道后羡慕嫉妒恨，硬逼姐姐将人账号让给她谈，否则就自杀。\n但女配撩了谢昼川半年了对方都只转钱不谈情，于是女配等他回国与一群混混合伙对他下药生米煮成熟饭，结果将人彻底惹怒。\n最后身败名裂惨死狱中。\n穿来的俞知楠一抬眼，正好看到手机里女配发的骚扰消息“哥哥，要视频看tui照吗”，瞬间冒出一身冷汗。　\n【能……能分、分个手吗？】\n【转帐+100000。收了钱就不认人是吧？】\n想到原主下场，她打了个哆嗦，害怕会被报复，只能逼他先分！\n她想尽了各种恶心人的网恋招数。\n她心想，他肯定恶心坏了吧。\n谢昼川：我媳妇儿原来是萌脸烧啊！\n　——\n谁也不知道为了甩掉网恋对象，俞知楠有多努力。\n掉马后，谢昼川看着被游戏网坛以及COSER界疯狂追捧的女人，某平台现象级火爆歌姬，直接气笑。“俞知楠，敢玩我？给你两个选择，乖乖过来亲我，或者……被我往死里亲。”",
    "creationStatus": 1,
    "wordNumber": 181101,
    "tags": [
      "青春甜宠",
      "现代言情",
      "校园",
      "总裁",
      "穿越",
      "双洁"
    ]
  },
  "7640429134237142041": {
    "bookId": "7640429134237142041",
    "bookName": "漂亮女配觉醒，高冷校草后悔了",
    "authorName": "月野山狐",
    "abstract": "【重生大学校园｜竹马男二上位｜男主火葬场】\n重生后，沈雨棠才知道，原来她是校园文里漂亮的恶毒女配。\n上一世，她身为千金大小姐，卑微追求穷小子傅寒生，掏心掏肺对他好，花钱给他买衣服，花钱为他奶奶治病，砸光手里的金钱捧他成为科技新贵。\n傅寒生却始终熟视无睹，对她冷淡如冰。\n这一世，她不追了！\n起初傅寒生毫不在乎，只用八个字点评她的行为：“欲擒故纵，自作多情。”\n后来，傅寒生眼睛通红，卑微地冲到沈雨棠家拍门，“沈雨棠，你跟他在一起了？你不是喜欢我吗？”\n哪料，开门的竟是桀骜太子爷贺烬，男人唇部带着吻痕，嘲讽地笑：\n“找我女朋友，你欠揍啊？”\n-\n沈雨棠从小有个跟她作对的竹马——贺烬。\n曾经，贺烬看着她追求傅寒生，冷声嘲讽：“眼睛瞎了，脑子抽了。”\n后来，贺烬紧紧搂着她的腰，低声哄道：“小公主，再亲我一口，嗯？”\n-\n【我一直在等，等你的目光落在我身上】",
    "creationStatus": 1,
    "wordNumber": 214784,
    "tags": [
      "青春甜宠",
      "现代言情",
      "重生",
      "青梅竹马",
      "追妻火葬场",
      "男二上位"
    ]
  },
  "7643333397640662040": {
    "bookId": "7643333397640662040",
    "bookName": "网恋对象居然是军训总教官",
    "authorName": "南亭北苑",
    "abstract": "京北附中的许南音，高三那年干过一件荒唐事——她网恋了。\n对象是个兵哥哥，25岁，人在外地。\n她以为这辈子都不会见到他，所以用的是真名。\n\n临近高考，她干脆利落地提了分手，拉黑删除，头也没回。\n\n三个月后，她站在京北大学的操场上。\n军训总教官的声音从头顶落下来：\n“许南音，京北附中许南音？”\n\n她抬起头，看到了那张她以为永远不会见到的脸。\n\n后来的每一天，陆知言都在用行动告诉她一件事——\n她随手丢掉的那段关系，他从来就没打算放手。",
    "creationStatus": 1,
    "wordNumber": 167365,
    "tags": [
      "青春甜宠",
      "现代言情",
      "校园",
      "年龄差"
    ]
  },
  "7616213056187550744": {
    "bookId": "7616213056187550744",
    "bookName": "宝宝乖，轻点撩",
    "authorName": "陈一诚",
    "abstract": "【大学校园➕破镜重圆➕男小三上位➕强制爱➕1v1双洁➕双向救赎】\n【温软坚韧乖乖女✖️冷拽坏种大少爷】\n谢京辞生了副好皮囊，中美混血，家世显赫，17岁拿下F1车赛冠军，天之骄子又恶劣至极。\n身边从不缺女人爱慕倾佩，可他却偏偏只跟在对他爱答不理的乖乖女身后，求夸、求哄、求亲亲。\n“为什么总躲我？乖宝，我长得很吓人吗？”\n-\n性格张扬不羁的他第一次这样纯情卑微求爱，却不料直接被人断崖式分手。\n再次重逢是在订婚宴上，初恋成了别人的未婚妻。\n可谢京辞不在乎。\n他淡蓝色的眸子充斥着惊喜和玩味，依旧张扬不驯又危险诱人：\n“宝贝，终于让我抓到你了。”\n他想，要怎么惩罚这个对他始乱终弃的坏女人才好？\n心里恨，可转身对上那心心念念的脸时，他又再次跪在裙边乖乖求爱。\n“乖宝宝，再亲亲我……”\n-\n温以蓁长了张清冷白月光的脸，性子孤傲内敛。\n所有人都说她玩不过这位恶少爷谢京辞。\n直到校表白墙一则视频流出——\n谢京辞半跪在地上，紧紧握着温以蓁的手，抬起一双泛红的眸子哀求：\n“宝宝，当小三我也愿意，求你不要不理我……”\n“求你利用我，让我成为你的底气。”",
    "creationStatus": 0,
    "wordNumber": 269273,
    "tags": [
      "青春甜宠",
      "豪门世家",
      "独宠",
      "破镜重圆",
      "校园",
      "位尊权重"
    ]
  },
  "7639342241709820952": {
    "bookId": "7639342241709820952",
    "bookName": "贵族学院：小傻子也有修罗场吗？",
    "authorName": "三文鱼爆炒鸡米花",
    "abstract": "【1vN雄竞修罗场+团宠+小傻子女主+全员真香+强制爱】\n_\n方青梨是洛斯特这所贵族学院里任人欺负的小傻子特招生。\n为了不被欺负，她找上了学院的S级学生傅景川。\n她举着皱巴巴的一团零钱，问：“你可不可以做我的老大呀？”\n可是这个老大怪怪的，得天天给他啃嘴巴。\n小傻子没听说过这个规矩，但还是乖乖凑上嘴巴给他啃。\n老大还说了，只有他一个人能啃她嘴巴。\n_\n可是后来，啃她嘴巴的人越来越多了。\n下城区的恶犬咬破她的嘴唇：不想被你老大发现就乖乖听我的话。\n白切黑医学生：小青梨，我可以和你接吻吗？\n看不上她的家族掌权人：我也想尝尝。\n_\n傅景川原本只是养个傻子玩玩而已，没想到却动了真心。\n意识到感情以后他也不委屈自己，连哄带骗把人哄成了自己的女朋友。\n可他发现，身边多了些上不得台面的小三小四。\n傅少打小三最狠了，来一个打一个。\n打着打着发现不对劲。\n“……哥，怎么你也有份？”\n后来看着眼前四个男人，恢复智力的方青梨有些招架不住了。\n她拿着他们给的零花钱，连夜跑路。\n结果还没跑出多远，就被几个人一起逮了回来。\n“这么狠心？扔下我们就跑了？”\n“不该补偿一下吗？”",
    "creationStatus": 1,
    "wordNumber": 282386,
    "tags": [
      "青春甜宠",
      "现代言情",
      "校园",
      "总裁",
      "团宠",
      "豪门世家"
    ]
  },
  "7631890148384328729": {
    "bookId": "7631890148384328729",
    "bookName": "港城小甜梨",
    "authorName": "桐月安歌",
    "abstract": "十七年讨好换不来养母一丝温柔，只因她并非亲生。\n\n被北城白家接走后，缺爱小可怜直接解锁豪门全员团宠。\n\n亲爹护短，三位堂哥撑腰。\n\n还有那位少年，正一步一步靠近她。\n\n白梨被一整个家族狠狠偏爱。\n\n【轻松搞笑+豪门团宠+慢热治愈+微群像】",
    "creationStatus": 1,
    "wordNumber": 142912,
    "tags": [
      "青春甜宠",
      "现代言情",
      "学霸",
      "团宠",
      "搞笑轻松",
      "群像"
    ]
  },
  "7628786824386710553": {
    "bookId": "7628786824386710553",
    "bookName": "用我照片网恋，抢你男友怎么了",
    "authorName": "富贵养乐多",
    "abstract": "【刚开分，会涨】\n漂亮钓系老实人妹宝vs高冷闷骚狐狸太子爷\n【觉醒+网恋+掉马+钓而不自知女主+看似高冷实则恋爱脑男主+真香】\n苏云汀觉醒了。\n原来她是一本网恋文中的炮灰女配。\n女主用她的照片网恋养鱼，大捞特捞，事情败露后，疯狂甩锅。\n双闪一打，不是我，是苏云汀！\n苏云汀替她背了锅，被谩骂，被霸凌，被退学，最后以诈骗罪进去踩缝纫机了。\n为了摆脱惨烈的结局，一向老实乖巧的苏云汀做了一个大胆的决定。\n既然你用我照片网恋，那我抢你男友怎么了。\n冒用女主身份和男主网恋：“你好，我是你女朋友。”\n只要度过原文剧情点，她就安全了。\n———\n一天，苏云汀看到沈聿礼和女主站在一起。\n女主：“我才是你的网恋女友，苏云汀她就是个骗子！”\n苏云汀浑身一冷，脑子里面警铃大作。\n完蛋了！\n害怕男主报复自己，立马收拾东西跑路。\n没想到直接被逮住。\n沈聿礼将人揽住腰，眸色幽深：“女朋友，跑什么？”\n苏云汀心如死灰，瑟瑟发抖的开口：“你要是想分手的话……”\n沈聿礼气急，不想再听到让人心梗的话，凶狠的堵住了她的嘴。\n骗了我就说对不起，说分手干什么！\n我又没说不原谅。",
    "creationStatus": 1,
    "wordNumber": 213837,
    "tags": [
      "青春甜宠",
      "现代言情",
      "豪门世家",
      "腹黑",
      "甜宠",
      "双洁"
    ]
  },
  "7633235109344201753": {
    "bookId": "7633235109344201753",
    "bookName": "乖乖女网恋，被京圈太子爷亲懵了",
    "authorName": "京九只",
    "abstract": "［内心叛逆乖乖女 vs 纯爱太子爷+1v1救赎+甜宠］\n沈知意是出了名的乖乖女。\n不迟到，不喝酒，不晚归，不顶嘴。\n\n可没人知道，她活在两个世界——\n白天是父亲手里的提线木偶，晚上是网恋对象嘴里的宝宝。\n“宝宝，腿露出来给哥哥看看。”\n“宝宝，想你想得睡不着。”\n“宝宝，乖，叫一声。”\n\n为了反抗父亲安排的相亲，她在一个APP上下单——“找个最不好惹的人，假扮我男朋友，气死我爸。”\n接单的人叫谢京臣，长得极具攻击性，眉眼冷戾，开口更欠：\n“什么都没干，别指望我态度好。”\n“你想怎么气你爸？打左脸还是右脸？”\n\n后来她爸查了谢京臣的家底，脸绿了——\n这个男人竟是京市首富，资产比他多好多个零！\n\n但她更想不到的是：\n那个每晚在手机里哄她睡觉、喊她“宝宝”的网恋对象……\n和眼前这个蹲下来给她系鞋带的男人，竟然是同一个人。　　\n\n“宝宝，”男人将她抵在墙角，捏住她的下巴，拇指轻轻蹭过她唇边：“现在知道我是谁了，还跑吗？”\n她声音发飘，眼尾泛红：“是你？”\n“嗯，是我，那个说想*你的人”",
    "creationStatus": 1,
    "wordNumber": 206062,
    "tags": [
      "青春甜宠",
      "现代言情",
      "位尊权重",
      "甜宠",
      "1v1",
      "校园",
      "双向奔赴"
    ]
  },
  "7639375832493853720": {
    "bookId": "7639375832493853720",
    "bookName": "重生后，冷拽死对头被我亲爽了",
    "authorName": "青芋酥",
    "abstract": "评分刚出，后期会涨，宝宝们不要被吓到(^з^)-☆\n【明媚小仙女X冷拽太子爷丨大学校园+同居+系统+死对头】\n卢筱筱在大四那年遭人毒害身亡。\n再睁眼，她重生到大一，还被迫绑定了系统。\n必须和死对头邵恩辞完成100件羞耻社死的任务，\n才能彻底复活。\n［任务1：篮球赛结束，当众强吻他。］\n卢筱筱：……老天奶为何如此整我！\n-\n邵恩辞，智商天花板，AI领域天才，家世显赫。\n191浓颜帅哥，薄肌冷白皮，爱滑板爱运动。\n高中起就是她的死对头，两人见面必掐。\n因为一条百科乌龙，众人都以为他们是一对。\n昨天她火速避嫌：“我谈百合都不会跟他有一腿。”\n没想到今天，众人便看见她在篮球场当众强吻他，\n并且嗲着嗓音说：“哥哥，你唇好甜。”\n众人傻眼：？\n-\n某晚卢筱筱为了完成任务，厚着脸皮住进他家里。\n偷看他洗澡，半夜爬上他的床，趁他睡觉摸他腹肌，\n这些邵恩辞都能忍。\n唯独接受不了她一个女孩子偷藏他裤衩这件事。\n急！暗恋对象成了变态怎么办？\n-\n后来兄弟邱柏野得知真相，提醒他：\n“她只是为了完成任务才接近你，你被骗财骗色了！”\n邵恩辞：“玩我都不介意了，还在乎被骗吗？”\n邱柏野：……哥们，你没救了。",
    "creationStatus": 1,
    "wordNumber": 234469,
    "tags": [
      "青春甜宠",
      "现代言情",
      "校园",
      "系统",
      "学霸",
      "暗恋"
    ]
  },
  "7477468603504135230": {
    "bookId": "7477468603504135230",
    "bookName": "杀死那个春夜",
    "authorName": "二水i",
    "abstract": "【酸涩救赎｜禁忌背德｜纯恨变纯爱｜对抗路｜校园微群像｜小镇｜1v1双洁】\n【白切黑装货✖️刺儿头犟种】\n起初，她讨厌他的虚情假意，他讨厌她的油盐不进。\n人前兄友妹恭，人后争锋相对。\n后来，假意里生出真心。\n他们攀附在彼此脆弱的脊背上生长，脚下的根系连理枝般盘根错节、纠缠不清。\n第二年春节。\n路朝在温迎的房间里步步紧逼。\n门外依稀传来春节联欢晚会热闹开播的声音，还有爸爸和许阿姨的笑声，温迎头皮发麻，手心燥热，盯着近在咫尺的少年，低声提醒：“他们就在外面。”\n路朝顽劣轻笑：“怕什么。”\n印象中，家里的电闸跳过两次。\n一次他们在打架，一次在接吻。\n*\n人总是会在年少时干出点惊天动地的事儿。\n赢下这场比赛，是她少女时代最伟大的英雄主义。\n“你每次嘴上说着远离我，眼睛里却全是救救我。”",
    "creationStatus": 0,
    "wordNumber": 291361,
    "tags": [
      "青春甜宠",
      "现代言情",
      "双洁",
      "1v1",
      "群像",
      "白切黑"
    ]
  },
  "7613572197243685950": {
    "bookId": "7613572197243685950",
    "bookName": "我，怂且恶毒",
    "authorName": "兔子好说话",
    "abstract": "【女主重生+男主系统】\n【怂且恶毒窝窝囊囊干坏事女主x口嫌体正直男妈妈男主】\n云落没想过她这种人还能重生。\n按理来说，她该下地狱的。\n为什么重生了\n还回到了高中。\n……高中确实挺像地狱的。\n_\n南宴没想过他还能绑定系统。\n系统说这世界其实是一本小说\n而你的任务是要感化恶毒女配。\n南宴：？\n_\n南宴：你说她是恶毒女配，怎么恶毒了？\n系统：呃……她把男主给阉了。\n南宴：？？？\n_\n南宴第一次见到云落是在一个雨天。\n她没带伞，蹲在路边，像只可怜兮兮的流浪猫。\n不像系统口中的恶毒女配\n对系统的质问还未说出口\n南宴就见她伸出腿绊倒一名路人后\n立马装作什么都不知道的表情无辜看向周围。\n南宴：……\n_\n刚开始的南宴：你让我去感化这玩意？？灵魂年龄都二十为什么还这么幼稚……\n后来的南宴：女大三抱金砖，女大四抱三分之四金砖。",
    "creationStatus": 0,
    "wordNumber": 213545,
    "tags": [
      "青春甜宠",
      "现代言情",
      "校园",
      "系统",
      "重生",
      "学霸"
    ]
  },
  "7633754783731420184": {
    "bookId": "7633754783731420184",
    "bookName": "海后日常崩大佬，手滑建了个群",
    "authorName": "君九如",
    "abstract": "【穿书+万人迷+强取豪夺+强制爱+多男主+男全洁+雄竞修罗场+1VN】\n【避雷：律师男主交往过女朋友，牵手拥抱过，非高洁】\n母单娇软小社恐苏星若穿成了同名同姓恶毒捞金海后。\n开局就是修罗场——鱼塘里的七个大佬被原主手抖拉进一个群。\n她反手拉了三百个好友进来发广告。\n本以为能安稳搞钱、和平分手、全身而退。\n可这几位怎么不按剧本走？\n——\n高冷律师似笑非笑：“趁我生病对我做了那种事，连哄也不愿意哄我？”\n野帅校草将她抵在黑暗的树林里：“若若，我不会让你吃醋，我只会喂你吃糖。”\n禁欲导师掐着她的腰，声音低哑：“形体课不是教过你吗？腰再放软一些。”\n就连那位从不见面的神秘榜一大哥，也忽然出现将她堵住。\n——\n她疯狂搞事业、拼命还钱，只想早日上岸。\n可他们一个个轮流上门，堵人、撒娇、放狠话，手段一个比一个疯。\n后来，她实在忍不住了：“钱还清了，咱们好聚好散行不行？”\n几个男人对视一眼，不约而同地笑了。\n“钱不要了。你，我们要定了。”\n爱一个人是藏不住的，爱七个人——还每个都是偏执大佬，那她必须得藏！藏得死死的！",
    "creationStatus": 1,
    "wordNumber": 262115,
    "tags": [
      "青春甜宠",
      "现代言情",
      "学霸",
      "穿书",
      "冰山",
      "律师"
    ]
  },
  "7655315504193621054": {
    "bookId": "7655315504193621054",
    "bookName": "缪斯要分手",
    "authorName": "阿唯",
    "abstract": "（评分刚出）\n毕业，分手，出国。\n经典情节永远是经典，但赵司程不吃这一套，不到一年就追去了纽约，找到沈加缪的第一句话就是，\n“复合，不然我闹给你看。”\n沈加缪妥协了，包吃包住有钱拿，不复合是傻子。\n可没过多久，她发现赵司程他丫的心眼子变多了，三句两句全是套路，不是套她结婚就是套她签卖身契，招架不住，真的招架不住。\n……\n【复合小剧场】\n“赵司程你直说吧，你想要什么，如果我能做到，我会答应。”\n“我要复合。”他面无表情。\n“……换一个。”\n“我要和好。”他满脸冰冷。\n“……不是让你换一个同义词。”\n“我要跟你重新开始。”\n沈加缪：……\n【复合小剧场2】\n赵司程：“复合。”\n沈加缪：“不。”\n赵司程：“理由。”\n沈加缪：“你妈给钱了。”\n赵司程沉默一瞬：“我出双倍。”\n沈加缪点开收款码：“扫吧。”\n【tips：微群像，会有少量Lesbian情节，很甜，也很虐，非爽文，绝对女主控慎入，慎入！不喜勿喷，（佛系鞠躬），感恩。】",
    "creationStatus": 1,
    "wordNumber": 186938,
    "tags": [
      "青春甜宠",
      "现代言情",
      "暗恋",
      "学霸",
      "追妻火葬场",
      "甜宠",
      "群像"
    ]
  },
  "7641086713061706776": {
    "bookId": "7641086713061706776",
    "bookName": "初遇盛夏里",
    "authorName": "一斤欠粉",
    "abstract": "【打直球明恋的男主×肤白貌美女主】\n　　【校园＋势均力敌＋双洁＋甜宠】\n　　北城一中转来一个新同学，长得肤白貌美，成绩还很好。\n　　一中的第一和第二万年不变，自从转学生来了之后两人被拉下神坛。\n　　后来有人起哄问两人看到成绩是什么心情呢。\n　　林耀南：【这我姐，厉害吧。】\n　　顾浔野：【挺骄傲的。】\n　　其他人：你有什么好骄傲的？\n　　再后来，顾浔野在朋友圈官宣：【第一名是她的，她是我的。】\n　　__________\n　　顾浔野，长相和成绩一样优秀，北城一中霸榜第一的男人，桀骜不驯的少年吸引了多少人的目光，他从未想过自己会对一个人一见钟情，那种感觉就像干涸的土地迎来了一场属于它独一无二的雨淋进了他的心里从此开始生根发芽。\n　　明初夏容貌出众成绩优异，高二转来北城一中，开学第一天课桌就被情书塞得满满的。\n　后来几人一起跨年的那天晚上，广场上时钟滴滴答答的声音混合着周围人倒数的声音\n人潮汹涌，控住不住的爱意，他弯腰轻轻靠近她的耳边轻声说了一句\n　　新年快乐，以及我喜欢你。\n　　我们在盛夏相遇，热恋却不止盛夏。",
    "creationStatus": 0,
    "wordNumber": 176768,
    "tags": [
      "青春甜宠",
      "现代言情",
      "校园",
      "甜宠",
      "一见钟情",
      "双洁"
    ]
  },
  "7646232020447677465": {
    "bookId": "7646232020447677465",
    "bookName": "【酸or涩】",
    "authorName": "周飒飒",
    "abstract": "沈清韵暗恋了盛司珩整整三年。\n她记得他考试时转笔的速度，记得他只喝冰美式不加糖，记得他对所有人都温柔有礼——却从不多看她一眼。\n她是年级第一的沉默学霸，他是万人迷校草。\n平行线不该有交集。\n所以她把秘密锁进日记本，一锁就是八年。\n再见面时，她是急诊科最冷静的住院医师，他是盛氏集团最年轻的掌门人。\n他变了，变得霸道、强势、步步紧逼。\n他没变，依然温柔、疏离、让人捉摸不透。\n原来双向暗恋，才是最甜的酸。",
    "creationStatus": 0,
    "wordNumber": 152205,
    "tags": [
      "青春甜宠",
      "现代言情",
      "学霸",
      "甜宠",
      "暗恋",
      "HE"
    ]
  },
  "7648715236710550552": {
    "bookId": "7648715236710550552",
    "bookName": "普女升级指南：拿下沪圈顶配",
    "authorName": "釒水",
    "abstract": "【 评分刚开~  钓系女主 + 阶段性1V1 + 女性成长史】\n从“普女”到沪圈第一太太。\n温妍这辈子只爱一样东西——钱。\n若自己拿不到足够多的，那就借别人的手。\n高考后的三个月把自己从头到脚打磨了一遍。\n从普通女孩，变成男人最“爱”的样子。\n多金贵公子的清纯初恋（双C）\n桀骜少年的温柔大姐姐(女非男C)\n顶级权贵的沪圈太太(女非男C)\n每上一级台阶，换一个并肩的人。\n一开始，她只要钱。\n再然后，她要事业。\n最后发现，她要的是金字塔尖的位子。\n钱是台阶，人是台阶，婚姻也是台阶。\n她要踩着所有能踩的东西，一步一步往上走。\n好风凭借力，送我至青云。\n 假白花真野心 / 成长型女主\n标签为系统动态生成，所有排雷以简介为主。\n（已详细标注）",
    "creationStatus": 1,
    "wordNumber": 244790,
    "tags": [
      "青春甜宠",
      "现代言情",
      "双洁",
      "1v1",
      "甜宠",
      "校园",
      "豪门世家"
    ]
  },
  "7637018189997542425": {
    "bookId": "7637018189997542425",
    "bookName": "贵族学院：吃瓜路人是万人迷",
    "authorName": "树上的咸鱼饼干",
    "abstract": "女主：伪路人·真玛丽苏万人迷·绑定吃瓜系统吃瓜人·天龙人·女主宋南樱\n男主：天龙人·表面风光霁月·暗地阴暗爬行·爱吃醋·占有欲强·男主谢乾安\n【贵族学院吃瓜日常+吃瓜系统+甜宠+天龙人恋爱】\n救人殒命功德加身的宋南樱穿到贵族学院世界，绑定吃瓜系统，什么F4大战贫民少女，戴着口罩的丑女其实是大美人，真假千金，天降活泼可爱转学生与青梅之间的艰难选择，酷炫男一与守护男二你选谁等一个瓜接着一个瓜冒了出来。\n系统：吃瓜值+1+1+1+1……\n宋南樱：【咔嚓咔嚓吃瓜ing~】\n吃到最后，等一下，这个学院第一美人·白月光·第一不能得罪人·学院大公主·高岭之花·学院明月是谁？说的是我吗？【挠头】\n谢乾安：【暗暗捏断钢笔】未婚妻太多人喜欢怎么办？\n那些人暗戳戳的就想要吸引未婚妻的注意怎么办？\n大家怎么还没发现我是她的未婚夫？\n总有贱人上赶着想要获得明月的目光，明明知道自己不配，却还想要月光的照耀，恶心至极！\n未婚妻是我的，我的，我的，我一个人的！",
    "creationStatus": 1,
    "wordNumber": 254592,
    "tags": [
      "青春甜宠",
      "现代言情",
      "校园",
      "系统",
      "穿越",
      "甜宠"
    ]
  },
  "7312837497564695604": {
    "bookId": "7312837497564695604",
    "bookName": "橘咖",
    "authorName": "温柔文人",
    "abstract": "【实体已上线，书名《橘咖》】\n裴霜第一次见到李长嬴是在西宛北站。他很高，身形颀长、比例极好、气质凌然。大背头，黑皮衣，黑墨镜，复古渐变破洞裤。\n男明星，酷哥，潮男。\n这是裴霜对这人的第一印象。\n事实也大抵如此，西宛大学新生报道第一天，这人就出了名。学校表白墙和论坛上疯传这人流连于万花丛中片叶不沾身，广撒网不走心，被称为海的嫡长子，是个渣男。\n后来——\n裴霜看着他，淡声说：“你脸又红了。”\n“……”\n李长嬴将头埋在她颈间，半晌后生无可恋的嗯了声。\n————\n李长嬴向朋友转述：“在我不认识她的情况下，她准确无误地叫了我的名字，还夸我长得好看，名字好听。”\n最终他得出结论：“她对我有意思。”\n朋友问：“你知道你属于哪种男生吗？”\n紧接着朋友犀利点评：“愿者上钩型，人家估计鱼饵都没放，你就主动送死了。”\n“……”\n酷哥vs拽姐（X）\n自我攻略恋爱脑vs撩而不自知（√）\n#春为发生，夏为长嬴#\n【感情节奏快，不喜勿喷，谨慎入坑，万分感谢。前前后后多次修稿，相关评论可能消失、错位，实在不好意思(⋟﹏⋞)】",
    "creationStatus": 0,
    "wordNumber": 288907,
    "tags": [
      "青春甜宠",
      "现代言情",
      "校园"
    ]
  },
  "7599272220879227966": {
    "bookId": "7599272220879227966",
    "bookName": "重生后，我伪造了遗嘱",
    "authorName": "爱吃肉的天灵灵地灵灵",
    "abstract": "苏念重生回来，第一时间伪造了遗嘱，远离了渣爸后妈。手握先机，她靠摆摊、炒股疯狂搞钱，实现财富自由。这一世，她要当人生赢家！",
    "creationStatus": 1,
    "wordNumber": 140558,
    "tags": [
      "青春甜宠",
      "现代言情",
      "重生",
      "前世今生",
      "发家致富",
      "家长里短"
    ]
  },
  "7643116702971989016": {
    "bookId": "7643116702971989016",
    "bookName": "疯撩！又野又欲！被偏执哥哥缠上",
    "authorName": "祁禄",
    "abstract": "【重生+病娇+甜撩+暗恋+双处+女救赎男/阴湿亡夫/HE】\n明媚小太阳*阴湿病娇变态*偏执狂\n想要摆脱自己的丈夫江问，是孟雨浓多年的心愿。\n和他结婚的那几年，她过得胆颤心惊，无时无刻不在害怕他。\n江问就是一个变态，他囚禁她，还喜欢将她关在地下室，然后用他那湿漉漉的舌头舔她。\n她恨他，恨不得他死去才好。\n终于有一天，江问真的死了，死在了她怀中。\n“我死了，宝宝开心吗？宝宝以后也不用再怕我了。”\n她的心愿终于达成，可她却并不开心。\n*\n重回大一那年，孟雨浓忍着害怕，这一次，她主动接近江问这个变态。\n“江问，我给你亲亲。”\n“江问，你很缺钱吗？我给你钱。”\n她希望他看在她对他这么好的份上，以后不要恩将仇报，不许再囚禁她了。\n江问，以后不能再当变态了噢~\n也不要偷我底裤了！！！",
    "creationStatus": 1,
    "wordNumber": 255988,
    "tags": [
      "青春甜宠",
      "现代言情",
      "校园",
      "重生",
      "甜宠",
      "病娇",
      "暗恋"
    ]
  },
  "7649940179041406014": {
    "bookId": "7649940179041406014",
    "bookName": "妹宝好欲！好会哭！太子爷亲红温",
    "authorName": "陈大喵0",
    "abstract": "【氧气甜妹vs冷淡混球｜双洁｜男替身｜兄弟雄竞｜上位低头｜强制爱】\n  邬漾心里有个早死的白月光。\n南大谢屹周，政商世家太子爷，顶级皮囊，出了名的高岭之花，除了眼下那颗痣之外跟白月光长得一模一样。\n邬漾为追他吃了不少苦头，被所有人嘲讽她是癞蛤蟆想吃天鹅肉。\n就在大家认为她不可能追到太子爷时，谢屹周却私下发了她照片宣布恋情。\n于是有人私下打赌，猜测他们早晚要分。\n没人知道，人前冷淡矜贵的谢屹周，人后是个重欲，有着渴肤症的混球。\n对她上瘾，会掐着她的腰，声音又哑又懒问她：“就这么喜欢我这张脸？”\n——\n谢屹周以为邬漾对他爱的要死，却被想到他被这个女人当成了替身。\n事情败露那天，他居高临下的对她放狠话：“今天走出这扇门，就别出现在我面前。”\n“我这人心眼小见不得你好过，不然绝对会弄死你跟你那个白月光。”\n后来邬漾真的走了，谢屹周却开始发疯。\n他开始遮住眼下那颗痣，敲开她的门，眼眶红透，声音却带着笑：“还喜欢这张脸吗？我比他更能满足你。”\n于是事情乱套了。\n谢屹周会在陆江彦在家时，故意进她房间，捂住她的嘴喘声说：“声音小点，我哥会听到。”\n“宝宝，我想听你对着我这张脸，叫他的名字。”",
    "creationStatus": 1,
    "wordNumber": 183719,
    "tags": [
      "青春甜宠",
      "现代言情",
      "校园",
      "替身",
      "豪门世家",
      "双洁"
    ]
  },
  "7634391867852868633": {
    "bookId": "7634391867852868633",
    "bookName": "狠捞的榜一大哥是前男友他舍友",
    "authorName": "折雾里",
    "abstract": "元雾白天是木讷呆板的女大学生，扔在人群里回头率为零。\n晚上是小有名气的颜值女主播，哄得无数观众哐哐给她砸钱。\n捞归捞，但有节操。线下把马甲捂得严严实实！\n渣男现女友嘲她土狗。\n元雾忍气吞声：家里穷，供俺上大学不容易\n榜一大哥给她转账要求见面。\n元雾忍痛拒绝：呜呜哥哥，人家最近过敏起疹子啦QAQ\n得知榜一大哥是渣男那位拽哥舍友，元雾从快快乐乐地捞，变成心惊胆战地捞。\n在翻车的边缘反复试探。\n-\n谢京隽是天之骄子，权势，名利，金钱于他唾手可得。\n但少有人知道，他患有严重失眠症。\n直到某天，不经意点进元雾直播间，对方清甜的声线该死戳中他的爽点。\n颜值主播（✖️）哄睡主播（✔）\n谢京隽主动加了元雾联系方式。\n别的金主要求看腿看身材。\n谢京隽画风清奇，给元雾寄了一箱睡前读物。\n元雾：……\n不知不觉砸了几百万，被钓成翘嘴的谢京隽要求见面，却得到对方的好人卡。\n谢京隽：？\n我拿你当对象你把我当冤种。\n-\n舍友生日，元雾被糊了一身蛋糕从浴室出来，听到旁边一声冷笑。\n黑框眼镜摘下，厚重刘海拨开，露出一张清艳的脸。\n谢京隽掐住她下巴，语气危险：你还挺能演。",
    "creationStatus": 0,
    "wordNumber": 206675,
    "tags": [
      "青春甜宠",
      "现代言情",
      "校园",
      "直播"
    ]
  },
  "7640326222639008792": {
    "bookId": "7640326222639008792",
    "bookName": "脑子一热，强吻了我哥的同窗好友",
    "authorName": "摆烂的步履",
    "abstract": "【一见钟情+生理性喜欢+系统助攻】\n系统搞错了人，绑定谢宜歌的第一天就触发强吻任务。\n她脑子一热，当众抢了亲哥同窗好友的初吻。\n还连续两次，把他亲懵了。\n那人是清河崔氏宗子，恪守四千条家规，口中说着成何体统。\n却早已泥潭深陷，夜夜在梦里失控沉沦。\n后来他一次次破戒，与她深吻厮磨。\n却一直误会她是挚友的未婚妻，在痴爱中隐忍克制，藏了满腔不敢外露的隐秘心动。\n那一记莽撞的吻，撕碎了他所有自持，甘愿沦为自己最唾弃的越界之人。\n误会解除后，那个早已经失控的男人再也忍不住化身野兽，将她彻底吃抹干净……",
    "creationStatus": 1,
    "wordNumber": 215997,
    "tags": [
      "古言脑洞",
      "古代言情",
      "系统",
      "一见钟情"
    ]
  },
  "7648619818370731033": {
    "bookId": "7648619818370731033",
    "bookName": "扶贫大秦：天幕盘点我是千古女相",
    "authorName": "思不诗",
    "abstract": "【秦始皇+CP是人民+女强+基建狂魔+群像文】\n一心为民、深耕基层的好干部宋也，一生鞠躬尽瘁，最终因胃癌离世。\n死后，她绑定了“救世安民”系统。\n系统告知：只要完成指定任务，积累万千功德，就能超脱凡俗、登临神位。\n然后，宋也开局就被丢到了一个鸟不拉屎的地方——沛县。\n基层扶贫吗？这她熟啊！\n·\n就这样，宋也女扮男装，以新县令的身份埋头苦干了三年。\n沛县百姓的日子越过越好，就当人人称颂这位宋大人时...\n天幕忽然降临！\n一位后世UP主，正一边参观女相陵墓，一边激情盘点：【现在向你走来的，是华夏千古第一女相，大秦五代帝师，大秦第一魅魔，搞经济第一人！】\n【学生、门客全是历史名人，开科举、修水利......不在话下！】\n【百官之首，社稷之臣，女中宰衡！】\n【华夏第一人喊出：人民万岁！！！】\n天幕之声，传遍四海。\n“？？？？？”\n秦始皇：“这位爱卿究竟在哪里！！”\n满朝文武：“女相？五代帝师？这简直闻所未闻！！”\n大秦百姓们：“！！！！！”\n·\n同一时间，沛县。\n刘邦、萧何等人，齐齐看向自家那位一身男装，正仰头看天的宋县令，纷纷陷入沉思.....\n系统：嗯？一觉睡醒，宿主怎么成万人迷了？？？",
    "creationStatus": 1,
    "wordNumber": 225800,
    "tags": [
      "古言脑洞",
      "古代言情",
      "系统",
      "穿越",
      "女强",
      "女扮男装",
      "无CP",
      "基建"
    ]
  },
  "7640115067735788606": {
    "bookId": "7640115067735788606",
    "bookName": "恶毒贵妃又又作死，弹幕教她躺赢",
    "authorName": "江予一",
    "abstract": "（评分刚出，会涨）【古言甜宠+帝王宠妃+双洁+弹幕爽文+虐渣打脸】\n戚以棠，太傅千金，生得花容月貌，过得顺风顺水。\n然而议亲那年，她被强取豪夺，成了反派帝王的妃子。\n竹马深情几许：“棠儿，你再忍忍，等我登基，定封你为后。”\n她信了竹马的话，打算给皇帝下毒。\n然而眼前飘过排排金色弹幕——\n“好蠢的女配，男主早和女主好上了，骗你送死呢！”\n“原著她下毒失败被反派囚禁了，桀桀桀黑化倒计时，搓手等待。”\n“死恋爱脑我服了！皇帝暗恋她十多年，给她后位不要，偏要当小三！”\n戚以棠：“……”\n蠢货竟是我自己？\n*****\n戚以棠觉醒了，自己竟是话本里的恶毒女配。\n因痴恋男主，她被骗下毒害死反派皇帝，导致大哥被诬陷通敌卖国，二哥被造谣私吞盐税，三哥被山贼砍掉半个脑袋，四哥染上花柳病……\n而男主踩着她全家的尸骨成了千古帝王！\n狗男人想让我当垫脚石，呵。\n戚以棠反手把毒药换成春药，灌进皇帝嘴里。\n既然弹幕说她是恶毒女配，何不“恶毒”到底呢？\n*****\n谢瓴知道戚以棠对他并无真心，但年少的执念困其一生，他偏要将她强娶到自己身边。\n后来，谢翎表示——\n瓜甜不甜，果然只有自己尝了才知道。",
    "creationStatus": 1,
    "wordNumber": 287940,
    "tags": [
      "古言脑洞",
      "古代言情",
      "甜宠",
      "虐渣",
      "暗恋",
      "攻略反派"
    ]
  },
  "7625615212606934078": {
    "bookId": "7625615212606934078",
    "bookName": "天幕说真千金是千古一帝",
    "authorName": "小猫和小狗在打架",
    "abstract": "北离歌从出生起就艰难的活着，直到10多岁才知道自己原是被报错的太子亲女，好不容易回到父母身边，占据自己身份的北婉清处处优秀把婉清衬托的粗鄙不堪，又被北韵雅的一众爱慕者逼去和亲，在离歌处境万分艰难时，一个意外让她觉醒前世记忆，得知自己穿越到一本自己看过的狗血小说中，处在历史中不存在的任何朝代，北离歌自觉斗不过有主角光环的主角们，远离一切时，天空一声巨响，天幕登场。\n“嗨，大家好，最近《景汉英雄传》正在热播，我那群最迷人的老祖宗，其中最闪耀的一颗星就是那位一路靠女人，世界最强赘婿，成为大汉王朝的开国之君，被誉为千古一帝的汉高祖！”\n北离歌：谁？汉高祖？刘邦穿了？\n又抬头看祖父和父王漆黑的脸色，心里很是幸灾乐祸。\n当得知自己就是那汉高祖的时候，北离歌再也笑不出来",
    "creationStatus": 1,
    "wordNumber": 193069,
    "tags": [
      "古言脑洞",
      "古代言情",
      "系统",
      "穿越",
      "女强",
      "真假千金"
    ]
  },
  "7646385352306854937": {
    "bookId": "7646385352306854937",
    "bookName": "我，女配，天幕曝光我是千古一帝",
    "authorName": "三千几许",
    "abstract": "【架空无cp+爽文+天幕曝光流+女主称帝+穿书+微群像+无雌竞】\n慕容芝穿书了。\n这是一本重生女主与高门男主经历种种磨难与误会相守一生的故事。\n可在甜宠文的表象下，是一个风雨飘摇的江山。\n争储的皇子们看不到底层百姓的苦，民间起义你方唱罢我方登场，慕容芝不愿和这世间的万千女子一样，到了年纪就嫁人生子，困于后宅。\n她想为自己争上一争。\n就算死去，也绝不后悔。\n既然这江山，谁都可以争，那她为什么不行？\n一朝筹谋数年，在慕容芝回京准备正式踏入权力的圈子时，天幕突然出现——\n【今天我们就来盘点一下历史上赫赫有名，争议不断，以女子之身开创大夏的，华夏史上最厉害的万古一帝——神昭大帝】\n慕容芝扬唇。\n她成功了。",
    "creationStatus": 1,
    "wordNumber": 177516,
    "tags": [
      "古言脑洞",
      "古代言情",
      "女强",
      "穿书",
      "无CP",
      "群像"
    ]
  },
  "7632381015444425752": {
    "bookId": "7632381015444425752",
    "bookName": "女配？我爹是皇帝，你最好也是哦",
    "authorName": "寒霜榭",
    "abstract": "【原生家庭的托举＋另类对抗路父女＋乱世女霸主】\n乾浅是个名声不太好的公主。\n她在街上飞来横祸，昏了三天醒来后，发现自己竟然是一本书里的炮灰女配。\n书里她不仅恶名昭著，甚至唯一的作用就只是被男女主绑去京城，骗她父皇开城门后又被男主一箭射死。\n而就在乾浅大骂主角岂有此理时：\n【恭喜宿主觉醒最苟女配系统，每活一月，奖励翻倍，请宿主苟到大结局并活下去】\n乾浅沉默：“你知道我爹是谁吗？”\n系统：【……？】\n乾浅：“我爹是皇帝，你现在最好祈祷男女主的爹也是皇帝。”　\n-\n乾浅十四岁时曾被一道圣旨贬斥出京。\n连续三年，圣意无转圜，人人都以为这位从小到大圣宠优渥的公主已经完了。\n可偏偏这时，手握剧情和系统的乾浅又杀了回来。\n她走到手握生杀大权的天子面前：“父皇放心，有我在你就闹心吧”\n【恭喜宿主进入主线剧情“乱世起，天下定”，已正式将宿主代号“恶毒公主”正式修改为——乱世女霸主。】\n-\n现在站在你面前的是：大乾唯一国号为姓，公主中唯一王爵持有者，“堂下何人状告本公主”，“和我的皇帝老爹说去吧”，“你有本事赐死我”，拳打太子，脚踩百官，辱骂皇帝第一人，男女主最严厉的母亲，昭明王，永郡大长公主——乾浅。",
    "creationStatus": 1,
    "wordNumber": 125474,
    "tags": [
      "古言脑洞",
      "古代言情",
      "系统",
      "公主",
      "团宠",
      "打脸",
      "虐渣"
    ]
  },
  "7653380132089908249": {
    "bookId": "7653380132089908249",
    "bookName": "穿古代开幼儿园满朝权贵求学位",
    "authorName": "墨柒点江山",
    "abstract": "【古代+穿越+经营种田+萌娃团宠+系统+爽文】\n幼师苏青青一觉醒来，穿成了大靖朝贫民窟里身无分文的孤女。\n开局破屋漏雨，米缸见底，好在她绑定了“超凡幼儿园系统”，系统商城里滑梯、绘本、营养餐应有尽有。\n别人穿越忙着宅斗宫斗，她忙着在破院子挂起招牌招收萌娃！\n第一个送来的，是打遍京城无敌手的将军府小霸王。\n三天后，小霸王乖乖行礼说谢谢，铁血将军当场泪洒三尺。\n第二个送来的，是三年不开口的丞相府小可怜。\n半月后，小可怜当众流利背诗，老丞相激动得要给苏青青立长生牌位。\n消息一传十十传百，满朝权贵彻底坐不住了，纷纷踏破门槛，黄金万两只求一个插班学位。\n连皇帝都微服私访，亲自牵着太子上门：“苏园长，朕的太子就交给你了，教不好……朕给你加薪！”\n从贫民窟的简陋托管班，到名震天下的皇家御赐书院。\n她教过的孩子，有人成了状元，有人成了神将，有人成了一代贤臣。\n大靖史书记载：“靖朝中兴，始于教化。教化之功，首推苏青青。”",
    "creationStatus": 1,
    "wordNumber": 292105,
    "tags": [
      "古言脑洞",
      "古代言情",
      "系统",
      "萌宝",
      "穿越",
      "团宠"
    ]
  },
  "7628961061521083416": {
    "bookId": "7628961061521083416",
    "bookName": "穿成了冷血皇帝的病弱炮灰养子",
    "authorName": "雨中拉肖邦阿",
    "abstract": "【亲情向＋无CP＋病弱＋团宠＋架空】\n　　作为第二代的陪伴型AI仿真人，零零一陪伴小主人从幼崽到成年期，功不可没。\n　　按照原计划，它是要更新老化零件，再陪伴主人到老年。\n　　但市面上越来越多的新款，大人们早就想要换掉它，他们第一时间销毁了零零一。\n　　零零一不知道自己被销毁了，在重新醒来过后，它以为自己升级成功了，换了新皮肤。\n　　但脑海中不知道为什么多出了一段奇怪的记忆，它是炮灰？叫做李临祎？\n　　还是个炮灰，因为身体孱弱，又天生寡言少语，被遗弃在雪天荒野，遇到了重伤的帝王李钦纶。\n　　帝王会心软，将他带回去，认作养子，养在身侧。但他不识好歹，偏执娇纵，横行无忌，得罪了一众皇子公主，以及妃子，甚至下到宫女太监，无一不厌恶他。\n　　最后落得废为庶人，驱逐出宫的下场。\n　　零零一不明白自己这是穿书了，以为这是自己被新植入的程序……既然是程序，就应该执行。\n　　至此，零零一变成了炮灰李临祎。\n　　但不太会阴谋诡计的陪伴型零零一，总会搞砸一切……\n　　他后知后觉地发现，已经和【程序】完全不一样的时候……\n　　嗯，大概是零零一变成了真人之后的古代日常。（架空哒！）",
    "creationStatus": 1,
    "wordNumber": 181792,
    "tags": [
      "古言脑洞",
      "古代言情",
      "穿越",
      "团宠",
      "医术",
      "无CP"
    ]
  },
  "7645508600718167102": {
    "bookId": "7645508600718167102",
    "bookName": "侯府罪妇开天眼，满京权贵藏不住",
    "authorName": "楹有闲",
    "abstract": "【重生+玄学+爽文+虐渣】\n顺阳伯府出了一桩丑闻。\n府中二姑娘冒领大姑娘救一城百姓之功，丑闻败露，万人唾骂。\n伯府顾念亲情，只将其遣去千里外的庄子上静养，却凭此功升爵侯府。\n八年后，顺阳侯府要接这位万人唾骂的二姑奶奶回京。\n京城勋贵皆是嗤笑，“她还有脸回来？”\n皆以为她在穷乡僻壤熬了八年，已嫁庄稼汉，生儿育女，容颜憔悴，庸碌度日。\n却不料，回来的秦二姑奶奶美瞎所有人的眼。　\n更是踹翻侯府大门，阉了府中管事，抢夺正院。\n有名门闺秀招惹她，她说，“你未婚夫有庶子，他那庶弟乃是他的庶子。”\n满座哗然。\n未婚夫：“？？？不是她招惹你吗？你揭我短作何？”\n有官员状告她不孝，她一眼扫去，“你靠妻供养读书，得官后买通匪徒，杀妻满门，倒会装深情。”　\n她无差别攻击上京所有她看不惯的勋贵。\n怼得满京勋贵闻风丧胆。\n却有越来越多的世家大族为她折腰。\n*\n终于打完胜仗的某王，背着奇珍异宝，带着媳妇的白虎，兴冲冲回家道歉。\n推开门，空了？\n某王懵了：我媳妇呢？我辣么大辣么美辣么厉害的媳妇儿呢？\n某乐滋滋准备翻肚，让阿娘揉肚皮的白虎也是两眼懵：我虎虎辣么大辣么美辣那么厉害的娘亲呢？",
    "creationStatus": 1,
    "wordNumber": 215509,
    "tags": [
      "古言脑洞",
      "古代言情",
      "幻想言情",
      "重生",
      "虐渣",
      "捉鬼"
    ]
  },
  "7641566657160170521": {
    "bookId": "7641566657160170521",
    "bookName": "我在大清当老六",
    "authorName": "东木木山",
    "abstract": "【轻松诙谐+团宠+亲情+日常+群像】\n丑了一辈子的小六明白一个道理——颜值即正义，这一辈子为了让新家人喜欢自己，小六才不管什么智力值、武力值——系统给我把美貌值加满！！！\n于是不怎么聪明、身子又不好的小六就这样卷入了夺嫡大战，最终一路成长为老六。\n别的皇子在一路拼荆斩棘，老六在带着五哥七弟偷瓜、在思考和尚道士谁的造型好看、在宗室酒席上听八卦、在给和离的亲戚保媒拉纤……\n就是这样脑回路清奇、又不按常理出牌的老六，竟然获得几代帝王的偏爱。\n老六的人生理想——当宗正每天判案吃瓜\n最后取得的成就——皇子团颜值扛把子·大清朝时尚标杆·宗室最佳调解员·京城金牌红娘……\n当皇帝有什么好的，在大清当老六也能活得美滋滋——\n只要我不想当皇帝，我想干什么就干什么！\n比起皇位，我更想要家人的爱和漂亮的脸蛋！\n……",
    "creationStatus": 1,
    "wordNumber": 254236,
    "tags": [
      "古言脑洞",
      "古代言情",
      "系统",
      "团宠",
      "搞笑轻松",
      "群像"
    ]
  },
  "7657387766208023576": {
    "bookId": "7657387766208023576",
    "bookName": "大秦天幕：六公主不想当女帝",
    "authorName": "爱吃馄饨馅的向星宇",
    "abstract": "嬴昭玥九岁那年，觉醒了前世记忆，还附带一只自称\"意念凝聚\"的系统猫。\n系统猫一脸正气：\"宿主，请登基称帝。\"\n嬴昭玥看了看自己连剑都提不动的小短手：\"……你是想让我拿你砸死我爹？\"\n系统猫这才发现自己跑错了时间线，还动不动就被雷劈。\n更离谱的是，天上突然开了个\"历史直播间\"，全天下都看见了她未来的模样——\n杀得比白起还狠，屠城只准立大秦旗帜，人称武昭女帝。\n九岁的嬴昭玥默默啃了口桂花糕。\n……他们说的那个杀人如麻的女魔头，真的是我吗？",
    "creationStatus": 1,
    "wordNumber": 114333,
    "tags": [
      "古言脑洞",
      "古代言情",
      "系统",
      "直播",
      "公主",
      "前世今生"
    ]
  },
  "7651447794707729433": {
    "bookId": "7651447794707729433",
    "bookName": "穿成废雌：我是兽世滚刀肉",
    "authorName": "烟雨风飞",
    "abstract": "【胎穿兽世+1VN+男全洁+爆笑魔丸姐妹花+团宠+雄竟修罗场+情报系统+基建种田】\n白棠在实验室连轴熬了半个月，猝死在工位岗位上。\n再次睁眼，她胎穿蛮荒兽世，成了一枚蛇蛋。\n开局遇上部落遇袭，同窝三四十个蛇蛋兄弟姐妹，尽数被凶悍的黑蛇一口吞噬。\n就在她这颗蛋蛋也要被沦为黑蛇口粮时，老登闪亮登场，救下她这条狗命。\n后来老登说，当年他要是早点回来，也不至于只剩下她们这两个半点没传承族群强悍的雌性。\n姐姐：嘤嘤嘤，怪我喽！\n妹妹：你是我老登，我啃你的老天经地义。\n整整十年光阴，这两个魔丸，把沉稳威严的老登气得七窍生烟。\n*\n别人穿越兽世，一路风生水起，攻略一众恪守男德的优质兽夫，人生快意逍遥。\n轮到白棠，就是个遇上原书穿越女主，演不过两集就狗带的炮灰。\n而她那嘤嘤怪的阿姐更了不得，还是原书剧情中最大反派。\n全族都是炮灰命。\n于是，胎穿一次，白棠组成(炮灰者联盟)，联合所有炮灰反派‘颠’覆原剧情。\n谁想破坏她躺平的退休日子，管她什么女主，干就完了。\n只是一路过来，女主这些未来兽夫为什么总是出现在她们姐妹身边？\n好难猜哦~\n",
    "creationStatus": 1,
    "wordNumber": 240276,
    "tags": [
      "古言脑洞",
      "古代言情",
      "系统",
      "兽世",
      "团宠",
      "胎穿"
    ]
  },
  "7649041104557313086": {
    "bookId": "7649041104557313086",
    "bookName": "携军事基地！母女穿越另一世",
    "authorName": "一路相伴",
    "abstract": "现代军人母女夏若兰、夏灵汐，穿越成被追杀至死的另一世自己，随身携带可复制建筑山川河流的神奇空间。\n军事基复制进了空间，里面物资无限，弹药充足，灵药可治百病、增神力。\n这一世，夏若兰是西宁国靖安侯府的正妻。\n撞破丈夫杜裴之与弟媳薛婉仪的奸情后，对方为夺嫁妆、掩丑事，竟买凶杀妻杀女。\n母女跳崖殒命，正与穿越而来的现代灵魂无缝衔接。\n既承此身，必报此仇。\n她们手刃渣男贱女，搬嫁妆、断亲缘、改姓归宗。\n夏灵汐更提出练兵之计，为宫中小姨夏嫔与表弟五皇子打造坚实后盾。\n皇室夺嫡暗流汹涌，母女携军事基地强势入局。\n助西宁吞并北齐，扶五皇子问鼎太子之位，最终登上那至高无上的宝座。\n从侯府到朝堂，从京城到边疆，母女联手，以暴制暴。\n杀仇敌，怼渣滓，句句扎心，拳拳到肉。\n她们要让所有人记住——忠烈之后，绝不好欺。\n且看这对现代军人母女，在古代快意恩仇，保家卫国，杀出一条血路。",
    "creationStatus": 1,
    "wordNumber": 232552,
    "tags": [
      "古言脑洞",
      "古代言情",
      "穿越",
      "空间",
      "虐渣"
    ]
  },
  "7640083605565230104": {
    "bookId": "7640083605565230104",
    "bookName": "小娘子天生魅体，权贵争相沦陷",
    "authorName": "凤凰落枝头",
    "abstract": "古言/穿越/发家致富/种田/\n多男主/男全洁/雄竞/绿茶/金手指\n\n奚舞，一个年近四十的小富婆。\n她信奉一句话：不能被男人左右，但不能左右没有男人。\n这些年来，她从不交二十五岁以上的男人。\n在她眼里，中意的男人是放床上的，而不是放心上的。\n空窗期，她也会点个男模消遣。\n唯独这一次，出了意外……\n她竟以这般不体面的方式，猝死在了床上。\n真是晚节不保！\n谁知一觉醒来，离谱的事情接踵而至。\n直白点讲，妥妥的地狱开局。\n她穿越成了一名小寡妇，原主私生活比她还要混乱。\n穿越最初的三天，每到夜里就有人翻墙入室，重点是，夜夜来人皆不相同。\n奚舞都不知道原主这具身子到底藏了多少个姘头。\n她被吓得连夜跑路，果断逃离。\n六年之后。\n春日宴上。\n这新科状元怎么有点眼熟呢？\n状元：“姐姐不认识我了吗？”\n这大将军怎么看我的眼神不对劲儿呢？\n大将军：“夫人，是不认识为夫了吗？”\n这大理寺卿好像更眼熟？\n大理寺卿：“居然敢偷偷跑了.......”\n这景阳王世子怎么瞪着她。\n世子：“渣女，睡了我就跑......”\n奚舞：能原地消失吗？\n这到底是春日宴，还是前任宴啊！",
    "creationStatus": 1,
    "wordNumber": 271356,
    "tags": [
      "古言脑洞",
      "古代言情",
      "系统",
      "穿越",
      "将军",
      "发家致富"
    ]
  },
  "7646761026335034393": {
    "bookId": "7646761026335034393",
    "bookName": "我在古代做临妻，多子多福赢麻了",
    "authorName": "枕金婉",
    "abstract": "【穿越+系统+大女主+女撩男+甜宠+群像】\n育儿嫂楚玲珑意外穿越，绑定多子多福育儿系统，依旧躲不开牛马的命运。甚至，这次还需要她亲自上阵，生了又生！\n哎呀，真是好惨一女的！\n摆烂不行吗，躺平不香吗？\n系统暗戳戳吐槽，“说的这么可怜，好像昨晚搂着猛男，快乐尖叫的人不是你一样！”\n楚玲珑窃笑。\n瞎说什么大实话！只不过是隐藏福利有亿点点多罢了！\n比如生崽容易，养崽全靠爸！\n比如三年一换夫郎合情合法！\n没有婆媳矛盾，没有柴米油盐，更没有家暴出轨抓马！\n哎呀，姐妹出息了，以前做梦都不敢做这么大！\n多金帅哥快到碗里来，姐姐愿意给你一个家！",
    "creationStatus": 1,
    "wordNumber": 179586,
    "tags": [
      "古言脑洞",
      "古代言情",
      "系统",
      "穿越",
      "甜宠",
      "群像"
    ]
  },
  "7656768107297377342": {
    "bookId": "7656768107297377342",
    "bookName": "听我心声后，九爷连夜抱四爷大腿",
    "authorName": "人间烟火落星河",
    "abstract": "董鄂·明月穿越了，开局就嫁给历史上被毒死惨死的毒舌九爷胤禟！\n本想安分守己当个咸鱼，混吃等死，反正这位爷最后要跟着八爷凉透。\n谁知，这毒舌老九居然能听到她的心声！\n大婚当夜，九爷冷脸：“收起你的心思，爷最烦你们这种深闺算计的女人。”\n表面上明月乖巧低头：“妾身明白，定恪守本分。”\n内心却疯狂吐槽：【笑死，要不是你马上就要被八爷坑得倾家荡产最后还得被毒死，真以为老娘稀罕你这傻狗？快点分房睡，别耽误我吃宵夜！】\n九爷：？？？\n后来，八爷来借钱，九爷一脚踹飞；太子来甩锅，九爷早跑没影。\n明月去四爷府做客，表面恭敬，内心：【四爷这小心眼又在记仇了，四福晋真惨，等会儿教她怎么偷偷藏私房钱，打马吊散心。】\n听见心声的九爷吓出冷汗，转头就抱紧四爷大腿：“四哥！弟弟我全心全意支持你啊！咱俩合伙做生意吧！”\n满朝文武都蒙了。\n说好的九爷是八爷党死忠呢？怎么成了四爷的专属移动金库？\n小心眼的冷面四爷看着满脸谄媚的老九，陷入了沉思。\n而那个传说中被九爷冷落的九福晋，不仅成了大清幕后女首富，把端庄的四福晋带成了吃货，顺手救下了弘晖阿哥，还被九爷宠成了京城最横的妻管严！",
    "creationStatus": 1,
    "wordNumber": 209902,
    "tags": [
      "古言脑洞",
      "古代言情",
      "宠妻",
      "幻想言情",
      "穿越",
      "清穿"
    ]
  },
  "7638673285600791576": {
    "bookId": "7638673285600791576",
    "bookName": "长公主的摆烂生活",
    "authorName": "圆不圆汤圆",
    "abstract": "开新书了，宝子们快来。\n【女尊+魂穿+1vN+男全洁+一见钟情+多男主自我攻略】\n\n　　单身女总裁过劳猝死，魂穿一个古代和现代相结合的女尊世界。\n都长公主了，谁还用干活啊？只想摆烂享受生活的她，却不自觉的一步步被推着改变这个世界。",
    "creationStatus": 0,
    "wordNumber": 237349,
    "tags": [
      "古言脑洞",
      "古代言情",
      "穿越",
      "公主",
      "一见钟情",
      "将军"
    ]
  },
  "7643458776611163161": {
    "bookId": "7643458776611163161",
    "bookName": "系统升级后，百官听见了我的心声",
    "authorName": "慕浔岸",
    "abstract": "【全员读心+吃瓜+胎穿+团宠】\n　叶慈因为地府工作人员失误投胎成了大梁朝段王的独生女儿叶慈，地府人员为了补偿给了她一个吃瓜系统。\n\n　　因段王不忍妻子继续遭受生育之苦，叶慈从小就被段王对外宣称是男孩。有一天叶慈为了吃瓜偷偷摸去朝堂，却被皇帝和众大臣发现可以听到叶慈和那个系统的心声。从此叶慈就开启了她的慢慢上朝路。\n\n　　【什么？表面一本正经的御史私下里竟然写小黄书，还写得大理寺卿和刑部郎中的小黄书。】\n\n　　【九皇子的癖好是穿女装，原因竟是九皇子的母妃喜欢皇后，想给皇后生一个女儿，没生出来就九皇子当女孩养了？】\n\n　　建元帝有十五个儿子，却一个公主也没有，唯一的亲弟弟段王也只有一个儿子，平时对其他弟弟生的小郡主极尽宠爱。当得知叶慈是女孩时，立即修书一封给段王：“弟弟！你怎么能重男轻女呢！”\n\n　　太后得知自己唯一的孙女被当成男孩养了十五年以后，当即就要去北疆暴揍段王。\n\n　　建元帝：弟弟你不要女儿，那就是朕的了！",
    "creationStatus": 1,
    "wordNumber": 181707,
    "tags": [
      "古言脑洞",
      "古代言情",
      "系统",
      "幻想言情",
      "穿越",
      "团宠"
    ]
  },
  "7628744898899872793": {
    "bookId": "7628744898899872793",
    "bookName": "穿成丫鬟后，赎身觅良人",
    "authorName": "甜心芙",
    "abstract": "1V1➕微金手指➕有男主\n重点:男女主不是神，都有各种各样的缺陷，男主原身家庭不太好，接受不了的可以退，写作不易，别恶意差评，谢谢！\n李春桃十六岁辍学进厂打工，有点运气分到了品质部，没有分到产线拧螺丝。\n打工十六年，男朋友谈了几个，就是不结婚。\n好不容易升到部门主管，一睁眼，穿越了不说，还成了个刚刚卖身的丫鬟。\n李春桃没想跑，她的身契还在人家手里捏着呢。\n最后没办法，只能苟着。\n既然要苟着，那就要老实。\n老老实实本本分分，后面找了个机会换到老夫人的小佛堂打扫卫生。\n李春桃:嗯，很好，这我熟啊！\n在小佛堂帮老夫人抄经书，学会了古代文字。\n如意、吉祥都是老夫人的二等丫鬟。\n如意会刺绣，吉祥会梳头。\n很好，李春桃又有了学习的机会。\n然后她缠着二人，学会了梳古代发髻，学会了怎么做衣服、学会了刺绣。\n眼看着十五岁了，老夫人身子却越来越差了。\n在老夫人去世前时，她求了恩典，想要赎身回家。\n老夫人知道自己日子不多了，便同意了，连带着放了一些愿意归家的仆人。\n回家后的李春桃\n“春来，姐姐饿了！”\n李春来:“好的姐姐，我来做饭！”\n李春桃:“春来，姐姐渴了”\n一杯茶递到她面前，“娘子，为夫比春来好使！",
    "creationStatus": 1,
    "wordNumber": 180913,
    "tags": [
      "古言脑洞",
      "古代言情",
      "穿越",
      "空间",
      "甜宠",
      "1v1"
    ]
  },
  "7634088410239487000": {
    "bookId": "7634088410239487000",
    "bookName": "我的夫君是大反派",
    "authorName": "云上之云",
    "abstract": "女主大美人/甜宠日常/万人迷/微玄学/医术/雄竞修罗场/穿越/双洁\n顾青青给自己挑了个夫君，对方温润，端方，百依百顺。\n　　成婚三年，日子过得挺舒心。\n　　唯一的问题是，他好像不是个好人。\n　　常常早出晚归也就算了，回来时衣裳上偶尔还带着血！\n　　姥姥说，夫妻之间过日子，得睁只眼闭只眼，顾青青听话，刻意忽略了对方留下的蛛丝马迹。\n　　她以为日子就这么过下去了。\n　　直到她在箱笼底层翻出一块可调兵遣将令牌，才知他是造反的头头！\n　　好好好，原来自己嫁的是大反派。\n　　女主：表面佛系咸鱼美人，实则医术玄学点满·深藏不露·心态稳如老狗理性脑。\n　　男主：表面温润如玉·大度君子·商业巨贾，实则偏执阴鸷·占有欲爆表·连狗都醋·暗里争霸天下的疯批恋爱脑。",
    "creationStatus": 1,
    "wordNumber": 248770,
    "tags": [
      "古言脑洞",
      "古代言情",
      "穿越",
      "甜宠",
      "医术"
    ]
  },
  "7645902383704198168": {
    "bookId": "7645902383704198168",
    "bookName": "男多女少：他们都想让我负责",
    "authorName": "兮兮伴月",
    "abstract": "评分刚出~【甜宠+空间+非1v1+轻松搞笑+非女强】\n\n永昭国男女比例10：1。\n女子年满二十，若夫君不足四人，官府便会亲自安排。\n苏知渺一朝穿越，只想低调苟活。\n谁知道。\n一个冷面王爷，一个温柔王妃，一个纯情弟弟，一个腹黑左相。\n一个比一个想让她负责。\n苏知渺：“等等，我一个都没想招惹！”\n萧惊辞：“负责。”\n沈时樾：“负责。”\n楚寻：“负责。”\n宁宴：“……负责。”\n苏知渺：“？？？”\n空间在手，方便面、手机、卫生巾……一样一样往外搬。\n最后苏知渺抱着脑袋：“不是……你们怎么都想让我负责啊！”",
    "creationStatus": 1,
    "wordNumber": 207782,
    "tags": [
      "古言脑洞",
      "古代言情",
      "甜宠",
      "穿越",
      "空间"
    ]
  },
  "7647870152372931609": {
    "bookId": "7647870152372931609",
    "bookName": "和暴君互穿，侯府众人天天被家暴",
    "authorName": "咘咘行",
    "abstract": "【病弱·贵女VS糙汉·暴君，互穿，轻松爽文】\n（丧丧阴阳师/高武没头脑）\n李微澜重生了。\n前世被侯府一家吃尽绝户，被污蔑、被毁容，寒冬腊月让人推入湖水，含恨而终。\n一朝重生，原想着占尽先机能不入前世后尘，被想到，重生到了那位一夜杀百人的暴君身上。\n李微澜：“？？？”\n所以暴君他在……\n“！！！”\n……\n燕京传闻——\n忠勇侯府那位世子夫人疯了！！\n手扇婆母脚踹公爹，阉割世子倒吊妾室。\n家、暴、全、家、呐！！！\n……\n外人视角：\n暴君最近有点不对劲。\n早朝不骂人了，也不砸人了，竟然还开始看书了？！\n准备回家含饴弄孙的太傅：退休再等等，皇帝好像还能教。\n心灰意冷有回村打算的状元郎：回村再等等，我还能为这个国家贡献力量。\n闲着没事想叛国的将军：谋逆再等等，暴君给我兵了，我想……什么？已经大一统了？？没事，听说海那边还有几个小国……\n……\n注：一对因配得感太高而人憎狗厌的男女主（bushi）",
    "creationStatus": 1,
    "wordNumber": 145874,
    "tags": [
      "古言脑洞",
      "古代言情",
      "重生",
      "魂穿",
      "打脸",
      "虐渣"
    ]
  },
  "7651265869963611161": {
    "bookId": "7651265869963611161",
    "bookName": "天塌了！我撩的小太监是疯批暴君",
    "authorName": "江轻辞",
    "abstract": "【1v1双洁+读心术】\n空樾身穿到天启王朝，成为一个洒扫小宫女，\n每天两眼一睁就是清理地面的血污，人都麻了。\n皇宫压抑危险又吃人，哪哪都不好，但宫里有个很好很好的小太监。\n小太监容色绝绝又乖巧听话。\n空樾想要，空樾得到。\n好不容易将人撩到手，空樾眸光熠熠地看着躺在自己身侧的小太监，许下了诺言。\n“我此生绝不会负你。”\n**\n后来，空樾食言了。\n她的小太监是书中杀人如麻的炮灰暴君，那个杀光皇室成员且把他们尸骨制成地砖任人踩踏的暴君。\n空樾害怕地跑了。\n**\n两年后，暴君出现在空樾面前。\n他抚摸着她的脸，红着眼，声音带着几分哽咽，满是委屈，“你始乱终弃。”\n偏偏暴君拿她没办法，“阿樾，求你别跑了。”\n空樾：？？？\n你不是疯批暴君吗？怎么红眼求我别跑？",
    "creationStatus": 1,
    "wordNumber": 178237,
    "tags": [
      "古言脑洞",
      "古代言情",
      "甜宠",
      "反派",
      "病娇",
      "穿书",
      "异世穿越"
    ]
  },
  "7646752148612451390": {
    "bookId": "7646752148612451390",
    "bookName": "小世子不想黑化，只想要爹爹抱",
    "authorName": "托尔图加岛的沐辉",
    "abstract": "父子&亲情&微虐&救赎&无cp\n小可怜时安穿成了摄政王府病弱小世子。\n好消息：他有爹了。\n坏消息：这个爹不疼他。\n亲娘早死，亲爹冷漠，下人欺辱，偏偏他还绑定了一个反派系统，天天逼他学坏、害父、攒黑化值。\n可时安天生心软，毒糕点舍不得送，栽赃陷害学不会，只会可怜巴巴挨罚。\n本该养出大反派的系统，最后先把自己养成了崽控。\n而那个冷心冷情的摄政王，也在这个孩子一次次小心翼翼的靠近里，终于一点点学会了爱自己的儿子。\n小世子不想黑化，\n他只想要爹爹抱。",
    "creationStatus": 1,
    "wordNumber": 294343,
    "tags": [
      "古言脑洞",
      "古代言情",
      "系统",
      "萌宝",
      "穿越",
      "无CP"
    ]
  },
  "7648651025292725273": {
    "bookId": "7648651025292725273",
    "bookName": "陛下求您放过我",
    "authorName": "欣可YIN",
    "abstract": "巧取豪夺+囚禁＋空间＋强制爱＋金手指＋系统\n倏然睁眼，旖旎的触感瞬间席卷全身。\n她猝然僵住，视线定格在身前男子脸上，心头巨震\n这……这是哪？\n还有这发型……\n一朝穿越，她从没想过攀附皇权，只盼隐于深宫，安稳过完一生。\n可这位冷面帝王，却执意将她锁在寝殿之内，朝夕相伴，恩宠成囚。\n万般无奈之下，她轻声啜泣，苦苦央求：“皇上，求您放过臣妾吧。”\n玄烨指尖抚过她的脸颊，声线低沉，裹挟着帝王独有的强势：“乖些。若不听话，你………”",
    "creationStatus": 1,
    "wordNumber": 221263,
    "tags": [
      "古言脑洞",
      "古代言情",
      "系统",
      "穿越",
      "空间",
      "清穿"
    ]
  },
  "7647229791044635672": {
    "bookId": "7647229791044635672",
    "bookName": "娇软万人迷，疯批权贵都想抢",
    "authorName": "浅夏夜空",
    "abstract": "【1vn多男主/万人迷/男全洁/疯批病娇/雄竞修罗场/强制爱/强取豪夺/男强女弱/女嬷】\n众星捧月长大的公主楚灵汐，容色倾城，是寄养在皇室的掌上明珠。\n外表光鲜亮丽的她，却守着一个不可告人的秘密。\n每到圆月之夜，楚灵汐都会长出九条狐尾和两只狐耳，化身九尾狐妖。\n为了死守秘密，每月的这一日，她都会将自己关在房内，艰难熬过一整晚。\n直到一次中秋宫宴，楚灵汐的秘密被曝光，素来畏惧妖邪的皇室将她始作洪水猛兽。\n她以为等来的会是众人的审判，会被送上斩妖除魔的断头台，却不想，等来的却是权贵们晦暗的心思：\n*\n权倾朝野的太子步步为营，亮出真面目：正直皇叔撕下伪善面具，假意帮忙实则为了将她私藏；\n温润如玉的未婚夫伙同腹黑小叔，将她骗进别院；心狠手辣的敌国质子，将她掳至大漠深处：\n就连最信任的青梅竹马，都亮出锋利爪牙。\n【万人迷小白兔被群狼环伺，抢来抢去的故事】",
    "creationStatus": 1,
    "wordNumber": 198199,
    "tags": [
      "古言脑洞",
      "古代言情",
      "公主",
      "腹黑",
      "病娇",
      "青梅竹马"
    ]
  },
  "7652725973925776409": {
    "bookId": "7652725973925776409",
    "bookName": "绝美杀神：摄政王夜夜为我疯魔",
    "authorName": "柴小妞",
    "abstract": "穿越、空间、热武器、系统商城、涅渣、\n新作品出炉，欢迎大家前往番茄小说阅读我的作品，希望大家能够喜欢，你们的关注是我写作的动力，我会努力讲好每个故事！",
    "creationStatus": 0,
    "wordNumber": 162044,
    "tags": [
      "古言脑洞",
      "古代言情",
      "系统",
      "穿越",
      "空间",
      "虐渣"
    ]
  },
  "7646335759317732377": {
    "bookId": "7646335759317732377",
    "bookName": "大明：系统让我争宠，我扮演神明",
    "authorName": "无焰秦漠",
    "abstract": "【大明+穿越+大女主无CP+扮演神明+非正统历史+剧本演绎】\n月清宸本是一个现代大学生，意外猝死后绑定【绝代宠妃系统】。\n本该前往后宫位面争宠，谁料空间坐标错乱，她一头栽进洪武大明，沦为皇宫最底层的打杂宫女。\n系统急得团团转，拼命怂恿她攀附帝王、混迹后宫，靠争宠赚取情绪值。\n可看透封建牢笼的月清宸嗤之以鼻：后宫争宠？帝王情爱？无趣至极。\n她拒绝。\n既然争宠走不通，那就换条路走。\n一人一系统敲定剧本，从此深宫之中，多了一位下凡历劫的上古神明。\n她气场超然，演技封神，仅凭几句“神言”、一身气度，就让整座皇宫人心惶惶，帝后群臣纷纷侧目。\n随手展露的奇术、精准预判的国运、改良民生的新知，一步步坐实神尊身份，从任人践踏的小宫女，变成举国敬畏的护国真神。\n系统从最初的催争宠、搞宫斗，逐渐陷入深度怀疑：\n这演技、这眼界、这深不可测的神魂……她真的只是个普通穿越者？\n当域外妖邪觊觎功德，她不再隐藏实力，战神神威横扫群魔，天下众生彻底跪拜。\n漫天神纹凝聚至尊神袍，六界第一战神真身临世。\n原来从来不是凡人扮神，而是真神历劫，顺势而行。\n弃宫斗，济万民，改国运，渡红尘。\n一代尊神，名留青史。",
    "creationStatus": 1,
    "wordNumber": 167413,
    "tags": [
      "古言脑洞",
      "古代言情",
      "系统",
      "无CP",
      "魂穿"
    ]
  },
  "7652224733592685592": {
    "bookId": "7652224733592685592",
    "bookName": "被丢乱坟坡后，我的客户全是鬼",
    "authorName": "洋柿子",
    "abstract": "修仙界不务正业的茱萸散人渡劫失败，一睁眼发现自己穿到古代奄奄一息的三岁小儿身体里。\n大冬天被家里人扔到乱坟坡，眼瞅着就要冻死了。\n 好消息：渡劫失败被雷劈死又活了。\n坏消息：这个世界没有灵气，修炼不了。\n本以为这辈子都要像凡人一样生活了，突然发现天道还给她留了条缝。\n她继承了原主的阴阳眼，能以凡人之躯看到鬼。\n在帮鬼完成心愿后，对方的真心感激会化为愿力进入她体内，而这愿力能转化成灵气。\n这就叫天无绝人之路啊！\n\n于是接下来茱萸的日子变了。\nA：我死时没来得及告诉儿子我私房钱藏在哪，烦请姑娘帮忙找出来放到儿子床头。\n茱萸：行\nB：我儿子换了我的棺材板，你帮我把他私房钱偷来咱俩分。\n茱萸：可以\nC：我要跟我老相好埋一起。\n茱萸：没问题\nDEFJGHIJK……\n\n茱萸一鱼两吃，愿力+劳务费两手抓，每天睁开眼：办完你的办你的……\n\n",
    "creationStatus": 1,
    "wordNumber": 185068,
    "tags": [
      "古言脑洞",
      "古代言情",
      "乡村",
      "幻想言情",
      "穿越",
      "风水秘术"
    ]
  },
  "7620486269809740825": {
    "bookId": "7620486269809740825",
    "bookName": "囤货后我穿进了灾荒梦境娶夫",
    "authorName": "阿双妹妹",
    "abstract": "微女尊＋古代＋空间＋末世天灾＋女强男强\n\n女主不是娇妻\n\n姜晚凝性情淡漠，却被一场连绵不绝的怪梦缠上。\n梦中并非同一场景，而是一个痴傻孤女的完整一生。\n女孩父母早亡，全靠族中亲人拼尽全力庇护，可灭世天灾接踵而至——地震山摇、火山喷发、洪水滔天、极寒封世，乱世之中甚至人相食。\n护着她的人一个个惨死，临终前仍柔声叮嘱：别怕，别看。\n惨烈景象，纵使是姜晚凝也心有余悸，满心悲怆与不安。\n一次意外，她获得一方随身空间，强烈的预感让她确信，梦境绝非虚。\n她开始疯狂囤积物资，粮食、衣物、药品、工具……塞满整个空间，只为应对即将到来的浩劫。\n一朝睁眼，她果真穿进了那个灾劫横行的微女尊世界，成了梦中那个痴傻孤女。\n想到步步逼近的灭世天灾，姜晚凝微微头疼。\n既来之，则安之。\n她不能任人宰割，定要护住仅剩的亲人族人，在乱世之中站稳脚跟，安稳度日，顺便……再娶几位合心意的温柔夫君，一世安稳。",
    "creationStatus": 0,
    "wordNumber": 251255,
    "tags": [
      "古言脑洞",
      "古代言情",
      "乡村",
      "空间",
      "末世",
      "强强"
    ]
  },
  "7633433896964590617": {
    "bookId": "7633433896964590617",
    "bookName": "没血条？你管这绝美NPC叫病弱",
    "authorName": "大天使伽百列",
    "abstract": "说好的恐怖副本，玩家们怎么都把我一个NPC当成靠山？\n穿越诡异无限流世界，别人都是艰难求生，木知兮却连个肉身都没有。\n好在前世的角色创作软件激活，木知兮能附身于自己亲手捏的角色，获得其能力与背景。\n于是——身份不够神秘怎么办？自己编！\n势力不够庞大怎么办？自己吹！吹牛谁不会呀！\n更有趣的是，木知兮发现她能随意修改自己的NPC面板！\n作为重度颜控，她第一时间就是把头顶巨丑无比的血条给抠掉了（严肃）\n万万没想到，这个纯粹出于“颜控”的举动，直接引爆了整个无限流圈子！\n玩家A：“没血条？你管这绝色NPC叫病弱？她岂不是无法被杀死！”\n玩家B：“她的面板上写着至纯至善，是位仁慈神女，大家快去抱大腿！”\n为了苟命，木知兮附身神女，随手给自己的面板加了一行：【隐藏阵营：圣域教堂，古纪元势力】\n玩家疯了，争着给她刷好感、做任务，把她当成副本里的唯一生路。\n所有人都以为木知兮背后藏着一个传承万万年的古老神国，疯狂考据她的势力秘史，甚至为了她的马甲分化阵营。\n只有木知兮知道，从教堂到帝国，从神女到帝女，全是她随口扯的。\n全网玩家考据：“她是隐世势力神女，是隐藏主线！”\n木知兮微笑不语。\n不好意思，你们考据出的古老势力，都是我刚编的。",
    "creationStatus": 1,
    "wordNumber": 191265,
    "tags": [
      "悬疑脑洞",
      "悬疑",
      "穿越",
      "灵异",
      "惊悚游戏",
      "规则怪谈"
    ]
  },
  "7563612379108346905": {
    "bookId": "7563612379108346905",
    "bookName": "盗墓：强制诚实的我憋不住了",
    "authorName": "雪山下的糊汝伊",
    "abstract": "（评分刚出，会涨哒）\n一个普通人穿越到盗笔世界，成了吴家小少爷。\n吴言，开局抽奖抽到了‘强制诚实’，这是奖励？\n再次抽奖，抽到了‘不会坏的计算器’。\n为了活下去，吴言只能尽量少说话，用‘计算器’代替自己发言！\n（有CP，有系统，团宠，搞笑甜味，不虐。主角性格是被特意培养的，单纯、幼稚，但三观极正。介意者，勿看！！！！！！！）\n看着不停说话欺负自己的黑瞎子，吴言不语，拿出计算器，不停按下减号键，计算器不停响起 “ jian jian jian jian jian jian ........”\n看着出言不逊的伙计，吴言用计算器按下几个键，计算器响起“平方根62500  等于......”\n遇到嘲讽吴家的藿仙姑，吴言不语，拿出计算器，按下六个数字‘4’ ‘3’ ‘8’， ‘4’ ‘7’ ‘8’！\n不想回答别人问题，按下计算器的“X的y次方”键，计算器会响起‘mi’！\n周围人的沉默震耳欲聋.........\n————————————\n吴言实在憋不住的时候，大家都完蛋了！\n‘强制诚实’开始了！\n吴言要么不语，掏出计算器按‘按键’！  要么，话说不停，还气人！\n大家默默捏紧拳头，不能生气！孩子就是太实诚了！忍忍吧！",
    "creationStatus": 1,
    "wordNumber": 170740,
    "tags": [
      "悬疑脑洞",
      "悬疑",
      "系统",
      "穿越",
      "灵异",
      "同人"
    ]
  },
  "7651204736850332697": {
    "bookId": "7651204736850332697",
    "bookName": "我靠装逼征服诡异世界",
    "authorName": "Crazy杨",
    "abstract": "【评分刚出，求五星🙏🏻】\n【1VN】【无CP】【装逼】【迪化】\n【注：无CP等于谁都能是CPヘ(￣ω￣ヘ)】\n公元3077年，诡异入侵世界，杨宴被迫卷入到诡异副本当中，正准备摆烂混日子，谁曾想居然绑定了一个装逼系统，从此在迪化的道路上一去不复返……\n杨宴：闭眼休息\n众人：都闭上眼睛！大佬察觉了不对！\n杨宴：发发呆放空大脑\n众人：都不要轻举妄动！大佬在思考破局之法！\n杨宴：？\n系统欲哭无泪：家人们谁懂啊！本以为绑定了一个大佬，谁知道是个面瘫装逼男啊！\n—\n“听说十三区来了一个顶级大佬！”\n“真的假的！”\n“真的！据说他杀伐果断，深不可测，腰细腿长，清冷矜贵……”\n“嗯？等等？后面的形容词不对吧啊喂……”\n“细说深不可测……”\n——\n于此同时，副本内的大佬们……\n孤狼大佬呈影（心满意足）：“是的，我是他的狗，这是我的荣幸(｡･ω･｡)。”\n公会会长风惊羽（认真脸）：“啊？你问我杨宴吗？他宽肩窄腰，气质斐然，高冷神秘……（此处省略一万字）”\n商会盟主枭鹤（温润如玉）：“希望能够取代呈影的位置，他还不配(◣_◢)。”\n某反派：“真的不能改变阵营吗？老师我想和杨宴一组o(╥﹏╥)o”\n杨宴：？你们",
    "creationStatus": 1,
    "wordNumber": 186637,
    "tags": [
      "悬疑脑洞",
      "悬疑",
      "系统",
      "直播",
      "灵异",
      "惊悚游戏"
    ]
  },
  "7646318154984983614": {
    "bookId": "7646318154984983614",
    "bookName": "惊悚游戏降临后，我变成女巫了",
    "authorName": "言无早",
    "abstract": "【惊悚游戏+直播+微恐+轻松+群像爽文+装逼+无CP】\n评分刚出会涨的，求求五星好评，感谢(◦˙▽˙◦)\n女主超强，但是刚开始心态还是普通人心态，等她进副本就好。\n惊悚游戏降临，怕死的岑杳意外绑定学习系统，学习如何成为全宇宙最伟大的女巫。\n于是，别人在副本逃生，她在空间疯狂学魔法。\n本以为能单刷副本，却捡到了一群“破布娃娃”一样的神仙队友。\n于是，全网都知道，岑杳的队伍是惊悚游戏里最奇葩的存在。\n队长岑杳是眼神清澈的准大学生。\n队员更离谱：高冷的聋子、自闭的哑巴、自恋的瞎子、刻薄的腿残人士、没有触觉的迟钝路痴。\n副本Boss狂喜：全员残废和一个不足为惧的清澈大学生，这把稳了！\n结果开局就遭到了惨无人道的毒打。\n清澈大学生岑杳左手凤凰右手冰龙，追着BOSS哐哐砸；\n触觉失灵的祝灵犀，戴上面具请神诛邪；\n聋子黑客迟霜序，手敲代码重写规则；\n双腿残疾的裴听澜，海妖歌声操控万鬼；\n自闭哑巴顾砚迟，一拳干碎规则屏障；\n瞎子少爷谢昼行，大喊着黑夜由他主宰。\n聋、哑、瞎、残、无触感，却个个都是满级大佬！\n岑杳：很好，刚好带这群疯批制霸惊悚局！\n后来，只要这六个人出现，鬼怪连夜扛着火车跑",
    "creationStatus": 1,
    "wordNumber": 195801,
    "tags": [
      "悬疑脑洞",
      "悬疑",
      "直播",
      "灵异",
      "惊悚游戏",
      "群像"
    ]
  },
  "7647750288681471000": {
    "bookId": "7647750288681471000",
    "bookName": "我的人格超会演【卡牌扮演】",
    "authorName": "烟火喵喵",
    "abstract": "现代诡异、女频但男主且无CP、群像、马甲文、规则类无限流。【评分刚出，会涨】\n诡异降临地球的第十年，从小被诡异养大的青年靠着自己的努力开了家武器店养老。\n但意外的被马甲系统绑定，要他靠扮演那些马甲们得到知名度，去帮助这个世界的主角团们拯救世界。\n作为一个资深精神病，马甲系统深得他心。\n同生不同死的双生子、乐子人贵族少爷、失了声的作家、白切黑的玩偶师、盛开在荆棘中的玫瑰花语、人猫双形态的少年、看破一切的命者……\n每一个马甲都有自己的疯病。\n主角团们：……这些神经病都是从哪冒出来的？\n后来，他们发现这些马甲的背后都有一个组织者，他们喊他主人，奉他为“神明”。",
    "creationStatus": 1,
    "wordNumber": 207088,
    "tags": [
      "悬疑脑洞",
      "悬疑",
      "无CP",
      "系统",
      "群像",
      "白切黑",
      "灵异"
    ]
  },
  "7646504547661138968": {
    "bookId": "7646504547661138968",
    "bookName": "盗墓：我那柔弱不能自理的本体",
    "authorName": "大桡子",
    "abstract": "（刚出分后续会涨）\n「无cp+不下墓+比较日常+马甲+完美演绎」\n　　别人穿越都是隐藏大佬，运筹帷幄，轻轻松松玩转主角团。\n　　关云闲不一样。\n　　他是脆皮，体弱多病，一筹莫展，活着都是问题。\n　　关云闲：“我就非死不可吗？”\n　　系统害羞捂脸：“哎呀，人家叫传奇耐活王系统嘛~”\n　　“请宿主努力完成人设完美演绎，演绎值越高，打卡掉落的奖品越丰厚，每打卡一次可获得随机辅助道具，演绎分满，任务结束，祝贺宿主任务顺利，活着完成任务！”\n　　关云闲：？？？\n　　听听，人言否？\n　　前文提醒：\n　　没什么下墓剧情，本书也可以叫剧情外主角团的日常生活，同人文里，下墓的剧情看多了，有点腻，又找不到代餐，只能自己做饭了。",
    "creationStatus": 1,
    "wordNumber": 134219,
    "tags": [
      "悬疑脑洞",
      "悬疑",
      "系统",
      "灵异",
      "无CP",
      "同人"
    ]
  },
  "7615733068296358974": {
    "bookId": "7615733068296358974",
    "bookName": "什么变态，那是我老公",
    "authorName": "子桑翡",
    "abstract": "明想嫁给谢均，结婚两年，生活平淡且幸福。\n可这一天，她突然看到了出现的弹幕。\n【笑死，女配不会以为她会很幸福吧，嫁给了一个变态杀人狂魔】\n【都不知道自己怎么死的，还在那沾沾自喜】\n明想：胡说，我老公怎么可能是变态。\n她不信，觉得自己产生幻觉了。\n谢均从屠宰场回来，衣服上沾了不少血。\n【来了来了，女配今晚会被这个变态杀死分尸，我迫不及待了！】\n【终于能看到她的下场了，抢了女主的人生，该死！】\n明想看向朝自己温柔笑的丈夫，拿着把刀在切菜。\n她老公这么好，为了两人的小家，每天从早到晚去屠宰场杀猪，才不是什么变态。\n明想坚决不相信弹幕说的。\n当抛弃她的明家人找上门，对她颐指气使，骂她不孝，让她替养女去死时。\n谢均站在她面前，徒手捏死了嚣张气焰的一家人，化做血雾。\n弹幕空白几秒:\n【不是，你告诉我这是普通的鬼夫文？女主都被杀了，反派还是惊悚副本的boss，疯了，我真是疯了！】\n明想:？\n明想觉得自己精神更不正常了。\n她老公才没杀人，杀的是恶人，也不是变态。\n#女主眼中全是正常人，看不到诡异，甜文，1v1\n#什么，你说我老公是变态，胡说，他明明就是个普通屠宰场杀猪的",
    "creationStatus": 0,
    "wordNumber": 238862,
    "tags": [
      "悬疑脑洞",
      "悬疑",
      "灵异",
      "惊悚游戏",
      "1v1",
      "规则怪谈"
    ]
  },
  "7587450947035466776": {
    "bookId": "7587450947035466776",
    "bookName": "无限恐怖？反派玩家已上线！",
    "authorName": "一十三幺",
    "abstract": "【评分刚出~会涨的不用担心】\n【无CP无限流+掀桌系“羊”皮反派+非典型乐子人+微恐竞技+游戏现实双事业】\n·\n【叮！欢迎来到里世界恐怖直播游戏，新手教程已自动为您抽取身份牌——】\n【鬼牌】\n意思是1vN当内鬼，破坏其她玩家的任务，妥妥地狱模式！\n江·新手残疾人·貅：“……”\n逆天系统，在线发丧。\n谁在栽赃谁在陷害，到底谁让你抽了？！\n·\n号称消除痛苦的糖果乐园，售卖血肉内脏的鼹鼠小区，精英洗脑的鲤鱼学院，疯癫吃人的织女山庄……游戏内副本诡谲，入侵现实；玩家阶级分明，压榨新人规矩遍布。\n江貅觉得不行。\n在人家的规则里玩不赢。她要砸场子，她要成为吞并所有财富，推翻一切束缚的大反派！\n到序列之上，重构一切秩序！\nPS：\n【里世界温馨提示：如果有玩家说要毁灭世界，很幸运，您可以松口气啦~但如果对方说自己有一个推翻旧秩序，打造幸福家园的理想……跑！赶、紧、跑！！】\n……\n……\n【作者简介废，大概是中二爽文，因为作者极其偏爱热血女人；默认少年青年老年为女】\n【阳光鬼系主角，以理服人以和为贵，不服打死不和攮死，争做新时代乐子人！主打亲情友情生死之交，且因为主角太有魅力了，恕我无法阻挡角色为她倾倒（被打死也算倾倒了呀bb】",
    "creationStatus": 1,
    "wordNumber": 257205,
    "tags": [
      "悬疑脑洞",
      "悬疑",
      "无限流",
      "灵异",
      "无CP",
      "惊悚游戏"
    ]
  },
  "7638263689493089305": {
    "bookId": "7638263689493089305",
    "bookName": "老九门到盗笔，宿主他易燃易爆炸",
    "authorName": "开棺起尸",
    "abstract": "[无cp+团宠]\n江昭，快穿局绿茶部成员，被新上任的绿茶部部长直接打包扔进了盗笔小世界。\n江昭：不是，没人先过问一下我的意见吗？\n吴棠：你的意见是什么很重要的东西吗？要是任务失败了，我就把你扔星际监狱里去……\n江昭：一串优美的电报声飘过\n江昭再次睁眼的时候，就成了一个小婴儿。\n江昭：不是，就不能让我一穿过来的时候就是个成年人吗？为什么一穿过来就是生活不能自理的年纪？又是一串优美的电报声！\n小时候的江昭，是一颗乖巧软萌的灵珠，长大后的江昭，是唯恐天下不乱，而且还一点就炸的炮仗！\n水蝗：佛爷好歹也是九门之首，你这么直呼其名不太好吧？\n江昭嗖的一下过去踹翻了水蝗，\n江昭：我敢叫，他敢应吗？他逢年过节给我磕一个还差不多！\n张起山刚想开口\n江昭：你闭嘴！\n张起山：张家人为什么会有晚婚晚育这种东西？\n努力降低自己存在感的张鈤山：佛爷，咱也收敛点成吗？\n解九：阿昭，气大伤身！\n江昭：我要是有气不撒出来，更伤身！\n吴叁省／解联环：叔，你下手能轻点吗？我的医保卡要刷爆了！\n江昭：没把你们两个倒霉玩意儿打死，已经算得上是我脾气好了。\n吴斜：小爷爷，别骂了！别骂了！你再骂我就破防了！\n解雨辰：求放过",
    "creationStatus": 1,
    "wordNumber": 185371,
    "tags": [
      "悬疑脑洞",
      "悬疑",
      "穿越",
      "灵异",
      "无CP",
      "同人"
    ]
  },
  "7646795497851587608": {
    "bookId": "7646795497851587608",
    "bookName": "盗墓：萌脸烧他今天上吊了吗？",
    "authorName": "张凑凑",
    "abstract": "【团宠＋all＋穿越】\n  想泡主角，结果开局穿成个奶娃娃，怎么办？在线等，挺急的……  \n  解槿荣，一个顶着天真无辜的萌脸，却能把整个盗墓界搅得天翻地覆的男人。\n上辈子最大的愿望就是想要穿到盗墓世界，和他的男神们来一场轰轰烈烈的恋爱。为了实现这个伟大的梦想，他选择了一条捷径——大运“创死”套餐。\n    一睁眼，他成功了，但又没完全成功。 \n  别人的穿越是龙傲天开局，打脸升级收后宫；他的穿越是“哇哇”待哺，连翻身都得靠别人帮忙。 \n  现在每天只能叼着奶嘴，含糊不清地喊“饿饿”，等着未来老公（童年版）给自己换尿布。\n  这跟说好的剧本不一样啊喂！",
    "creationStatus": 1,
    "wordNumber": 151936,
    "tags": [
      "悬疑脑洞",
      "悬疑",
      "系统",
      "穿越",
      "灵异",
      "风水秘术"
    ]
  },
  "7654650438687411262": {
    "bookId": "7654650438687411262",
    "bookName": "从南部档案馆靠签到混成九门团宠",
    "authorName": "一鸽一鸽哟",
    "abstract": "(评分刚出♥)\n【盗笔同人+南部档案+爆笑日常+签到系统+老九门+弥补遗憾】\n穿越盗笔宇宙，成了张家籍籍无名的小透明张幺幺。本以为要卷入长生阴谋，每天在古墓里和粽子玩命，结果当场绑定【奇葩每日签到系统】！\n不签到就扣寿命？行！但你这任务是不是离谱过头了？！\n【滴！今日任务：拔下张海盐的一根头发。奖励：满级缩骨功！】\n张海盐捂着头皮狂飙脏话：张幺幺你有病是不是？！\n【滴！今日任务：在九门大会上，抢走张大佛爷的茶杯并一饮而尽。奖励：麒麟血脉纯度+10%！】\n张启山捏断了手中的钢笔：……把这个疯丫头给我叉出长沙城！\n【滴！今日任务：给闷油瓶讲三个冷笑话，并让他笑出声。奖励：黑金古刀（绝版）！】\n张幺幺两眼一黑：系统你干脆直接抹杀我吧！！\n为了活命，张幺幺在作死的边缘反复横跳。\n结果一路从南部档案签到到了西泠印社，生生把惊悚悬疑剧本玩成了情景喜剧。当年那个到处惹是生非的搞笑女，不知不觉间，竟成了九门几代大佬拼了命也要护着的祖宗。\n无邪：“如果有我幺幺姑奶奶在，这墓里的粽子都得连夜搬家。”\n张幺幺欲哭无泪：“我真的没想当大佬，我只是想安安静静签个到啊喂！”",
    "creationStatus": 1,
    "wordNumber": 192074,
    "tags": [
      "悬疑脑洞",
      "悬疑",
      "系统",
      "穿越",
      "灵异",
      "同人"
    ]
  },
  "7640624195927280702": {
    "bookId": "7640624195927280702",
    "bookName": "盗墓：让瓶邪黑花攻略我",
    "authorName": "再吃亿碗就够了",
    "abstract": "穿越进盗墓世界鹿琳绑定了一个坑爹的攻略系统：要攻略張起灵、吳邪、黑瞎子和谢雨臣。\n　　鹿琳：四个？一起？想让我死直说。\n　　她是穿越来的，她看过原著，她知道这四个人没一个好骗的，当然除了前期的吳邪小天真，但是那也是个小机灵鬼好不好。\n　　于是她干了一件系统都没想到的事。\n　　找到了子系统板块，把“伪·攻略系统”反向绑定给了他们四个。\n　　“来，你们来攻略我。”\n　　于是神奇的一幕发生了：\n　　吳邪笨拙地给她送早餐，内心OS：“加好感度了嘛？”\n　　黑瞎子天天土味情话暴击，自以为很帅。\n　　張起灵沉默地替她挡下所有危险，然后面无表情地等她夸他。\n　　谢雨臣若即若离，步步为营，每次靠近都让她心跳加速。\n　　鹿琳一边假装脸红，一边在心里打分：天真太可爱了，瞎子哥戏太多，小哥能不能多说两个字，花爷你再靠近一点我就要真沦陷了……\n　　每完成一次被攻略，系统就会给她发奖励。\n　　她从中抠出一点残羹，当作奖励分给他们。\n　　四人感激涕零：系统真好，任务真简单。\n　　鹿琳数着奖励偷笑：这波血赚。",
    "creationStatus": 1,
    "wordNumber": 281949,
    "tags": [
      "悬疑脑洞",
      "悬疑",
      "系统",
      "穿越",
      "灵异",
      "同人"
    ]
  },
  "7649396631116205080": {
    "bookId": "7649396631116205080",
    "bookName": "国运求生：我种的菜风靡地府",
    "authorName": "水岸云涯",
    "abstract": "【女频】【无cp】【诡异国运游戏】【种田】\n身为网文游戏的云安穿越到了新世界，因为国运游戏的出现，新世界种花家的情况不容乐观。\n云安还没来得及把自己掌握的民俗知识告诉大家，就被国运游戏选中，成为诡异游戏《黄泉垄上》的玩家。\n看着诡异邻居们一个个面黄肌瘦，吃不饱穿不暖，云安撸起袖子：“来吧！种地！”",
    "creationStatus": 1,
    "wordNumber": 178616,
    "tags": [
      "悬疑脑洞",
      "悬疑",
      "穿越",
      "直播",
      "灵异",
      "无CP"
    ]
  },
  "7645899400291552281": {
    "bookId": "7645899400291552281",
    "bookName": "跑团：谁家调查员90外貌啊？！",
    "authorName": "绝望中诞生的希望xw",
    "abstract": "穿越三天，成为了一名调查员？\n黎溪笑了，她前世可是一名资深调查员！（汗）\n于是，在队友小心翼翼找线索，对抗神话生物时，黎溪在干嘛？\n哦，她在泡npc。\n面对最终大boss时，其他调查员be like：这个邪教徒也太强了！！！\n黎溪be like：你是人是吧？看我的魅惑90啊！\n【魅惑技能检定结果大成功】\n所以什么叫邪教徒被改邪归正了？！！\n黎溪：我也不想的，可惜，我的魅力还是如此不讲道理～\n诶？有外貌90的npc小姐姐？我来啦！！！\n靠，怎么是奈亚？！！\n一定是TM奈亚拉托提普干的（魔怔）",
    "creationStatus": 1,
    "wordNumber": 124075,
    "tags": [
      "悬疑脑洞",
      "悬疑",
      "穿越",
      "推理",
      "异世穿越",
      "惊悚游戏"
    ]
  },
  "7626196453022518296": {
    "bookId": "7626196453022518296",
    "bookName": "诡异国运：我以道法震慑全球",
    "authorName": "无名茶",
    "abstract": "新书，评分刚出，后面会慢慢长的\n【国运游戏】【全球直播】【东方玄学】【无CP】\n诡异国运降临蓝星，各国选手被投入恐怖副本。\n身负正统道法，别人进诡异副本：躲鬼、逃命、哭着找生路。\n沈青禾进诡异副本：拎着符箓揣着道术，追着诡异满地图杀。\n \n凶煞想吓她？被她反手镇压。\n怨灵想索命？被她当场超度。\n副本BOSS刚摆好pose，就见这位道门传人抄家伙冲上来，比怪还凶。\n诡异：系统救命，有人打诡！",
    "creationStatus": 1,
    "wordNumber": 251953,
    "tags": [
      "悬疑脑洞",
      "悬疑",
      "灵异",
      "无CP",
      "惊悚游戏",
      "风水秘术"
    ]
  },
  "7650509466441354302": {
    "bookId": "7650509466441354302",
    "bookName": "盗笔：嫩牛五方一直在我坟头蹦迪",
    "authorName": "锦衣书华",
    "abstract": "【盗笔同人+长生种+正文无cp+万人迷all向+ooc致歉+本传+九门+南部档案】\n说出来你可能不信，烛廷玉活了两千多年。\n从春秋战国一路苟到现代，见过烛之武退秦兵，围观过李白作诗，甚至给朱元璋扔过两个钱。\n但是一次穿越，让烛廷玉一朝回到解放前——她穿进了盗笔的世界里，而已经用惯了无线支付的她身上没有一分钱\n烛廷玉一拍大腿：对了，我有墓啊！\n摸进自己的墓穴，她轻车熟路地避开自己设计的机关，正准备拿点陪葬品换钱花，结果一回头，有五个人正蹲在角落里，眼睛直勾勾盯着她。\n“这位姐姐，”无邪咽了咽口水，“您是粽子还是前辈？”\n烛廷玉面无表情地把自己的青铜剑塞回包里：“让让，别挡我拿自己的东西。”\n“…您自己的？”\n从此以后，圈里多出一个下地绝不走空的烛姐，有关于神秘烛姐的猜测纷纷扰扰。\n但实际上是：\n无邪：这你也来过？\n烛廷玉：我宋代时候修的坟，都我自己的，随便拿。\n解雨辰：你对这地儿挺熟啊？\n烛廷玉：你走自己家会迷路吗？\n黑瞎子：哎呦，烛姐您这体力差点意思啊。\n烛廷玉：哎，年纪大了，不比你们年轻人了。\n张启灵：多大？\n烛廷玉：也就两千七百多岁吧。\n王胖子：…来来来老人家吃点软乎的，千万别把牙",
    "creationStatus": 1,
    "wordNumber": 114535,
    "tags": [
      "悬疑脑洞",
      "悬疑",
      "灵异",
      "无CP",
      "同人",
      "风水秘术"
    ]
  },
  "7629974068464208920": {
    "bookId": "7629974068464208920",
    "bookName": "穿进盗笔当采购，全九门都喊我靠",
    "authorName": "旧巷里的猫语",
    "abstract": "（主受＋ALL+搞笑＋打工人＋普通人＋部分剧情＋部分日常+小小金手指）\n这是女频同人文，怎么一堆男频的人啊，真求你们了，避避雷吧，男频给我把分拉的太离谱了\n林越穿越了\n一睁眼就在杭州巷子里，全身三百二十七块五毛钱。\n就在他绝望的时候看到了无山居的招聘启事\n凭着前世卷出来的采购经验，他成功拿下了这份工作\n五险一金拉满，月薪六位数，出差补贴翻倍，加班费按分钟算。\n林越当场签下合同：这班我能上到公司倒闭！\n直到上班第一天，他接到了大老板的电话。\n“什么叫你要三百斤犀角粉？”\n这玩意儿犯法吧？你是要开工厂吗？怕不是神经病。\n“什么叫你要五十斤雄黄送到沙漠？”\n你是杭州人还是法海本人，沙漠里是藏着一条修炼千年的眼镜王蛇精么。\n“什么叫把东西送到沙漠一个树的边上”\n把我当骆驼呢，你怎么不说放沙丘上呢！\n采购单一次比一次离谱，配送地址一次比一次阴间。\n更要命的是，无斜发现他好用以后，转头就把他的微信推给了谢宇辰和黑眼镜。\n林越正要抗议，无斜轻飘飘一句话堵住了他的嘴：“你的工资和所有报销，都是谢老板给的。”\n林越瞬间安静。\n从此，别人下斗是九死一生闯剧情，他送货是跋山涉水赶deadline",
    "creationStatus": 1,
    "wordNumber": 249169,
    "tags": [
      "悬疑脑洞",
      "悬疑",
      "穿越",
      "灵异",
      "同人",
      "搞笑轻松"
    ]
  },
  "7657943637115816985": {
    "bookId": "7657943637115816985",
    "bookName": "盗墓：穿成黑金古刀，小哥求贴贴",
    "authorName": "云飞小橙",
    "abstract": "【爆笑爽文？包的！】\n穿成黑金古刀的第一天，我正被张起灵握在手里，准备一刀劈碎血尸的脑壳。\n看着那流黄水的粽子，我在他脑子里爆发出土拨鼠尖叫：\n“啊啊啊丑东西退散！别拿老娘劈他！老娘叫林软软，不叫砍骨刀！碰到这生化垃圾我会掉漆毁容的！”\n下一秒，道上神佛皆惧的哑巴张手一抖，强行扭转手腕，宁可自己用胳膊挡住酸血，也护着刀刃滴水不沾，随后一记飞踹送血尸归西。\n胖子手欠，想拿黑金古刀切冰镇西瓜。\n刀还没碰到，就被一股煞气崩飞三米远。\n刚洗完澡的张起灵裹着浴巾踹门而出，满眼戾气地夺回长刀，将刀死死护在胸前。\n吴邪和胖子吓傻了：\n“小、小哥……那只是一把刀，你怎么护得跟没过门的媳妇似的？”\n张起灵面若冰霜，冷冷吐出几个字：\n“她不喜欢。”\n没人知道，此刻一向冷傲的神明，耳根早已红得滴血。\n因为他怀里那把冰冷的刀，正用软糯的声音疯狂撩拨：\n“老公好帅！老公腹肌好硬！快，把我塞进你冲锋衣里，我要贴贴充电！”\n直到某天夜里，吸足了麒麟血的古刀终于攒够能量，化作娇软少女跌入他怀中。\n张起灵那双常年波澜不惊的眼眸，彻底暗了。\n【高冷面瘫双标神明 × 满嘴跑火车沙雕刀灵】\n排雷：非传统惊悚盗墓，含糖量超标，小哥单向读心私密频道，一路爆笑互宠！",
    "creationStatus": 1,
    "wordNumber": 200835,
    "tags": [
      "悬疑脑洞",
      "悬疑",
      "盗墓",
      "搞笑轻松",
      "同人",
      "穿越"
    ]
  },
  "7606231917322570776": {
    "bookId": "7606231917322570776",
    "bookName": "睡醒家丢了，我召唤族长振兴张家",
    "authorName": "墙头草随风飘",
    "abstract": "耶咦，居然出评分了，评分刚刚出，比较低。新人出品，先避个雷，无cp＋不和九门玩＋番外和正文无关无关无关＋现有的是黑瞎子和小哥\n\n张守源一觉睡了七百年，醒来家没了，族人没了，只剩一个瘦巴巴的小可怜张麒麟。\n系统表示：【家族振兴系统】已激活！\n张守源心梗：振兴个屁，全族就俩人！\n还好他翻出祖传召唤符，正所谓死道友不死贫道，当场把自己当年甩锅的冤种族长张守清强行拉来打工。\n张守清：我都死了，你还薅我干活？\n张守源：族长不上谁上！",
    "creationStatus": 1,
    "wordNumber": 279406,
    "tags": [
      "悬疑脑洞",
      "悬疑",
      "系统",
      "灵异",
      "无CP",
      "同人"
    ]
  },
  "7649561914988579902": {
    "bookId": "7649561914988579902",
    "bookName": "盗墓：被星际生子系统绑定了",
    "authorName": "中年失业的设计师",
    "abstract": "穿越+盗墓+生子+强制+单元剧+all(万人迷)+OOC（黑九门，有的黑无邪，不喜勿入）\n现代社会平平无奇的女大学生，性格胆小、怕黑、怕阿飘，（女主非女强，属于成长型的）刚刚失去父母，又因为救了一个孩子而意外身亡，成了名阿飘。在世间飘飘荡荡一年多，及没遇到鬼差，也没有遇到其他阿飘，无聊之下跟着一个‘稻米’看书追剧，又跟着去了长白山。结果被星际系统局的生子系统绑定了，被迫去各个盗墓世界做任务，只为解绑或者移民星际。\n穿成倒霉的霍有雪？没事，看我把股份卖给霍仙姑，拐跑张起灵。穿成霍秀秀，奶奶刚死？没关系，先找小花哥哥解除婚约，被送出国，拐走姐姐霍有雪，跑去墨脱睡了张起灵。\n系统001看着宿主的操作，说好的你胆小呢？胆小你敢睡了张起灵？要不让宿主穿成个男的？不知道会有什么惊喜呢？！\n1、穿越成霍有雪（CP瓶、黑、花）\n2、穿成霍秀秀（CP瓶、黑、花）开局先睡张起灵\n3、穿成尹南风（CP黑、花、瓶）\n4、穿成阿宁（CP暂定瓶、邪、黑、花）\n5、未定......",
    "creationStatus": 1,
    "wordNumber": 133290,
    "tags": [
      "悬疑脑洞",
      "悬疑",
      "盗墓",
      "星际",
      "系统",
      "穿越",
      "同人"
    ]
  },
  "7654856654374046782": {
    "bookId": "7654856654374046782",
    "bookName": "绑定技能后万人迷被迫陷入修罗场",
    "authorName": "枫叶没红",
    "abstract": "【万人迷｜男全洁｜雄竞修罗场｜玛丽苏｜凝女女嬷】\n　　白莺绑定了一个不可描述的安全房技能，唯一的特点就是房间绝对安全。\n　　她自以为拿到了金手指，可房间却“恶趣味”制定规则。\n　　【第一条：熟悉气息】\n　　【第二条：触摸位置】\n　　【第三条：狠狠缠住柔软的……】\n　　每一次解锁使用房间，要求也更加越界，而离开只能遵守规则。\n　　白莺深知不可以，也不想冒犯别人，躲男人躲的极远，寻找自救方法。但是后来每一个被拉入房间的男人却都和白莺想象的不太一样。\n　　他会直勾勾的盯着她，带着妒意问道：“你和别的男人在这里吻过吗？”\n　　白莺：？\n　　……\n　　末世海岛，貌美但愚蠢的娇纵大小姐×闻着味蠢蠢欲动的坏狗痴汉们\n　　惊悚高校，女扮男装却皮肤饥渴症小漂亮×心怀各异的偷窃癖室友们\n　　克苏鲁小镇，伪装怪物家人的泪失禁妹宝×善妒混沌的人外们\n　　……",
    "creationStatus": 1,
    "wordNumber": 130127,
    "tags": [
      "悬疑脑洞",
      "悬疑",
      "系统",
      "穿越",
      "无限流",
      "灵异"
    ]
  },
  "7656405978484575294": {
    "bookId": "7656405978484575294",
    "bookName": "盗墓沙海：江同学魅力值爆表",
    "authorName": "风月折笺",
    "abstract": "【沙海+盲冢+万人迷+NPC觉醒】（全文存稿，重启可能会写。）\n江游突然觉醒记忆，发现自己竟然是小说里连名字都没有的路人甲。他没有顺从命运，而是做出惊人之举——改写黎簇的结局，硬闯盗笔世界。\n可偏偏，他越疯，越有人挪不开眼。\n沙三角：我难道不是昭昭最喜欢的哥哥吗？\n小汪们：敌友难辨，立场摇摆。\n无邪：死之前，我只想再见他一面。\n黑瞎子：“兄弟”太多，要不要先下手为强？\n江游一路走来，常常感叹自己运气不错，遇上了一群过命的兄弟。\n直到某天，他忽然发现，身边这些“好兄弟”似乎都藏着不为人知的心思……\n【主角已成年，无不良导向。】",
    "creationStatus": 1,
    "wordNumber": 122711,
    "tags": [
      "悬疑脑洞",
      "悬疑",
      "盗墓",
      "同人",
      "衍生",
      "搞笑轻松"
    ]
  },
  "7654162614947171390": {
    "bookId": "7654162614947171390",
    "bookName": "九叔：家通义庄，我的道侣是九叔",
    "authorName": "柳檀",
    "abstract": "沈砚芙满心震惊，她万万没料到，一觉糊涂缠绵，竟和大名鼎鼎的茅山僵尸道长林凤娇结缘！\n家里卧室连通阴阳，一头连着现代居所，一头直通任家镇九叔的义庄。\n九叔：动她，你们逝世！\n九叔：文才，换上体面衣裳，随为师去见一个人。”\n文才：“师父，你是要给我.....”\n九叔：“不错，是要给你找个师娘了！”\n文才：不是老婆吗？.....我要裂开了啊！\n九叔：老东西，我的芙妹在那里！！！\n现代老年文才：师父，你这样为了师娘，会引起道门大派大战的啊！\n九叔一意孤行：区区门派纷争，不及我芙妹半分重要！\n九叔：混账玩意！就凭我僵尸道长林凤娇这七个字，含金量够不够！\n秋生：师娘驾到，统统闪开！",
    "creationStatus": 1,
    "wordNumber": 200142,
    "tags": [
      "悬疑脑洞",
      "悬疑",
      "灵异",
      "同人",
      "风水秘术",
      "九叔"
    ]
  },
  "7630757830928124953": {
    "bookId": "7630757830928124953",
    "bookName": "乙女：在无限流里当万人迷！",
    "authorName": "凡雪荼",
    "abstract": "【第二人称】【纯代入向】【乙女】【多男主】【男全洁】\n纯代哦纯代，谁敢在评论区发第三人称的称呼（如女主什么的）破坏我可爱的纯代小宝们的体验的话，我不会客气的哦^-^\n提前避雷，我的文只给乙代姐们看，不代入的都另寻他处！\n[游戏]降临蓝星，所有年满18周岁的人都被拉进游戏世界\n只有完成任务，通过游戏，抓取副本中的一线生机，才有可能活下来\n而你，仅仅只是在熬夜刷小说睡着后就穿越到了这个世界\n没有强大的体魄，没有强力的金手指，你只有一个可以陪你聊聊天让你不至于那么寂寞的系统——淦！半毛钱用都没有啊！\n你愤愤不平，无可奈何，不得不接受现实，怀着“能活活不能活死”的念头进入第一场副本\n你看见了一个人，一个可以让你抱大腿的存在——你穿越前还在看的那本无限流小说里的“圣父”男主\n你不可思议，你喜极而泣，你想着你或许不用死了\n在躺赢第一个副本后，你心满意足地等着第二个副本到来，觉得多活一天都是多赚的时候，你看见了第二位男主\n…………既然如此，那你可就不客气地把这游戏玩成攻略游戏啦！\n（简介无能，请移步正文）",
    "creationStatus": 1,
    "wordNumber": 143884,
    "tags": [
      "悬疑脑洞",
      "悬疑",
      "穿越",
      "无限流",
      "灵异",
      "惊悚游戏"
    ]
  },
  "7650118945734659134": {
    "bookId": "7650118945734659134",
    "bookName": "言灵魔女：觉醒就是神级血脉",
    "authorName": "当星河闪烁",
    "abstract": "【穿越+无CP+乐子人+超凡+后期多体系融合】\n正文视角第三人称，只有第一章开头会有一部分的第一人称。\n主角不可能有CP，阵营算是中立邪恶，别惹她就没事惹了她没好事。\n*\n埃莉诺，一款倒霉实验室开局目标登临神位的纯血魔女，107死亡公交唯一免票选手，沧啸山基金会会长都要回避的特别顾问，试图抢夺某世界月亮并成功第一人。\n主角战力会很高，因为是乐子人属性中立邪恶，很多时候是乐于旁观别人倒霉甚至加点火的。",
    "creationStatus": 1,
    "wordNumber": 190056,
    "tags": [
      "悬疑脑洞",
      "悬疑",
      "灵异",
      "无CP",
      "异世穿越",
      "胎穿"
    ]
  },
  "7593718367312170009": {
    "bookId": "7593718367312170009",
    "bookName": "盗墓：嘀！癫多多抽卡系统已上线",
    "authorName": "咕啾桃愿",
    "abstract": "［原创女主+团宠all+全员暧昧+支线番外+私设很多+ooc致歉］\n栗梨，死于古早霸总文的最惨路人甲。\n前脚被疯批女主飙车创飞，后脚被恋爱脑男主二次碾压。\n觉醒后，她看着这对“杀人犯”男女主，直接原地发疯：“尼玛，这也能HE？老子不活了！”\n \n她摆烂、她发疯、她随地大小癫。\n结果，那个智商欠费的男主竟然爱上了她？！\n面对漫天烟花表白，栗梨淡定地竖起中指：“老子死都不跟你一起！”\n轰隆——\n一道天雷降下，她真死了。\n栗梨（濒死）：“草，这男主上面真有人……”\n \n再次睁眼，她被“癫多多”系统绑定，空投到了一个新的世界。\n开局就是一只张着血盆大口的血尸！\n系统：“宿主快抽卡！”\n栗梨十连抽：9个谢谢惠顾，1张【光之国召唤卡】。\n使用条件：身边人必须相信光。\n \n栗梨看着眼前凶神恶煞的血尸，又看了看旁边的王胖子，深吸一口气：\n“哥们，在这个生死关头，我想问你一个严肃的问题……”\n“你相信光吗？”\n \n王胖子：？？？",
    "creationStatus": 1,
    "wordNumber": 271475,
    "tags": [
      "悬疑脑洞",
      "悬疑",
      "系统",
      "穿越",
      "盗墓",
      "灵异"
    ]
  },
  "7651505440534039577": {
    "bookId": "7651505440534039577",
    "bookName": "盗墓：从南部档案馆偶遇海虾开始",
    "authorName": "筷子笼笼",
    "abstract": "【南部档案馆】【九门】【终极笔记】等等——\n陆引在不同剧本中来回穿梭，有时是地下古墓，有时是海底，雪山，草原——\n在不同的副本中存活下来。\n一开始她只当这是系统设定的游戏，后来，受伤后，好久无法愈合的伤口，真实出现的地名和人物，都在告诉她，这一切都是真实发生的故事，她不是在副本里面游戏。她必须存活下来。",
    "creationStatus": 1,
    "wordNumber": 140923,
    "tags": [
      "悬疑脑洞",
      "悬疑",
      "二次元",
      "盗墓",
      "灵异",
      "同人"
    ]
  },
  "7650859423321033790": {
    "bookId": "7650859423321033790",
    "bookName": "乙女游戏哪来的面板和血条啊喂？",
    "authorName": "王嘻嘻兮",
    "abstract": "【系统+万人迷+病娇+暧昧拉扯+直播弹幕+升级流+反杀+宿敌+诡异副本】\n#狠狠玩弄病娇们感情，她超勇的#\n#表面《诡异恋爱模拟游戏》，实际惊悚副本生死局#\n深夜，沈亦言手机弹出某诡异恋爱游戏。\n开局就抽中伪人卡并被画面吓死。\n好在得到重生方法——通关副本赚积分买重生卡。\n【叮咚！恭喜您开局出生在病床上】\n【您的状态：被绳索水灵灵地五花大绑着】\n【黑发红眸的斯文败类医生正优雅地拿着电锯，即将把您五马分尸！】\n沈亦言：“......？”\n【恭喜您受迷魂香影响扑倒了眼前矜贵优雅却无力反抗的白发青年！】\n【场面一度活色生香！】\n沈亦言：“这才是我们大女人该玩的恋爱游......”戏。\n【检测到白发青年为诡异，与您教导培训中会释放虫胚，使其寄生于您】\n沈亦言：“......？”\n【叮咚！】\n【--检测更多疯批病娇们正在靠近，请玩家做好准备--】\n***\n作为一个间歇性疯批变态的沧桑忧郁社畜。\n越偏执目的不纯的危险爱意，越能激发沈亦言病态的战意，令她热血沸腾......\n“常言道，宿敌就是宿敌，宿敌是不能成为妻子/丈夫的。”\n--所有感情，动机不纯，去向不明，对待不善--",
    "creationStatus": 1,
    "wordNumber": 165873,
    "tags": [
      "悬疑脑洞",
      "悬疑",
      "系统",
      "直播",
      "灵异",
      "惊悚游戏"
    ]
  },
  "7645611224037608473": {
    "bookId": "7645611224037608473",
    "bookName": "盗笔，开局穿到黑瞎子床上",
    "authorName": "锅包肉大大",
    "abstract": "苏宁宁是一名普通的大学生，最大的烦恼不过是早八和期末考。没想到，一觉醒来，她直接换了片场——旁边躺着一个戴墨镜的陌生男人！\n“绑架？我跟你说，最好把我送回去，不然等我舍友发现我不见了，一定会报警的！”\n黑瞎子莫名其妙，自己床上怎么凭空出现个女人？还疯疯癫癫大吼大叫。他竟完全没有察觉，难道是谁派来的间谍？正警惕时，耳边突然涌入一长串嘈杂心声——他居然能听到这女人的心里话！\n苏宁宁也在这时发现自己绑定了系统。“008，难道我穿越了？”\n008骄傲脸：“没错，就是本宝宝，人见人爱花见花开的系统~”\n苏宁宁冷漠：“关我屁事，快送我回去，你这个绑架犯。”\n008：“一千万。”\n苏宁宁秒变脸，声线甜美：“好的老板，不知道小女子要做什么呢？端茶倒水暖被窝，本人非常全能~”\n就这样，一个满脑子吐槽的财迷女大学生，和一个能听到她所有心声的痞气黑瞎子，命运的齿轮开始转动。从七星鲁王宫到云顶天宫，别人下墓是玩命，苏宁宁下墓是“带薪团建”。更没想到的是，张起灵、解雨臣、吴邪……各路大佬似乎都对她这个穿越者格外“关照”。",
    "creationStatus": 1,
    "wordNumber": 224213,
    "tags": [
      "悬疑脑洞",
      "悬疑",
      "穿越",
      "灵异",
      "同人",
      "风水秘术"
    ]
  },
  "7645770321408052286": {
    "bookId": "7645770321408052286",
    "bookName": "五毒认我为母，我靠吃虫发家",
    "authorName": "最强豆芽",
    "abstract": "评分刚出，后面会长[无cp+无限流+女强+群像+萌宠+微惊悚+成长型女主]\n每一位算命先生都说温不烦这辈子气运不凡，往后荣华富贵享也享不尽。\n但事实却恰恰相反，温不烦因为身体太差连小学都没上完，直接辍学在家养病了。\n医生说她活不过12，但她却拖着那具千疮百孔的身体苟活到了18。\n敢问哪家气运之子身体脏器没一处好的。\n温不烦原以为自己会在18岁生日那天西去升天。\n但天不遂人愿，就在她濒临死亡的时候。\n系统机械的提示音降临了！\n只要进入副本她就还有生的机会，并且通关后还可以获得大量的奖金和道具，只要她能做到，以后都会是衣食无忧！\n她心想，反正自己都要死了，最后赌这么一把吧！就算赌输了，也只不过是面临自己本来就要死的结局……\n但没想到，第一局游戏副本自己就起飞了!!\n【恭喜玩家获得Boss道具【Boss双生蛾母其一】。】\n【恭喜玩家获得【雷霆情书×3】。】\n【恭喜玩家获得【救命的壳】。】\n【恭喜玩家获得【不错的匕首】。】\n【恭喜玩家获得【毛孩子们的家】。】\n既来之则安之。\n以后还要和【梦魇】打很久的交道。\n来让我们看看这【梦魇】究竟是个怎么样都存在吧。",
    "creationStatus": 1,
    "wordNumber": 162043,
    "tags": [
      "悬疑脑洞",
      "悬疑",
      "规则怪谈",
      "惊悚游戏",
      "无CP",
      "系统",
      "女强"
    ]
  },
  "7654572647035964440": {
    "bookId": "7654572647035964440",
    "bookName": "小炮灰变美后，抢了财阀太子爷",
    "authorName": "草莓糖心",
    "abstract": "【穿书 + 贵族学院F4 +  娇柔大美人 + 勾引上位】\n冷厉傲慢第一财阀太子爷（193cm） × 纯欲娇柔炮灰大美人（168cm）\n铃兰小花妖渡劫失败，本该魂飞魄散，却意外绑定了炮灰系统，穿进一本贵族学院小说，成了同名小炮灰。\n原剧情里，她是女主林晓葵的好朋友，对照组的配平工具人。\n对花心浪子温衍一见钟情，深情不移，最终嫁入豪门。\n可甜文结局的背面，是浪子永不回头，是情人和私生子登堂入室，是小产后再也不能生育，是抑郁而终。\n而她的好姐妹林晓葵，却嫁给了第一财阀太子爷司凛，人人称羡。\n穿过来那天，阮棠看着镜子里灰扑扑的原主。\n再看她灵魂带来的属性点：冰肌玉骨、倾城之貌、杨柳细腰、内媚天成……\n每一样都是她原本拥有的东西，但没有气运值，一样也解锁不了。\n而这个世界的气运，集中在圣澜学院执事团的四个天之骄子身上，尤其是执事之首：司凛。\n阮棠想得很清楚：既然要蹭气运，为什么要蹭温衍那个浪子的？\n要蹭，就蹭最大的那个。\n排雷：F4贵族文学，非NP，不买股。",
    "creationStatus": 1,
    "wordNumber": 187444,
    "tags": [
      "现言脑洞",
      "现代言情",
      "系统",
      "穿书",
      "豪门世家"
    ]
  },
  "7641635688978336792": {
    "bookId": "7641635688978336792",
    "bookName": "穿成财阀太子爷的作精前女友",
    "authorName": "雀鸣灯",
    "abstract": "「腹黑男人X娇气包｜双洁、甜宠」\n穿成财阀校园文里的恶毒女配，柯眠棠接到的任务是：半年内扮演好男主的女朋友，稳定他的反社会情绪，等原书女主出场后，然后拿钱走人，功成身退。\n男主荣涉，星云集团太子爷，白名单榜首。\n表面温润如玉，骨子里偏执病态，占有欲强到令人发指。\n柯眠棠每天战战兢兢地演着娇纵女友，生怕露馅。\n可来的第一天，她就被男主亲哭了。\n系统：“问题不大，别慌。”\n她信了。\n然而男主看她的眼神越来越不对劲，并非原著里对恶毒女配的冷漠，倒像是让人后背发凉的痴迷。\n系统又说：“别怕，小说结局是男主和原书女主在一起，既定结局。”\n她放下心来。\n后来，原书女主终于登场。\n但男主对那位真命天女兴趣淡淡，反倒对前女友兴致盎然。\n柯眠棠瑟瑟发抖：说好的原著里他会爱上原书女主呢？\n-\n终于，任务结束前一晚，她满心欢喜一亿到账。\n结果系统突然失联。\n重启后，终端程序直接被篡改，从“剧情纠正”变成了“爱上男主”。\n她懵了。\n一双大手从身后掐住她的腰，男人的呼吸落在耳畔，嗓音低哑带笑：“宝贝，你知道我为了留住你，有多辛苦吗？”\n他早在她穿来的第一天就发现了真相。\n立意：黑心的财阀继承人从不做亏本买卖。",
    "creationStatus": 1,
    "wordNumber": 292497,
    "tags": [
      "现言脑洞",
      "现代言情",
      "系统",
      "穿越",
      "甜宠",
      "双洁"
    ]
  },
  "7643830276526722110": {
    "bookId": "7643830276526722110",
    "bookName": "看见弹幕时白月光回国了",
    "authorName": "妖精幸运猫",
    "abstract": "绿茶偏执阴暗男二VS温柔白月光\n温以宁从小就是人群里的月亮，温柔漂亮善解人意。高中时无数人下课挤在走廊，只为远远看她一眼，包括那个永远站在角落的沉默少年\n——陆斯年。\n后来她出国深造，那段岁月被彻底封存。\n直到某天，她的视野里突然飘过弹幕：\n——“男二好可怜，守护了女主一辈子，却从来没被爱过。”\n——“听说他有个白月光？那又怎样，白月光只是过去式。”\n——“可惜了，他注定要爱女主一生一世。”\n——“等等，白月光好像叫……温以宁？”\n她心头一震，顺着弹幕指引回国，见到了那个所谓的“男主”，也见到了陆斯年。\n陆斯年温柔体贴，是所有人眼中深情的男二，命中注定要守护原女主，爱而不得地过完这一生。\n系统告诉他：只要完成任务，就能再见到他的白月光。\n他其实找过温以宁，但世界规则像一睹透明的墙，他永远找不到她。\n而她也从来没有注意过他。\n于是陆斯年学会伪装，把偏执阴暗藏在温柔皮相之下，按部就班地扮演一个深情配角。\n只有陆斯年自己知道，所有体面都是装出来的，骨子里早烂透了。\n1.极端女主控别看，超高洁别看\n2.男主偏执阴暗，善装绿茶\n3.双处\n4.重启只为遇见你……",
    "creationStatus": 1,
    "wordNumber": 224602,
    "tags": [
      "现言脑洞",
      "现代言情",
      "系统",
      "总裁",
      "豪门世家",
      "久别重逢"
    ]
  },
  "7617768412449606718": {
    "bookId": "7617768412449606718",
    "bookName": "拜托，病娇老公是我自己求来的！",
    "authorName": "奶茶要喝杨枝甘露",
    "abstract": "害怕和陌生人接触的商姝看完一本男主是病娇的小说后发表长篇书评并祈求上天赐她一个病娇老公。\n商姝想要，商姝得到！\n为了掩盖自己病态的内心，裴时昂每次向商姝提出不正常的要求都会先想好充分的理由，但他想的那些理由一个都用不上！\n用不上的原因如下↓↓↓\n不想老婆上班接触别人的裴时昂：“别找工作了，我养你，上班……”\n商姝：行！\n不想老婆和别的男人说话的裴时昂：不要和他来往……\n商姝：行。\n不想老婆穿露背礼服的裴时昂：换一件……\n商姝：行。\n不想老婆出门的裴时昂：不出门行不行……\n商姝：行。\n每次话都没说完老婆就答应了，老婆好爱他！",
    "creationStatus": 1,
    "wordNumber": 157518,
    "tags": [
      "现言脑洞",
      "现代言情",
      "系统",
      "穿越",
      "先婚后爱",
      "病娇"
    ]
  },
  "7640410171792968728": {
    "bookId": "7640410171792968728",
    "bookName": "穿成耽美文小受的炮灰妹妹",
    "authorName": "水中观玉",
    "abstract": "【万人迷+微微强制雄竞+伪弯掰直+弹幕戏份多+男全洁】\n温情醒来后发现自己成为了一篇耽美虐文里主角受没血缘的炮灰妹妹\n文中主角受被虐身虐心，和攻恨海晴天\n而她作为推动剧情的工具人需要在必要的时候下线成为主角受黑化的契机\n然后攻受继续纠缠，而她则被众人渐渐遗忘\n温情不想落到这样的结局，于是为了活下去她只能主动破坏剧情\n一次次下来，她最终看到了破防的弹幕，互相敌对的攻受，还有不断上涨的喜爱值\n温情对此觉得满意\n但在她不知道的是，在她看不到的地方，攻受看她的目光却越来越不对劲\n尤其是主角受\n温情完全懵了，看到依旧黑化了的主角受，她心里满是问号\n不过她很快没时间多想了，因为她已经……\n",
    "creationStatus": 1,
    "wordNumber": 182623,
    "tags": [
      "现言脑洞",
      "现代言情",
      "系统",
      "穿越",
      "穿书",
      "魂穿"
    ]
  },
  "7624784956866186264": {
    "bookId": "7624784956866186264",
    "bookName": "恶毒女二被男主错认成女主后",
    "authorName": "朝来露雨",
    "abstract": "【现言甜宠/日常向/双洁/男主逗比脑补帝/女主吐槽大师】\n十八岁那年，虞晚发现自己是一本小说里的恶毒女二。\n她虚荣、拜金、挥金如土，最后被继兄男二指着鼻子骂吸血鬼、寄生虫。\n——最后，她被赶出豪门，惨死街头。\n……不行！恶毒女二也要自力更生！\n于是虞晚拒绝了豪门的每一分钱，开始打工。\n直到有一天，她正在咖啡店洗杯子，突然听见了男主的心声：\n【系统，你确定是她？】\n【宿主，根据原著简介描述，‘A大最美最穷的女生’就是本书女主。虞晚又穷又美！她一定是女主！】\n【你确定，她就是我命中注定的另一半？】\n【宿主，我十分确定！你，李熠，是这本小说的男主。她，虞晚，是这本小说的女主。】\n【你们就是天造地设的一对！】\n虞晚：……？\n天呐！男主把她一个恶毒女二错认成女主了！\n——\n当李熠又一次疑惑女主的好感度加的这么慢后，系统提出了疑问：\n【宿主，有没有可能，我们找错人了？】\n【想什么呢！】李熠冷哼：【要是女主这么好攻略，凭什么当女主？】\n他转头，看向虞晚的目光炯炯有神：\n【不愧是我命中注定的女人，就是与众不同！】",
    "creationStatus": 0,
    "wordNumber": 228024,
    "tags": [
      "现言脑洞",
      "现代言情",
      "系统",
      "甜宠",
      "豪门世家",
      "双洁"
    ]
  },
  "7639999012308798526": {
    "bookId": "7639999012308798526",
    "bookName": "哭大点声，我听不见",
    "authorName": "婳宁她姓沈",
    "abstract": "【极限求生倒霉蛋VS假正经真重欲大反派】\n【强制爱+病娇+系统+性张力拉扯+双洁he】\n穿成恶毒女配的第五年。\n在云荞把大反派沈溯危得罪了个彻底之后，系统突然改变任务：\n【一个月内，让大反派爱上你并答应和你结婚。】\n云荞：？？？这可能？\n为了活命，云荞还是硬着头皮各种撩拨、讨好、甚至下药。\n可使尽了浑身解数，对方都无动于衷。\n本以为要失败了，没承想，只是临死前去见了下男二，转头云荞就失去了意识。\n醒来时。\n耳边吐息灼热逼近，声音低哑到发颤：\n“不是说喜欢我吗，为什么要见他？为什么对他笑？”\n任务结束那一天。\n“想和我结婚？可以啊。”\n任务结束一周后。\n“你刚才应该不是要逃跑吧？”\n“宝宝那么喜欢我，肯定不会抛弃我的，对吗？”\n任务结束一个月后。\n“宝宝，是不喜欢我了吗？”\n“还是说，”拇指缓缓摩挲她的唇瓣，声音温柔，却令人毛骨悚然，“一直在骗我？”\n“宝宝想好了再回答哦。”\n任务结束半年后。\n“宝宝怎么还不死心呢。”\n浴室里，他声音叹息，扣着她的后颈，呼吸带着愉悦的颤栗：\n“不是要攻略我吗，继续啊……”\n“宝宝，哭大点声…”\n“我听不到。”\n（文案只是一部剧剧情，死遁梗依旧会有）\n（不黑原女主）\n",
    "creationStatus": 1,
    "wordNumber": 217490,
    "tags": [
      "现言脑洞",
      "现代言情",
      "系统",
      "病娇",
      "双洁",
      "攻略反派"
    ]
  },
  "7611568734850780222": {
    "bookId": "7611568734850780222",
    "bookName": "不怼！阴湿女配怎么被男主盯上了",
    "authorName": "温言久",
    "abstract": "【双洁穿书+女主回归+网恋翻车+猫鼠游戏】【评分刚出，后面会涨！入股不亏哦~】\n【怂且自恋小太阳妹宝vs恶劣真阴湿皮肤饥渴症男主】\n闻眠是个怂包，上辈子救小女孩横死马路，本以为能升天堂，结果穿进一本大学校园文，成了痴恋男主的阴湿女配。\n原主做过的好事包括：跟踪男主、视奸男主、收集男主衣物、网上发骚扰短信。最终惹怒男主，被扔进公海里喂鲨鱼。\n最怕水的闻眠：！！！\n好在原主还没有过度招惹男主，她打算远离男女主安心躺平，却被剧情修正系统888绑定，不按原著走就会回到马路牙子横死街头。\n为了活命，她咬牙完成任务：线上给男主的弃号发骚扰信息，线下狼狈跟踪。\n反正男主早就不用那个微信号了，她只要演到任务结束就行。\n直到某天，那个被废弃的账号突然弹出一条消息：\n“？”\n--\n楚聿州早就发现了那个嘴上说喜欢、一见他就躲的小怂包。\n像只胆小的猫，伸出爪子试探，又随时准备缩回去。\n她以为自己在两个身份间反复横跳演得滴水不漏，他只觉得有趣。\n线上叫他哥哥撒娇，线下叫他学长。\n他一直想看看，这只猫什么时候才会发现自己早已掉进陷阱。\n直到某天，他想要更进一步的时候，那只小猫却连夜跑了。\n楚聿州捏着她手腕，眼底阴郁：\"不是说最喜欢我吗，跑什么？\"",
    "creationStatus": 1,
    "wordNumber": 274664,
    "tags": [
      "现言脑洞",
      "现代言情",
      "校园",
      "系统",
      "穿书",
      "双洁"
    ]
  },
  "7650882559328406553": {
    "bookId": "7650882559328406553",
    "bookName": "直播间每人每天给我一百块",
    "authorName": "山里山狸",
    "abstract": "刚开分会涨，入股不亏【直播+神豪+变美+逆袭+打脸+爽文+万人迷+雄竞修罗场+男全洁】\n简苏270斤，人丑声甜，是甜心语音厅的女主播，丑照被网恋对象曝光后——\n昔日给她刷礼物的大哥纷纷退款，网友辱骂她、给她p丑图，语音厅以违约为由勒索天价赔偿费。\n即将退网之际，她突然绑定了个“直播间每人每天给我一百块系统”\n“只要有人点进直播间，不管是黑粉还是路人，通通返现一百块！一人一百，上不封顶！”\n简苏果断开播！疯狂挑衅黑粉！\n开播第一天，收入一百万…\n开播第二天，她买房了…\n开播第三天，神豪哥给她怒刷百万…\n【恭喜主播，达成直播间万人成就，获得抽奖机会一次！】\n【恭喜主播，抽中减肥沐浴露一瓶！越洗身材越棒！】\n【恭喜主播，获得神颜水！】\n【恭喜主播……】\n播着播着，她拥有完美的身材，绝美的脸蛋，天籁的歌喉，和数不清的老公粉…\n后来简苏一开播，直播间百万人。\n一招手，无数华子升空！\nPS：究极爽文，内含大量打脸，掉马，修罗场情节，女主万人迷来的，胖的时候就有大哥抢着刷礼物",
    "creationStatus": 1,
    "wordNumber": 244131,
    "tags": [
      "现言脑洞",
      "现代言情",
      "系统",
      "直播",
      "虐渣",
      "打脸"
    ]
  },
  "7641848767729110078": {
    "bookId": "7641848767729110078",
    "bookName": "她又结婚了？",
    "authorName": "小丫么小刺花",
    "abstract": "顾浓每次拿离婚证那天，民政局门口都停满了豪车\n各行各业的优质男人，为这个老实本分，恪守道德的女人哐哐撞大墙！\nAAA建材王总带着他几蛇皮袋的房产证向你走来\n科技巨贵的迈巴赫后备箱里放着给你准备的50斤五金\n青春洋溢的弟弟默默掏出自己最新的体检报告\n哦，还有做地产的，搞空运的，卖石油的，造加特林的......\n当他们争先恐后\n你将如何选择\n————————\n做老实女人，享不平凡人生",
    "creationStatus": 1,
    "wordNumber": 227045,
    "tags": [
      "现言脑洞",
      "现代言情",
      "系统",
      "总裁",
      "豪门世家"
    ]
  },
  "7648307083388931096": {
    "bookId": "7648307083388931096",
    "bookName": "全家惨死后，她从末世杀回来了",
    "authorName": "九离九离",
    "abstract": "（无CP，有异能和空间，女主智商武力双在线，步步揭秘，复仇不隔夜，杀伐果断不圣母，全程暴爽无虐。）\n时家上亿资产被霸占，父母被敲碎全身骨头折磨致死，姐姐更是被数十人凌辱后推下六楼伪装成自杀。\n时愿，极品供体，15岁被送上岛屿当了三年猎物，18岁生日这天，是她无比惨烈的死期。\n所有人都以为时家彻底被瓜分，那些吃着时家人血馒头的禽兽正在帝都举办庆功宴。\n直到那个本该死在手术台上的少女，带着一身极致战力，手提染血长刀，炸穿孤岛，重回内陆时……所有的复仇才刚刚开始。",
    "creationStatus": 1,
    "wordNumber": 181536,
    "tags": [
      "现言脑洞",
      "现代言情",
      "无敌",
      "无CP",
      "虐渣",
      "黑化"
    ]
  },
  "7598215355617512472": {
    "bookId": "7598215355617512472",
    "bookName": "高危漫画路人自救指南",
    "authorName": "水微W",
    "abstract": "【无CP万人迷+迪化+原创漫画+论坛体】\n【如果你突然发现，自己是高危漫画中必死的普通路人，你要如何自救？】\n*\n江时一直不信鬼神，直到她的房客像蜘蛛一样用八条腿趴在天花板上，对她露出痴迷的微笑。\n她的世界观崩塌了。\n机缘巧合，她拥有了看到漫画的能力，\n好消息：漫画介绍了怪物的弱点：吃掉“爱人”后会由于心情低落陷入虚弱状态\n坏消息：这个怪物好像爱上她了……\n\n好不容易活下来的江时打开漫画，读者竟然认为怪物是她饲养的、弱小可怜又破碎的她怎么会是幕后大BOSS——你们糊涂啊！！\n漫画中的人气角色也怪怪的：\n“接下来您有什么打算……”一刀砍下怪物脑袋的狠人男主小心翼翼地询问她\n江时困惑地微微歪头，问我吗？\n“我明白了……但您真的没必要事事为别人考虑。”男主用敬佩的目光注视着她。\n不兑！？你明白了啥？我不明白啊！！\n“您不需要再掩饰了，您为这个世界做的已经够多了。”少女坚定地将她护在身后，“这次，换我保护您。”\n啊？我做了什么吗？\n阴郁厌世反派目光复杂地注视着她，“罢了，若您执意要守护这个世界……”\n*\n众人：您是污浊世界的太阳／指引希望之人／人类最强\n江时：不要再脑补了！是路人不是救世主啊！",
    "creationStatus": 1,
    "wordNumber": 135496,
    "tags": [
      "现言脑洞",
      "现代言情",
      "幻想言情",
      "无CP"
    ]
  },
  "7654225801818164286": {
    "bookId": "7654225801818164286",
    "bookName": "卡皮巴拉穿越恶毒女配成团宠了？",
    "authorName": "初九大米",
    "abstract": "【雄竞修罗场+佛系女主+全洁+团宠+上位者低头+HE+青春校园】\n动物园里的一只幼年雌性卡皮巴拉穿书了\n好消息：穿成人了\n坏消息：穿成了全校黑、疯狂倒贴F4的恶毒女配怎么办？\n系统在脑子里疯狂尖叫：“拿下男主！重振你恶毒女配的雌风！”\n林晚慢吞吞掏出一块小熊饼干：“哦，卡皮巴拉没有竞争。”\n身为一只穿书的尊贵卡皮巴拉，她的毕生追求只有：干饭、泡澡、睡觉。至于那四个难以攻略的财阀少爷？\n林晚：“我只想干饭睡觉和泡澡。”\n全校都等看林晚退学的笑话，F4更是见她就恶心。\n可后来，画风怎么越来越不对劲？\n洁癖强迫症高冷会长，将她圈在角落里疯狂贴贴：“逃课去睡觉？不如在我怀里睡。”\n阴郁顶流少爷将她堵在后台：“不看我的舞台没关系，只看着我好不好？”\n情感缺失的医学天才，把她写满观察日记：“我因为你学会了感情。”\n连最暴躁的财阀恶少，也乖乖蹲在她脚边递上零食：“吃的给你，你给我，行吗？”\n面对争风吃醋的四个大佬。\n林晚：“那个、能让我先吃个饼干睡一觉吗？”\n【情绪极度稳定的佛系卡皮巴拉女主 × 疯狂自我攻略疯批男团】\n不争不抢，岁月静好，系统气炸，大佬折腰！反向钓系，极致甜宠！",
    "creationStatus": 1,
    "wordNumber": 217155,
    "tags": [
      "现言脑洞",
      "现代言情",
      "校园",
      "穿越",
      "团宠",
      "HE"
    ]
  },
  "7641990468129016857": {
    "bookId": "7641990468129016857",
    "bookName": "恋爱脑能传染？幸好我是个神经病",
    "authorName": "残烛跳荡",
    "abstract": "沙雕抽象玩梗➕读心➕自我攻略\n姜灵焕穿成古早贵族学院文中的舔狗炮灰，绑定“反恋爱脑”系统，靠阻止书中cp传染恋爱毒气续命：\n追妻火葬场cp，霸道少爷用广播强势示爱，全校磕爆，恋爱毒气浓度暴涨！\n姜灵焕把广播示爱爆改英语听力，全校瞬间萎掉：？这是什么脏东西！\n偶尔也打击校园非文明恋爱行为：\n有人当众激吻，她将乒乓拍精准扔到两人嘴巴之间：“图书馆不是你们的大床房。”\n有人泳池放肆爱，她举着插电的插线板放在泳池边：“再不出来，让你们做亡命鸳鸯。”\n有人偷摸调情，她牵着十几条狗冲进去：“别在小树林法天法地！墙对面是幼儿园！”\n…\n全校恋爱脑：姜灵焕是地狱来的魔鬼！！\n-\n姜灵焕经常被书中“恋爱毒气”侵扰，清醒值也跟着下降，一下降就疯狂想谈恋爱。\n后来，她发现待在学生会主席谢风叙身边，下降速度就能减缓，跟他触碰一下，就能立即回血！\n于是，姜灵焕把谢风叙当充电宝，变着花样跟他制造接触。\n谁曾想谢风叙不仅有皮肤饥渴症，还能听见她的心声，还只能听一半！\n她内心：他手好大，感觉能一把握住我的头。胸肌练得不错。\n他听到：他手好大，感觉能一把握住我的…胸，不错。\n谢风叙：？她好变态\n姜灵焕：？我冤枉啊",
    "creationStatus": 1,
    "wordNumber": 274616,
    "tags": [
      "现言脑洞",
      "现代言情",
      "校园",
      "系统",
      "穿越",
      "搞笑轻松"
    ]
  },
  "7645410819764669502": {
    "bookId": "7645410819764669502",
    "bookName": "捞女主播她自带神豪马甲！",
    "authorName": "任雪",
    "abstract": "评分低是因为刚开！后续会涨到9以上！\n【女本位+直播＋神豪马甲+无cp＋变美+万人迷男女通杀＋搞钱】\n夏弥是个美貌配不上自身野心的女人，她努力挣钱，想做自己的女娲（后天变美）。\n一朝神豪系统降临，她终于有机会实现无痛变美，利用神奇物品一步步提升自己。\n至于打赏额度，为什么要给那些臭男人刷？她要把每一分钱都花在自己身上！\n从不露脸开始，语音厅主播、团播、个播，她要一步步走到屏幕前，要世人都见证她的荣耀！\n请叫我——野心家！\n大量必看排雷！\n一：主事业线，很多老公粉，女主但求荣华富贵，不求一丝真情，全程不掉马，马甲伪水仙（戏份中等）\n二：女主道德有瑕疵，会养鱼，介意勿入。\n三：男角色身心全洁，正文全员单箭头，番外多线1V1HE，但会在梦境里恋爱互动（入梦卡）\n四：有虐男桥段\n五：大量主播竞争pk情节，女对手也有，事业上的良性竞争。\n六：神豪系统偏现实向，前期额度低\n七：女主很爱美，爱美是为了事业和自己的野心。\n八：弥宝做什么都是对的！\n作者女宝亲妈，已有百万完结书，许愿追更，养肥会饿死。゜゜(´Ｏ`) ゜゜。",
    "creationStatus": 1,
    "wordNumber": 298773,
    "tags": [
      "现言脑洞",
      "现代言情",
      "系统",
      "直播"
    ]
  },
  "7650314635018521625": {
    "bookId": "7650314635018521625",
    "bookName": "狐狸精下山，顶级万人迷训狗守则",
    "authorName": "骑驴点灯",
    "abstract": "刚开分，会涨【钓系万人迷 + 诱而不自知 + 修罗场 + 上位者为爱低头 + 1vn + 纯欲系笨蛋美人 + 改造变美（含网恋、高干元素）】\n\n因暗恋舍友的高富帅男友而声名狼藉的乡下普女胡宝芝，机缘巧合下……\n\n被一只刚刚下山的狐狸精取代了身体。\n\n众所周知，狐狸精要吃男人的阳气才能活。\n\n初出茅庐的小狐狸精宝芝在努力学习当一个女大学生的同时，也开始了自己的寻找口粮之路。\n\n高冷学霸、电竞男神、封建大爹总裁、权势滔天的京三代…\n\n这些口粮们开始都看不上她，最后却都红着眼质问宝芝为什么要抛弃他们。\n\n宝芝却只能无辜地眨眨眼睛。\n\n再好吃的东西吃久了，也会腻的，不是吗？\n\n每个曾拥有过宝芝的男人都以为自己能与她天长地久。\n\n总之妹宝走到哪撩到哪，天然渣属性。\n男主不是在当小三就是在打小三的路上。\n\n本文两个地图：\n京市篇：校园背景（包含文案中出现的男嘉宾）\n沪市篇：都市背景（男嘉宾待解锁中…）",
    "creationStatus": 1,
    "wordNumber": 170576,
    "tags": [
      "现言脑洞",
      "现代言情",
      "校园",
      "总裁",
      "幻想言情",
      "学霸"
    ]
  },
  "7629229367456959513": {
    "bookId": "7629229367456959513",
    "bookName": "穿成动物后我萌翻全网！",
    "authorName": "巨龙啊",
    "abstract": "动物文｜1v1 | 团宠｜萌晕｜日常爽 | 人类观察动物\n蓝小小病重，过生日她吹蜡烛许愿：希望下辈子投胎不当人了。\n再睁眼——她成了国宝大熊猫幼崽！！\n母亲还是野培大熊猫！附近山林里还有一群观察的研究员！\n既来之则安之，喝奶，爬爬，等长大点就可以吃笋！熊生美滋滋！\n直到隔壁来了一头大熊猫！\n蓝小小每天都提心吊胆，怕它跟妈妈打架！\n结果它真闯进来了！\n没打架，没抢领地，而是直奔她这只幼崽，把她翻来覆去，拍了拍，舔了舔，还疯狂投喂笋尖尖！\n蓝小小被玩懵了。\n这断视频被传到网上爆火，全网围观，网友感动落泪：隔壁女邻居母性真强！\n科考队点头：这肯定是一头雌性熊猫，母性很强！\n蓝小小看着它胯下的蛋蛋，陷入沉思……\n你们管这叫雌性？！！\n雄性大熊猫不懂什么是童养媳，熊熊只知道宝宝很可爱！想撸，想亲，想投喂！\n……\n蓝小小：小小的世界，大大的能量！\n……\n［全网爆火：雄性大熊猫带崽！］\n［网红比格大王，永远保持赏味期！VS网红边牧，全网智商最高狗狗！］\n［草原巨人大象！］\n［海洋街溜子虎鲸！］\n［……］\n（女主男主永不变人！一直都是动物快穿！不会生崽！）",
    "creationStatus": 1,
    "wordNumber": 297885,
    "tags": [
      "现言脑洞",
      "现代言情",
      "穿越",
      "团宠",
      "1v1",
      "魂穿"
    ]
  },
  "7638281502991584318": {
    "bookId": "7638281502991584318",
    "bookName": "谁懂！3S精神力在星际浪疯了！",
    "authorName": "李杳晚",
    "abstract": "评分刚出，后期会涨的！\n【1VN男全c】【无脑吃饭】【爱细节描写】【风格多样】【升级】\n21世纪牛马白染，每天沉浸在星际文中不可自拔，想出演几集，终于身穿了！\nSSS级精神力在星际疯狂爽！\n白狮少将、白虎太子、雪豹少将、银狼护卫长、金丝雀老师、狐狸年下弟弟通通都是笼中物！\n她的到来是流光星域千年的期盼，原来命运早就写好了...",
    "creationStatus": 1,
    "wordNumber": 292692,
    "tags": [
      "现言脑洞",
      "现代言情",
      "幻想言情",
      "穿越",
      "星际",
      "无脑爽"
    ]
  },
  "7649762798997621822": {
    "bookId": "7649762798997621822",
    "bookName": "变美：好热，你这系统正经吗？",
    "authorName": "不吃苦瓜123",
    "abstract": "［直播+1vn+雄竞+万人迷+男洁］\n送外卖的第五天，乔薇被车撞了，但戏剧性的是，在身体腾空而起的那一刻她绑定了［逆袭人生］模拟器。\n乔薇知道，她改变命运的机会终于来了。\n减肥、变美、直播，就在生活变得越来越好时，系统发布的任务却越来让人心跳失控、浑身燥热。\n很久很久以后……乔薇才惊觉，这丫的根本就不是啥正经模拟器！",
    "creationStatus": 1,
    "wordNumber": 192560,
    "tags": [
      "现言脑洞",
      "现代言情",
      "系统",
      "直播"
    ]
  },
  "7643312326749195326": {
    "bookId": "7643312326749195326",
    "bookName": "黑粉美貌惊人！大佬们关我小黑屋",
    "authorName": "深渊XD一y",
    "abstract": "【万人迷+1VN+顶级修罗场+自我攻略+白切黑+男洁+软萌娇气包】\n熬夜追更，姜染穿成书中头号黑粉。\n群发粉丝群炸裂造谣后，男主正顺着网线杀过来。\n系统说：演好人前甜妹、背后恶毒阴湿女配，熬到结局就奖励十亿加别墅。\n她牙一咬：我演。\n财阀男神踹开她家门，看到她火气全消：“你那么单纯无辜，不可能做出造谣的事。”\n腹黑总裁轻咬她耳垂：“那些照片…你最好留着慢慢看。”\n阴湿权贵将她抵在墙角：“偷窥我不行？试试？”\n京圈太子爷掐着她腰，声音沙哑：“钓一个不够，还群发？”\n说好的全网封杀、法律制裁呢？\n怎么一个两个都红着眼要关她小黑屋？\n她终于意识到——这群男人追杀的从来不是黑粉，而是她本人。\n系统给的剧本，每一页都写着：引狼入室。\n你以为的穿书：黑粉作妖 | 实际上的穿书：猎人对猎物说——逮到你了\n高亮预警：\n✓ 黑粉女主翻车实录\n✓ 修罗场×反套路×极限拉扯\n“——跑？晚了。”",
    "creationStatus": 1,
    "wordNumber": 174717,
    "tags": [
      "现言脑洞",
      "现代言情",
      "位尊权重",
      "大佬",
      "穿书",
      "系统",
      "白切黑"
    ]
  },
  "7642394220224859161": {
    "bookId": "7642394220224859161",
    "bookName": "星际强宠：大佬的五个疯批好难哄",
    "authorName": "芝士槑槑",
    "abstract": "评分刚出【兽世＋1vN＋雄竞＋训狗日常+男全洁＋哑巴老公+团宠＋女主自带金手指＋哥哥追妻火葬场】\n\n　　夏乔被丧尸给咬死了！\n\n　　再一睁眼，她成了寰宇陆家的假千金，假千金作天作地，尽干一些上不了台面的事情，还是个不折不扣的零精神力废雌。\n\n　　被赶出门，被未婚夫退婚，终端匹配的五个兽夫对她也是避之不及。\n\n    “∞”特殊精神等级，这个说她强，那个说她废，总之是应了那句：骂她的人从地球排到了火星！！！\n\n　　没关系，都没关系。\n\n　　强者从不抱怨环境，因为她们可以改变环境。\n\n　　后来？\n\n　　击杀榜第一：夏乔！\n\n　　边陲星土皇帝：夏乔！\n\n　　星域军事最高指挥官：夏乔！\n\n　　你问那五只？\n\n　　萌萌黑王蛇歪头，傲娇小白鹇摆尾，纯中带萌的犟种猫猫哼唧背身，龙王Daddy头戴小花帽，以及追妻火葬场的哥哥齐齐回头：“妻主大人拍好了吗？”\n\n　　夏乔：拍好了，名字就叫《星际强宠，大佬的五个疯批好难哄！》\n\n　　哈？\n\n　　他们...\n\n　　难哄？！",
    "creationStatus": 1,
    "wordNumber": 215232,
    "tags": [
      "现言脑洞",
      "现代言情",
      "星际",
      "团宠",
      "大佬",
      "追妻火葬场"
    ]
  },
  "7598851423186471998": {
    "bookId": "7598851423186471998",
    "bookName": "神豪：渣女诱男双修手册",
    "authorName": "煌喵",
    "abstract": "【渣女＋女强＋无三观＋多男全洁＋虐男＋强制＋爽文】\n有私设，具体看第一章有话说。\n主角种族非人类，因为本体原因，修炼需要很多咳咳.......精气。\n女主利己主义，有肌肤饥渴症，走肾不走心，还有不要心疼男人，除了某些时候会让他们受点苦，其他时候他们爽爆了！！\n因为玩弄了天道的儿子，大妖唐绾在渡劫时被公报私仇，被天雷劈毁肉身的瞬间来到现代世界，为维持生命强弄了一个男人后，莫名其妙的绑定了神豪系统.......\n从此以后，清冷学霸，精致美少年，禁欲系高岭之花，温柔包容年上，温文尔雅斯文败类，高冷电竞男神........\n全都成了她修炼升级的工具。\n简介无力，不太会写简介.......",
    "creationStatus": 1,
    "wordNumber": 173261,
    "tags": [
      "现言脑洞",
      "现代言情",
      "青梅竹马",
      "女强",
      "系统",
      "穿越",
      "幻想言情"
    ]
  },
  "7641540435936021529": {
    "bookId": "7641540435936021529",
    "bookName": "穿成男频文男主的虚荣妹妹",
    "authorName": "折花枝换酒钱",
    "abstract": "【双洁+系统】\n任柚穿书了，穿成了假冒男主救命恩人的炮灰女配。\n　　为了报答恩情，男主承诺以后会将女配当做亲妹妹看待。\n　　有了男主妹妹这个身份之后，原主作威作福，铺张浪费，把能得罪的人给得罪了个遍。\n　　最后事情败露，得到了一个被众人厌弃、贫困潦倒的下场。\n　　……\n　　穿过来的时候，原主已经把男主给得罪狠了。\n　　救命之恩的功劳已经冒领。\n　　其他的谎也撒了一个又一个。\n　　为了保命，任柚没办法，只能继续哄，继续骗。\n　　每天哥哥长哥哥短，天天把哥哥挂嘴边。\n　　于是，男主身边亲近的朋友渐渐知道了，男主多了一个黏人嘴甜的妹妹，会哄人，会撒娇。\n　　……\n　　后来，冒充救命恩人一事还是曝光了，任柚忐忑不安地等着被清算。\n　　她想，她当了这么久的乖巧妹妹，有没有一点可能，她还是继续给男主做妹妹呢？\n　　结果下一秒，她就听到男主说，“其实，我早就不想当你哥哥了。”\n　　任柚：？？？\n　　“我只想做你的男朋友。”\n　　任柚：！！！\n　　……\n　　小剧场：\n　　朋友聚会，有朋友调侃，“你之前不还说你这个异父异母的假妹妹谎话连篇嘴里没一句真话？现在什么情况？”\n　　凌序棱语气淡淡，“但是她只骗我一人，只哄我一个，这不是爱又是什么？”",
    "creationStatus": 1,
    "wordNumber": 123035,
    "tags": [
      "现言脑洞",
      "现代言情",
      "系统",
      "穿越",
      "双洁",
      "魂穿"
    ]
  },
  "7645616954404768793": {
    "bookId": "7645616954404768793",
    "bookName": "她才不要嫁给一个臭卖鱼的！",
    "authorName": "妺娘",
    "abstract": "她是谁？千亿集团夏氏千金、夏泡芙诶！\n　　含着金汤匙出生的大小姐，老总夏业为的独生女，住在宫殿一样的庄园里，每天吃着空运来的新鲜食物，光照顾她的佣人就有上百人。\n　　夏泡芙是家里的掌上明珠、尊贵无比，备受宠爱，养成了作天作地的肆意性格，那又怎么样，夏家有这个资本。\n　　然而有一天，她亲爹突然要把她嫁给一个住小岛破屋卖鱼的贫民。\n　　夏泡芙将大小姐脾气全撒到她丈夫身上，骑在丈夫头上作威作福，男人长得虎背熊腰，就是个臭卖鱼的。\n　　一个没用、寡言少语，但开口会惹她生气的臭男人！\n　　丈夫由着她作天作地，打不还手，骂不还口，除了精力格外旺盛，除了是个臭卖鱼的，退一千万步来说，也，也不是不能接受。\n　　然而，渐渐的，夏泡芙发现，她身处的世界变得古怪，而她的丈夫也有些诡异。\n　　她的丈夫好像不是人类……\n　　一些灵异事件发生了，她的丈夫好像是诡……她的丈夫杀人……她的丈夫有奇怪的力量……\n　　丈夫抓回来要逃跑的小妻子，沉声哄着：“由着你作了，不许跑。”\n　　作精娇气漂亮美人大小姐x诡异强大凶狠装老实男人\n　　（女主作天作地，超级能作。）",
    "creationStatus": 1,
    "wordNumber": 133897,
    "tags": [
      "现言脑洞",
      "现代言情",
      "幻想言情",
      "豪门世家",
      "大小姐",
      "作精"
    ]
  },
  "7650296368858156094": {
    "bookId": "7650296368858156094",
    "bookName": "穿成心机白月光，钓疯男主",
    "authorName": "七笺光",
    "abstract": "无三观/女主永远被偏爱/破镜重圆/清醒沉沦/女主胎穿，是男主真正意义上的初恋白月光\n\n　　【你是古早虐文里，曾抛弃过男主的心机白月光，为了维持世界不被崩坏，您必须维持主线剧情，让男女主达成he结局。】\n\n　　宋茉妍本是大渊朝最受宠的公主，终于熬到同胞弟弟登了基，自己荣升成了所欲为的长公主，还没来得及享受，便因一场刺杀胎穿到了现代。\n\n　　刚回国，便被系统告知自己是书中女配，还得维持主线剧情。\n\n　　任务她接了，但……\n\n　　她，堂堂长公主，宋氏集团千金，要给别人当爱情路上的踏脚石？\n这怎么行？\n　　那不能够呀！\n　　世界男主＝顶级资源。\n　　后宫生存法则：若想得到什么，就得去争、去抢。\n\n　　宋茉妍和女主同时生病。\n乔舒然拉着男主苦苦哀求：“阿衡，别走，留下来陪陪我好吗？”\n　　男主：“别闹，生个病而已，你向来坚强懂事，吃个药自己睡一觉就好了。”\n　　“茉莉和你不一样，她身体娇弱，从没吃过苦，没我陪着不行。”\n\n　　宋茉妍装病将沈序衡叫走。\n　　乔舒然咬牙：“你明知道她是装的，为什么还要信她？”\n　　沈序衡：“她能为了我费尽心思装病，证明她爱我、需要我。”",
    "creationStatus": 1,
    "wordNumber": 98182,
    "tags": [
      "现言脑洞",
      "现代言情",
      "系统",
      "豪门世家",
      "破镜重圆",
      "胎穿"
    ]
  },
  "7643069756320255001": {
    "bookId": "7643069756320255001",
    "bookName": "穿成拜金心机漂亮小青梅炮灰女配",
    "authorName": "东风啊",
    "abstract": "苏念穿书了，一来就怒欠几百万，很快要吃牢饭，想一头撞死。\n系统：宝宝，你先别死，你的强来了。\n苏念是个拜金虚荣网骗漂亮炮灰女配。\n有钱的青梅竹马钓着她。\n她钓着网友，还钓了好几个，凭实力借了几百万就是不还，就是想作死。\n苏念和男主在玩同一个游戏，是男主唯一的徒弟 。\n发现男主身份不一般之后，就骗男主和她结婚。\n她骗男主说，和男主结婚只是为了做夫妻任务，对他绝对没有意思。\n她是对男主没意思，但是，对男主的钱有意思 。\n男主一开始很满意游戏里苏念这个听话的小徒弟，不会纠缠他的情缘。\n但是，她怎么总是围着他兄弟打转，还一直给他们送这送那？\n她是不是忘了。\n他才是她的师傅。\n他才是她唯一的情缘。\n男主提出面基，吓得苏念要离婚。\n气的男主一个仰倒，感觉头顶绿油油的。\n“你是不是外面有狗了？”\n苏念：“没狗，我有个很狗的青梅竹马。”\n男主醋疯了：“叫什么名字？”\n苏念：“那不能告诉你，你知道他的名字肯定就知道我了，我又不傻。”\n男主威胁：“你给我等着。”\n苏念：“离婚。”\n男主跪下：“对不起老婆，我错了。”\n苏念立刻滑跪：“师傅，求求你饶了我吧，我不网恋。”\n男主：“我也不网恋，我们实恋”",
    "creationStatus": 1,
    "wordNumber": 196792,
    "tags": [
      "现言脑洞",
      "现代言情",
      "位尊权重",
      "青梅竹马",
      "甜宠"
    ]
  },
  "7650436144575826969": {
    "bookId": "7650436144575826969",
    "bookName": "都修仙了，谁还当恶毒女配？",
    "authorName": "珠珠小鱼干",
    "abstract": "（评分刚出，会涨的）（爽文+打脸+多重生+大女主）\n林娇，一个无父无母的实习生，被秃头上司剽窃设计稿，被威胁“不听话就滚蛋”，被生活逼到走投无路。\n\n上一世，她选择爬上大老板苏砚的床——搞风搞雨，作天作地，正牌白月光归来后，看不清地位针对白月光，最后她像垃圾一样被扫地出门，冻死在寒冬街头。\n\n重生归来，同样的绝境，同样的选择摆在面前。\n\n这一次，她在卫生间里没有急着去爬床，而是低头看了一眼手机——\n\n一款她差点遗忘的种田修仙小游戏，弹出一条提示：\n\n「洗髓丹已合成完毕，是否收取？」\n\n她手一抖，点了“收取”。\n\n一颗真正的丹药，凭空出现在她掌心。\n\n从这一刻起，林娇的世界天翻地覆。\n\n她不爬床了，不跪了，不忍了。\n\n怼秃头上司，截获被下药的苏总，开口就要感谢费——腰杆挺得比谁都直。\n\n再后来，虫族入侵，林娇身后站着的是：已经修炼到大乘期（化神期……）的无数龙国同胞，以及从跨越时空而来的祖宗们……\n",
    "creationStatus": 1,
    "wordNumber": 187087,
    "tags": [
      "现言脑洞",
      "现代言情",
      "系统",
      "幻想言情",
      "重生",
      "虐渣"
    ]
  },
  "7654990870877326361": {
    "bookId": "7654990870877326361",
    "bookName": "成五爪金龙幼崽，萌翻全网举国宠",
    "authorName": "织语画",
    "abstract": "（动物文）（团宠）（全网直播）（萌系神明）（国家级饲养）（不会变人）\n沈漪期末周第四个通宵，猝死在图书馆。\n再睁眼，她成了一条巴掌大的五爪金龙幼崽！！\n金色鳞片，透明利爪，还会喷火！\n既来之则安之，啃蛋壳，晒太阳，等长大了腾云驾雾！龙生美滋滋！\n直到一个户外主播把镜头怼到了她脸上。\n三千人在线，亲眼看她打了个喷嚏烧掉一片树叶，又用尾巴毁灭证据，然后装死。\n这段视频传到网上全球爆火，举国震动！\n最高层拍桌子：她是华夏五千年的信仰！不是研究对象，是客人！谁敢提\"切片\"两个字，上军事法庭！\n沈漪被供得五迷三道，终于大发慈悲在平板上写下第一句话。\n“饿了。”\n全场两百名顶尖科学家：…………\n张教授（含泪怒吼）：大道至简！这是在测试我们的供养诚意！快上五十公斤顶级雪花牛排！！！\n沈漪叼着蓝鳍金枪鱼大腹，尾巴尖愉快地扫来扫去。\n挺好的，这帮人类，还算识相。",
    "creationStatus": 1,
    "wordNumber": 196819,
    "tags": [
      "现言脑洞",
      "现代言情",
      "幻想言情",
      "重生",
      "直播",
      "团宠"
    ]
  },
  "7605202501763091481": {
    "bookId": "7605202501763091481",
    "bookName": "失踪六十年的妹妹从修仙界回来了",
    "authorName": "摆烂的绿宝",
    "abstract": "【无cp，爽文，抓鬼，灵异，女主最强，超级护短，睚眦必报！】\n　　黎昭本是南城首富千金，在她十六岁生日那天，莫名其妙被一个自称是系统的东西强制绑定穿书了。\n\n狗系统对她威逼利诱，要她配合走完恶毒女配的剧情才能回家。\n\n原来她穿进的是一本修仙虐文小说。\n\n傻逼男主对失忆女主虐身又虐心。直到女主死后，猪油蒙了心的男主才幡然醒悟，原来他早已深爱女主而不自知。他抱着女主的尸体在雨中发誓，要将曾经伤害过女主的人都千刀万剐，挫骨扬灰！\n　　\n当男主提剑杀上门时，却被黎昭反杀。\n　　系统破防了，气急败坏【啊啊啊，你竟然把男主杀了。任务失败，我要把你抹杀！】\n　　\n黎昭擦了擦嘴角的血，笑得肆意张狂，“呵呵，那我死前也要拉着你给我陪葬！”\n　　她本应在渡劫飞升的雷劫中跟狗系统同归于尽，却被书中世界的天道所救。\n　　黎昭回到了现实世界，却发现一切都物是人非。\n　　恋爱脑姐姐为了嫁入白家，竟然泄露公司机密给竞争公司。父亲一气之下心梗发作去世了。母亲在丈夫和小女儿的双重打击下，郁郁寡欢，没几年也病逝了。\n　　大哥多器官衰竭，命不久矣，年轻俊美的影帝二哥也白发苍苍，垂垂老矣。\n　　……",
    "creationStatus": 1,
    "wordNumber": 117135,
    "tags": [
      "现言脑洞",
      "现代言情",
      "穿越",
      "女强",
      "无CP",
      "捉鬼"
    ]
  },
  "7651695960543726617": {
    "bookId": "7651695960543726617",
    "bookName": "开门！比格幼崽来拯救反派全家了",
    "authorName": "小火慢炖夜",
    "abstract": "【沙雕日常+萌宝团宠+玄学+比格型人格+发癫+救赎反派】\n　　江妙妙前一秒还在天桥下算命，下一秒就变成救赎反派文中衬托女主的炮灰女配。\n　　她本想逆天改命！\n　　可江妙妙低头一看，发现自己比一滩尿大不了多少，正是一个容易被屁崩死的年龄。\n　　于是乎，无奈的江妙妙决定做回自己。\n　　反派爸爸易燃易爆炸？安神符先拍他脑门上，再反复拆家让他知道什么是真正的魔童降世。\n　　大哥高冷且话少？江妙妙一出手他的嘴秒变输出机器！\n　　二哥是笑面虎？没关系很快他就笑不出来了，因为想赢的人脸上是没有笑容的。\n　　铁拳且憨憨的三哥更是被江妙妙玩弄于股掌之中！\n　　顺带着拯救女主、爆改男主、收服邪恶女配的江妙妙表示：穿书？易如反掌！",
    "creationStatus": 1,
    "wordNumber": 155185,
    "tags": [
      "现言脑洞",
      "现代言情",
      "风水秘术",
      "反派",
      "穿书",
      "团宠",
      "搞笑轻松"
    ]
  }
}