{
  "category": "女频新书榜-宫斗宅斗",
  "categoryId": 246,
  "total": 30,
  "items": [
    {
      "rank": 1,
      "title": "宫即，陛妹怕谁",
      "author": "慕",
      "bookId": "7648256759785589784",
      "link": "https://fanqienovel.com/page/7648256759785589784",
      "inRead": 593765,
      "wordCount": 193979,
      "desc": "宫斗+伪兄妹+极限扯+攻+训狗\n（，评涨）\n昭启春。\n沈嘉玉召宫，妃妾。\n彼宫似浪静，则害缠杂、暗流潜。诸妃争暗斗，百般算计，刚宫秀兢兢，怕，丧黄泉。\n唯沈嘉玉淡淡，示？\n爽，服干。\n甩巴掌资。\n今宠容华！势贵嫔！掌权妃！\n整宫搅翻覆。\n沈嘉玉丝毫惧。\n陛妹怕谁？！\n毕竟，陛羁绊深。\n，，，血缘。\n*\n娇纵妹宫，\n始寡疏冷帝王：尊玉贵养，亏待委屈。\n逐渐控破防帝王：朕喜欢，凭敢喜欢朕！\n，权御九州帝王，匍匐裙，俯首称臣，卑微求。\n*\n阅读指南:封建爹帝王娇纵跋扈妹",
      "cover": "https://p3-reading-sign.fqnovelpic.com/novel-pic/p2o2d5c57331ce0d26f4bcc690cadf74f13~tplv-resize:225:0.image?lk3s=5b7047ff&x-expires=1785393662&x-signature=hnwDa44YGbGDBl%2BuVqy1ZI6C5uQ%3D"
    },
    {
      "rank": 2,
      "title": "欢，摄政王慌",
      "author": "奇迹鱼",
      "bookId": "7642999427736554521",
      "link": "https://fanqienovel.com/page/7642999427736554521",
      "inRead": 181825,
      "wordCount": 205017,
      "desc": "【追妻火葬+强取豪夺+低】\n【娇软怂包×冷闷骚摄政王】\n，寇染霍珣依靠，苦追，药识破，囚禁寺庙，凄惨。\n药，翻药碗，断转。\n摄政王缠烂，，招驸！\n，假辞冷摄政王奇奇怪怪……\n赏宴，孔雀屏；\n喜欢，脱穿玄袍；\n抱抱举，站断；\n选驸，疯批逼角落：“干净，武，哪强？”\n脸困惑：“，娶。”\n红眶：“赘！”\n：？？？\n…\n，捧，铺锦绣，求。\n“选择，选项……？”\n——\n洁，，虐\n非爽，控勿！！！！！",
      "cover": "https://p3-reading-sign.fqnovelpic.com/novel-pic/p2o1499631f8c15ea640f546ca97763f9ea~tplv-resize:225:0.image?lk3s=5b7047ff&x-expires=1785393662&x-signature=%2FuFiDWxrSuqf4n3CepcN85xiZUs%3D"
    },
    {
      "rank": 3,
      "title": "皇城纨绔妻",
      "author": "拾",
      "bookId": "7638310864465972249",
      "link": "https://fanqienovel.com/page/7638310864465972249",
      "inRead": 144427,
      "wordCount": 251077,
      "desc": "评刚，慢慢涨。\n【+宅斗+权谋+爽+沙雕搞】\n崔清漪辈累。\n辈，座右铭：，咸鱼。\n弃途量尚，选择皇城纨绔梁王，提退休。\n：梁王术，嗣碍，嫁皇，崔怜。\n崔清漪：谢邀，术=赏赐，嗣碍=院干净，梁王=躺。\n软饭，香香。\n避雷预警：纨绔，术较差。掺杂词汇，提致歉",
      "cover": "https://p3-reading-sign.fqnovelpic.com/novel-pic/p2o18291f038b0f1c0ae5cf4e7bca7fbe6c~tplv-resize:225:0.image?lk3s=5b7047ff&x-expires=1785393662&x-signature=6h03NPivS%2Fv5A%2BJ7AmvBMMCkLqM%3D"
    },
    {
      "rank": 4,
      "title": "姐今吗",
      "author": "皆",
      "bookId": "7641605996002954265",
      "link": "https://fanqienovel.com/page/7641605996002954265",
      "inRead": 77761,
      "wordCount": 266881,
      "desc": "【+疯+追妻火葬+微强制+迷雄竞】\n谢云初昭侯府姐，侯府青梅竹，必嫁二哥妻，借层系，倒反罡，管裴。\n喝酒，曲，晚。\n惹恼，裴狠：“喜欢，娶！”\n，，，甚叉腰壮规矩。\n二哥，寺庙倒塌，选......曾。\n埋废墟，险丢。\n劫余，救佛，宝庄严，慈悲怀，悟。\n“姨，佛缘，请。”\n*\n谢云初佛，找。\n二哥跪狗。\n卫拦非送香囊。\n科状元堵院硬。\n连清冷持哥，逼房，“辈，休离。”\n谢云初斜视，丝毫摇，宁静且慈悲，“耽误佛。”",
      "cover": "https://p3-reading-sign.fqnovelpic.com/novel-pic/p2o878bb6e86284a0aa191ccbf745dce872~tplv-resize:225:0.image?lk3s=5b7047ff&x-expires=1785393662&x-signature=60fAUl70%2BhfjhFV5vHZ070y0cM0%3D"
    },
    {
      "rank": 5,
      "title": "奶娘府，绝嗣抱",
      "author": "",
      "bookId": "7650076960386731070",
      "link": "https://fanqienovel.com/page/7650076960386731070",
      "inRead": 80517,
      "wordCount": 154225,
      "desc": "：府孕？丰腴奶娘抱\n【系统＋胎＋丰腴＋宫斗宅斗＋独宠＋非双洁】\n社畜叶禾双班猝，朝穿古丈、早夭丰腴貌寡妇。\n婆嫌灾星，卖鳏换钱，跑半猝，顶包。\n恰逢府招奶娘，段奶足，顺试。\n岗奶，醒福系统，送婴语技。\n合。\n混，赚银府养。\n求调岗，辈奶嬷嬷。\n谁承，爷婚五嗣，养，调房丫，干升职薪！\n考核标准——怀孕！\n岗，叶禾示。\n系统。\n丸、丸、双胎丸、胎丸、肤丸、痛丸尽。\n崽品质，懈努，顶呱呱。\n昔传闻绝嗣爷，抱娃。\n六，\n吵闹，既幸福烦恼。\n奈摸叶禾隆孕肚，“，绝嗣药吗？碰。”\n：\n始，，强。",
      "cover": "https://p3-reading-sign.fqnovelpic.com/novel-pic/32877625b5b27d57fd0f83b26725a86d~tplv-resize:225:0.image?lk3s=5b7047ff&x-expires=1785393662&x-signature=NH2TH9MF7kLuQ9143xdBDmUPlto%3D"
    },
    {
      "rank": 6,
      "title": "勾禁欲？刚醒，哭！",
      "author": "春蜜桃",
      "bookId": "7654598215152454680",
      "link": "https://fanqienovel.com/page/7654598215152454680",
      "inRead": 74689,
      "wordCount": 151982,
      "desc": "【病娇欲+娇软咸鱼妹宝，超级宠，宠尾！】\n桑稚娇养，冰肌玉骨娇媚撩，勾引殿逃避。\n懵，醒，恶毒配。\n萧衍，则段残暴，阴鸷病娇，送宫牢，折磨致！\n桑稚压胡乱吻俊。\n保，砸晕！跑！\n—\n萧衍容貌俊，段狠戾，朝野畏惧存。\n皆传，冷矜贵，禁欲攀，近。\n故爬床刻，萧衍丧制隐忍。\n“稚稚，既招惹孤，逃。”\n萧衍禁欲，欲，占欲极强疯。\n晚桑稚压，低哄骗：\n“稚稚，乖，。”\n，桑稚甘愿妃。\n偷偷背飞。\n逃，追。\n萧衍抓逃跑桑稚，抚颤抖唇瓣，眸闪病态芒：\n“稚稚，孤够？...孤疯？”\n“跑，怪孤惩罚。”\n—\n皆，桑稚攀附萧衍。\n宫宴，众睽睽，帝王竟脸温柔，低哄怀。\n“朕错，皇朕。”",
      "cover": "https://p3-reading-sign.fqnovelpic.com/novel-pic/p2oafb8e470bf3853166855b728638abeb1~tplv-resize:225:0.image?lk3s=5b7047ff&x-expires=1785393662&x-signature=dc4G7qyPkPJE8ospkUSPhrYPeI0%3D"
    },
    {
      "rank": 7,
      "title": "妾？八千禁卫迎宫",
      "author": "鹿凰",
      "bookId": "7654988013595790361",
      "link": "https://fanqienovel.com/page/7654988013595790361",
      "inRead": 83252,
      "wordCount": 146213,
      "desc": "赐婚圣旨，谢昭颜贯财抵达京城，履跟镇北侯婚约，婚侯府堵。　　\n　　侯府摆阵仗，试图威：“商贾，根资侯府，若识趣愿贬妾，谢嫁妆丰厚份，勉强贵妾。”\n　　刚归镇北侯眉冷漠：“份差距，贵妾份抬举，识歹。阿缨救恩，资妻。”\n　　居临：“嫁妆归侯府支配，卑贱，务急京城礼节，侯府丢。”\n　　谢昭颜罢，冷冷。\n妾？凉，侯府该诛。\n　　“阿梅，贺陆续谢医馆赊欠贵补品，共计银九千百，今算。”\n　　“阿兰，镇北侯谢借银，拿账单，镇北侯钱。”\n　　“阿竹，镇北侯京城阿缨敌细，亮罪证，请镇北侯宾客释。”\n　　“阿菊，送宫，请皇旨，取消镇北侯婚约，派禁卫宫。”\n落，寂。\n镇北侯脸惨，摇摇欲坠。",
      "cover": "https://p3-reading-sign.fqnovelpic.com/novel-pic/p2o3876b08f8c04629c2b72d048b3e1def7~tplv-resize:225:0.image?lk3s=5b7047ff&x-expires=1785393662&x-signature=gHLjhWMNF%2BGAyzbDCQEepNI8v6s%3D"
    },
    {
      "rank": 8,
      "title": "穿揣崽恶毒，苟",
      "author": "瑶瑶",
      "bookId": "7643445112600546366",
      "link": "https://fanqienovel.com/page/7643445112600546366",
      "inRead": 53832,
      "wordCount": 288115,
      "desc": "（刚，低）【穿+揣崽+苟+甜宠+岭坛+】\n【苟破局萧清欢+厌恶香祁洛】\n堂堂梁嫡萧清欢，贫苦状元祁洛强取豪夺夜，愿揣崽嫁祁洛，催化剂，联反派送萧清欢线。\n苏芊昨骂骂咧咧骂萧清欢蠢，牌稀烂，睁萧清欢，崩局！\n惊绝萧清欢，苟，坚决垫脚石！\n撤掉盯梢。\n伙食必送。\n遇？必须破坏！\n，怎拐？撕伪装？拆反派布局？\n午夜梦，祁洛贴耳畔：“衾穴，，。”",
      "cover": "https://p3-reading-sign.fqnovelpic.com/novel-pic/p2oeefdaae787502d2e493b5b9b118fe30f~tplv-resize:225:0.image?lk3s=5b7047ff&x-expires=1785393662&x-signature=Y5ZNdrXVckKlB%2FiPk6sC6MwDKbk%3D"
    },
    {
      "rank": 9,
      "title": "爹诉反贼？",
      "author": "香菜猪猪",
      "bookId": "7648971640935566360",
      "link": "https://fanqienovel.com/page/7648971640935566360",
      "inRead": 65101,
      "wordCount": 201858,
      "desc": "【团宠+胚胎哄+松搞+沙雕+爽+微权谋+群+双洁】\n 楚茉辈侯府找，府假千。\n 假千，狼狈杀。\n ，彼侯府找，断跑雍王府抱紧雍王腿。\n“爹，爹吗？”\n 雍王：？\n *\n 楚茉抱腿，稳。\n 某落烧，醒忆穿，恶毒配。\n 腿，反派，脑怎造反登皇。\n 阴狠毒辣哥，善恶二哥，疯批哥，卑敏黑化哥，造反败，翘翘。\n 楚茉：跑及吗？\n 雍王磨刀：？\n *\n 楚茉，寂片雍王府鸡飞狗跳。\n ，精充沛癫，京城蹿跳，试图改局，罪清。\n 造反雍王淡菊雍王妃疼，追擦屁股。\n ＊\n 某，楚茉领。\n 楚茉：爹啊，穷。\n 雍王：确穷，。\n 楚茉：……",
      "cover": "https://p3-reading-sign.fqnovelpic.com/novel-pic/p2o17885ba1982ca17cfb222b9834b9ad34~tplv-resize:225:0.image?lk3s=5b7047ff&x-expires=1785393662&x-signature=M6Wm0PE9UJXQvpDZwUfZn%2Fyo8Ks%3D"
    },
    {
      "rank": 10,
      "title": "兼祧妻",
      "author": "棠",
      "bookId": "7643903286667381822",
      "link": "https://fanqienovel.com/page/7643903286667381822",
      "inRead": 63177,
      "wordCount": 136808,
      "desc": "（刚，涨）【貌柔弱孀妇  制守礼郡】\n\n罗令妤副绝容貌，双早亡，随舅舅。\n\n六嫁族首裴氏房。\n\n二青州宅。\n\n睁，离座囚笼，婆房留香火。\n\n，避避，终究。\n\n*\n\n\n视角：裴氏房嗣凋零，裴显礼，纪族首，朝傅，品郡。\n\n，嗣，延续房香火，君各，奈答。\n\n晓，裴氏郡早房寡媳积虑。\n\n深夜，罗令妤悔恨初招惹。\n\n非，妻病弱早逝，圆房！\n配！",
      "cover": "https://p3-reading-sign.fqnovelpic.com/novel-pic/p2o032253e992c13f17437004f60d1667be~tplv-resize:225:0.image?lk3s=5b7047ff&x-expires=1785393662&x-signature=HYFsAd9okzWwv4VQuaJnYMLXv%2FU%3D"
    },
    {
      "rank": 11,
      "title": "哀",
      "author": "娘",
      "bookId": "7580374951530597401",
      "link": "https://fanqienovel.com/page/7580374951530597401",
      "inRead": 56432,
      "wordCount": 197219,
      "desc": "掌权监\n    -    \n\n\n\n       \n    社畜穿，虞栖提退休。\n\n    谁劝垂帘政，哭谁怀疑。\n\n    料脸阴冷萌监顺，非架牛。\n\n    ，辈卷，怕卷？\n\n    -\n    \n    朝臣近效率，娘娘言：\n\n    “晨控制刻钟，请抓紧。”\n\n    “各，吵架计效议，影响终考评。”\n\n    及：“哀！”\n\n\n\n\n-\n排雷：监，半切（），线！！！！松短篇\n-\n架空，，宦官系借鉴朝司礼监。",
      "cover": "https://p3-reading-sign.fqnovelpic.com/novel-pic/12b198665e6ff3dcb736afe3dae41fea~tplv-resize:225:0.image?lk3s=5b7047ff&x-expires=1785393673&x-signature=K6QeQ%2BzRpMtB1%2B9mlqkD5lHGRLQ%3D"
    },
    {
      "rank": 12,
      "title": "躺躺，咸鱼恪妃宫廷",
      "author": "瓜池鱼",
      "bookId": "7642762307155545113",
      "link": "https://fanqienovel.com/page/7642762307155545113",
      "inRead": 60768,
      "wordCount": 272252,
      "desc": "【非规清穿，私设，考据党慎。】\n石玉瑶班猝，凉透，弥留际愿辈衣食忧，牛。\n　　，睛睁，顺治宫，恪妃石氏！静静汉妃嫔。\n　　，保养，顺治，宫静妃。咸鱼达。\n　　，谁诉怎？静静喝怎升职？",
      "cover": "https://p3-reading-sign.fqnovelpic.com/novel-pic/p2o6012a139700491471716244c8c1c7690~tplv-resize:225:0.image?lk3s=5b7047ff&x-expires=1785393673&x-signature=KHg%2BXz5O59CCIxMoyt2gr9ilmtg%3D"
    },
    {
      "rank": 13,
      "title": "萌宝团团朝武跪",
      "author": "清昭",
      "bookId": "7648189270460484670",
      "link": "https://fanqienovel.com/page/7648189270460484670",
      "inRead": 87367,
      "wordCount": 253154,
      "desc": "【刚，涨，观～】沈团团五，侯府卖王爷冲喜。\n抱包袱坐槛，爹。\n“爹，冲喜包吗？”\n落魄侯爷沈宴辞沉默息。\n抱闺，连夜敲登闻鼓。\n京城疯。\n废侯爷，奶团，翻浪？\n团团，二房私吞爵产。\n团团二，伪造遗嘱。\n团团，朝齐齐脸。\n皇帝热闹。\n，团嘴案。\n俩京城怕。\n朝奏折，沈宴辞朝闺。\n查案靠刑讯，查案靠团团瓜。\n俩闯祸，脸。\n朝武哭求皇帝：！",
      "cover": "https://p3-reading-sign.fqnovelpic.com/novel-pic/p2o6fb224fa146280d7e3aea33cfa4d417c~tplv-resize:225:0.image?lk3s=5b7047ff&x-expires=1785393673&x-signature=6KFchb0q6Pgem%2FwTg2sQiLDKz%2B8%3D"
    },
    {
      "rank": 14,
      "title": "陛，娘娘刺杀您",
      "author": "鱼浅猫",
      "bookId": "7651616267891133502",
      "link": "https://fanqienovel.com/page/7651616267891133502",
      "inRead": 58564,
      "wordCount": 208820,
      "desc": "刚评，涨【+兄夺弟妻+娇艳丽宠妃善言辞冷漠帝王+双洁+虐渣脸+局】\n\n　　未婚兄强取豪夺，强封妃。\n\n　　怨毁姻缘、囚，宫肆胡闹，撕圣旨、摔珍宝、众顶撞，尽段惹厌烦，求纸废，旧。\n\n　　论刁，冷漠帝王舍罚毫，迁，默默替挡阴私算计。\n\n　　油尽灯枯离，轰砸。\n\n　　似深未婚，乃背弃义渣尾；畏惧冷漠帝王，独独腔温柔。\n\n　　尽悔恨困魂魄，若，，待。\n\n　　睁，精宠妃。\n\n　　、宫斗，刁，收拾，管貌享福谈恋。\n\n　　、极卑，，患患，阴暗角落卑微疯。\n\n　　、穿越，黑穿越，宝宝。穿越观，朗善良，朋，穿越抢剧。",
      "cover": "https://p3-reading-sign.fqnovelpic.com/novel-pic/p2o7d60d42736ffdb4b92b2f5eb3e2d55f2~tplv-resize:225:0.image?lk3s=5b7047ff&x-expires=1785393673&x-signature=X1tGonk1Mw4q2r%2Fc6K5OxvH2SKg%3D"
    },
    {
      "rank": 15,
      "title": "穿恶毒配，权臣强夺",
      "author": "阿芙",
      "bookId": "7650564175827045438",
      "link": "https://fanqienovel.com/page/7650564175827045438",
      "inRead": 55283,
      "wordCount": 258699,
      "desc": "评刚~\n【穿＋阴湿惦＋+甜宠】\n桑雁雪朝穿越，喜提恶毒配剧，迫嫁号恶毒配。\n幸！蜜穿，义君。\n深著惨局，二拍即合：抱紧腿！\n跟嘘寒暖，努抱腿，渐渐劲。\n糟糕，！\n哥，，妇。\n……\n辈喜欢。\n，破静湖，该妄念。\n二宴绵绵跳舞，毫犹豫挡箭，二恩甜蜜，嫉妒墙蔓延。\n雨夜，二房闹宿，忍脚踹房。\n复礼，，，抢！\n……\n蜜严肃挡：“幸福。”\n：“破坏庭，庭，单五，双二六，。”\n蜜假：“玩啊。”\n挑衅：“怎？怕？喜欢吗？”\n蜜喊：“宝救，态呀~”\n",
      "cover": "https://p3-reading-sign.fqnovelpic.com/novel-pic/p2o8cfb9b8a22343b9441887e5755ddd3ec~tplv-resize:225:0.image?lk3s=5b7047ff&x-expires=1785393673&x-signature=Pzg%2FiM05pzF4aqmAQJKKZ2qL5Ss%3D"
    },
    {
      "rank": 16,
      "title": "，？",
      "author": "倚栏君",
      "bookId": "7652739677799058494",
      "link": "https://fanqienovel.com/page/7652739677799058494",
      "inRead": 57928,
      "wordCount": 148077,
      "desc": "【穿+宫斗宅斗+爽+黑+群】\n，疼哥哥赵纯，跟谓闺蜜旅，闺蜜推悬崖，摔瞬，推归悬崖。\n喜欢赵纯，穿《选，宫》，穿早逝妹妹。\n显，姐，姐控哥，及皇皇早。\n早皇，坏，罪魁祸首。\n留恋赵纯，谁惹，疯，顺努靠。\n反派二谢景，，官五品：殿，驸？\n赵纯：宰，舔狗，舔青梅。\n谢景：殿误，青梅（官）",
      "cover": "https://p3-reading-sign.fqnovelpic.com/novel-pic/p2oe451e8a8b31654e802f12bfd6f0669a0~tplv-resize:225:0.image?lk3s=5b7047ff&x-expires=1785393673&x-signature=DUxhc4dIYTv%2B8XnxZv%2F37i%2FnV%2BE%3D"
    },
    {
      "rank": 17,
      "title": "噩梦示警，恋脑皇醒",
      "author": "甜",
      "bookId": "7651659391661247513",
      "link": "https://fanqienovel.com/page/7651659391661247513",
      "inRead": 51073,
      "wordCount": 266314,
      "desc": "楚妠梦，梦武皇帝丈念念救恩，宝贝似养京郊苑，待痊愈刻宫，封贵妃，荣宠限；\n配皇，争醋嫉妒陷害废黜冷宫，娘蹶振。\n噩梦惊醒，矜矜业业温柔五贤妻楚妠顿，选秀选，纳妾纳；糕送，衣裳。\n，哪狗皇帝，送临朝称制！\n*\n萧肇尚襁褓抢养，傀儡皇帝，临朝执政野。\n选秀宴，双桃尾泪痣漂亮，滋反叛，摒弃侄，另选楚氏皇。\n五载，傀儡帝王，政夺权，始终陪伴侧，温默默，离弃。\n萧肇，皇敬，；\n忽，皇，，糕衣裳，选秀纳妃。\n“……”\n底装、装？\n阅读指南：①梦≠\n②双，背景架空汉，帝争锋较量\n③纯古思维，双念，钟渠",
      "cover": "https://p3-reading-sign.fqnovelpic.com/novel-pic/p2o95141e05ab962a43adaae08bd1534877~tplv-resize:225:0.image?lk3s=5b7047ff&x-expires=1785393673&x-signature=6opKhz9J%2FzhaS%2BOVGUF5cqSsu4Y%3D"
    },
    {
      "rank": 18,
      "title": "阴郁嫌假千",
      "author": "凭雪千",
      "bookId": "7647129617769171993",
      "link": "https://fanqienovel.com/page/7647129617769171993",
      "inRead": 37104,
      "wordCount": 176108,
      "desc": "【/嫌迷/追妻/强取豪夺】\n【注：姜雨姜棹缘血缘系，抱错假千，局千归族谱，律血缘系】\n简介：\n亡降临姜雨，抢。\n姜灵千份，姜姜灵宠嫌弃，，深深。\n怜悯姜雨历遍拥，姜灵未姜。\n姜娇纵讲千姐，兄寡言沉默差支棠，邻趴墙嘻嘻灯，义未婚……既冷淡。\n姜雨，切属。\n，，兄竹，婚未婚姜灵，切离。\n切。\n兄深底，\n邻竹拽衣角哪，\n连未未婚执拗跟。\n“切。”。\n“该属。”。",
      "cover": "https://p3-reading-sign.fqnovelpic.com/novel-pic/p2o9cdc38451e85f979323f27e5734912c9~tplv-resize:225:0.image?lk3s=5b7047ff&x-expires=1785393673&x-signature=cUVPqdO5qbzG8VlIOkfqPqiZJTk%3D"
    },
    {
      "rank": 19,
      "title": "奸臣爹，靠怀崽保",
      "author": "",
      "bookId": "7647858595509308440",
      "link": "https://fanqienovel.com/page/7647858595509308440",
      "inRead": 48745,
      "wordCount": 233245,
      "desc": "刚，评低涨哒。\n权臣、奸臣(笨蛋+双洁)\n坑\n萧章毓，京城娇，跋扈，奸臣。\n爹萧雄贪，二爹傅渊巨贪，联持朝堂，骂朱雀街排城。则威福，欺负弟弟，横京城，滋润。\n梦抄流，雪冻鹌鹑。\n梦攀，摄政首辅沈宴清，骑，扫。\n猛惊醒，拍案——怀首辅，怎线，。\n沈宴清铲除奸臣，杀娘吧？\n油盐。\n棘，未婚妻，朝侄，皇帝姑姑。\n拼“改邪归”，爹继续贪。萧章毓急，硬皮岭撞。\n谁笨蛋攻略铁石肠？",
      "cover": "https://p3-reading-sign.fqnovelpic.com/novel-pic/p2o071a9de055da4cf328725bd623801803~tplv-resize:225:0.image?lk3s=5b7047ff&x-expires=1785393673&x-signature=RAh0BcFuRxSQIDsYXWSs8a02ZtI%3D"
    },
    {
      "rank": 20,
      "title": "兄温顺，背疯批",
      "author": "秋辞灯鸣",
      "bookId": "7649687729906666521",
      "link": "https://fanqienovel.com/page/7649687729906666521",
      "inRead": 35797,
      "wordCount": 148095,
      "desc": "双洁+细流甜\n偏执病娇，阴湿鬼，言合杀，喜类型误！\n七，沈双亡，祖祖陆府。\n五，养兄，亦舅舅骤离，守灵突晕厥，梦窥。\n，竟。\n待极哥陆观词，竟反派。\n，陆观词爹疼，娘，甚攀附权贵，送富商。\n，。\n陆观词查，踏仇。\n，识致，南闯北靠委托。\n，陆观词试图杀掉。\n终，完仇，戕侧，永弱冠。\n梦醒，守侧陆观词，沈决，待怜哥，希顺遂。\n渐渐，件展始劲……\n夜，陆观词既躺沈侧，圈怀。\n睫颤，显装睡沈，陆观词，幽深偏执，癫狂，“，啊。”\n“永，？”",
      "cover": "https://p3-reading-sign.fqnovelpic.com/novel-pic/p2o8195f3cd3b34c03c33f78ed344ba7d48~tplv-resize:225:0.image?lk3s=5b7047ff&x-expires=1785393673&x-signature=%2FRdoOn1P4vJAFcUlUdCjCCQ9ZNc%3D"
    },
    {
      "rank": 21,
      "title": "挺孕肚压室，姑娘软倒怀",
      "author": "夏冰",
      "bookId": "7514133125778115646",
      "link": "https://fanqienovel.com/page/7514133125778115646",
      "inRead": 33983,
      "wordCount": 138541,
      "desc": "【绝➕➕病弱➕宠妾灭妻】\n      ，林窈娘苏，苏姐嫁裴孕，擢选妾，送裴府，枚绵延嗣棋。\n　　\n　　府久，孕，谁承朝产，胎产香消玉殒。\n　　\n　　孤魂游荡，府算计，，睁睁伤，“”夭折！\n　　\n　　背推，皆姐，苏婉柔！\n　　\n　　仇恨林窈娘疯狂滋，达顶峰，运跟诡异玩——。\n　　\n　　，林窈娘，沈云霜，曾苏婉柔夜寐，极，妹。",
      "cover": "https://p3-reading-sign.fqnovelpic.com/novel-pic/p2ocb34dac9fc538ea1acdf2c1517641e88~tplv-resize:225:0.image?lk3s=5b7047ff&x-expires=1785393681&x-signature=PK9aK0j2eb%2FfOiYECu7DqicWGf4%3D"
    },
    {
      "rank": 22,
      "title": "贵妾，帝王强夺宫",
      "author": "千霜",
      "bookId": "7381538422843788313",
      "link": "https://fanqienovel.com/page/7381538422843788313",
      "inRead": 39294,
      "wordCount": 189099,
      "desc": "【嬷 弱 买股 虐慎】\n避雷:，玛丽苏迷，洁洁，虐宝宝慎！！阴湿鬼雷，封建爹掌控欲超强，……量。量虐爽，骂，骂吧，值骂。\n宁洛宁嫡，颜冠绝京城，朝抄，兄流，迫寄官府，官瑾藏深宅妾。官瑾宠、，困院。宁洛，换稳，选择，谓深，妻妾偏。散，宁洛局遇乔装帝王萧景珩。份，困境，深委屈。步步近，哄、依赖，官府夺，强娶宫。宫墙深深，恩宠牢。帝王诞嗣，始终忘……",
      "cover": "https://p3-reading-sign.fqnovelpic.com/novel-pic/p2o80eba1091d7fe6add2e738d0ae0503d4~tplv-resize:225:0.image?lk3s=5b7047ff&x-expires=1785393681&x-signature=aYrASEJKgKRRgjO0ilgUbtDtbtw%3D"
    },
    {
      "rank": 23,
      "title": "守寡，破戒勾错",
      "author": "朱莉王",
      "bookId": "7636858136652942398",
      "link": "https://fanqienovel.com/page/7636858136652942398",
      "inRead": 42485,
      "wordCount": 100281,
      "desc": "婚五，守寡，寂寞耐，段勾引丈，撩错。\n　　抽，百般纠缠。\n　　-\n　　房，丈清晰闻。\n　　房，容邪肆，指握，引推。\n　　惊恐哭掩恶劣嗓，“，，诉，跟跟。”",
      "cover": "https://p3-reading-sign.fqnovelpic.com/novel-pic/p2o8cd3658eb8af07f47a98e9b46750e7da~tplv-resize:225:0.image?lk3s=5b7047ff&x-expires=1785393681&x-signature=1Da8XzNe7Q7HnunOIYs8nmimptY%3D"
    },
    {
      "rank": 24,
      "title": "觊觎臣妻：清冷权臣装",
      "author": "雪尽霁",
      "bookId": "7650103887151500350",
      "link": "https://fanqienovel.com/page/7650103887151500350",
      "inRead": 37662,
      "wordCount": 191458,
      "desc": "【强取豪夺＋臣妻＋岭坛＋步步营】\n靖朝权倾朝野司裴修晏，皆清冷持，悲悯众佛。\n温眠棠深。\n七品御史沈煜娇妻，君羽翼稳。\n沈煜遇青爷。\n权倾朝野司裴修晏赏识，提拔，甚连递折圈阅夸赞。\n誓草衔环，答侯爷遇恩。\n某，陷案，即临抄斩局。\n投，温眠棠雨滂沱深夜，跪权倾朝野司府求。\n房，尊玉雕般圣缓步，温眠棠衣衫尽湿，跪倒清冷端脚。\n微凉指腹勾巴。\n“求？”温醇酿，底翻涌懂疯狂，“算拿换沈？”\n温眠棠，君局，圣引笼，布罗网。",
      "cover": "https://p3-reading-sign.fqnovelpic.com/novel-pic/p2oe1251215195534ca2ca4e050c8be3773~tplv-resize:225:0.image?lk3s=5b7047ff&x-expires=1785393681&x-signature=iC7ohOpOZtMMT709nIfS855ZvUg%3D"
    },
    {
      "rank": 25,
      "title": "搜罗八财富，古首富",
      "author": "网梦",
      "bookId": "7636618062921206809",
      "link": "https://fanqienovel.com/page/7636618062921206809",
      "inRead": 35856,
      "wordCount": 286600,
      "desc": "空骤！穿越？\n囤货缺钱？怕啥！\n“八联”底丰厚，零元购扫空！\n穿宠庶？怕球！\n保硬，偏古搞 —— 甲店艳压闺阁，照馆惊颜，影院引爆城，拍卖垄断奇珍！\n管嫡庶尊卑，凭空，艳羡，搅翻古！",
      "cover": "https://p3-reading-sign.fqnovelpic.com/novel-pic/p2ob00058ec4eef2a40b94e41c38cce453f~tplv-resize:225:0.image?lk3s=5b7047ff&x-expires=1785393681&x-signature=eyHJ1sSxxmdbd76VksHm9vudVyA%3D"
    },
    {
      "rank": 26,
      "title": "侍宅斗",
      "author": "麦熟千",
      "bookId": "7539760184927734809",
      "link": "https://fanqienovel.com/page/7539760184927734809",
      "inRead": 35094,
      "wordCount": 172276,
      "desc": "【+极残酷雄竞+洁】晏，衡，官府强制妻制。\n\n　　宁君府嫡沈貌双，引京倾慕。敬慕亦兄亦、伴读林竟舟，未料帝王圣旨，镇云珩赐。圣旨，林竟舟屈居侧，云珩忍府存极强侧室。\n\n　　。\n\n　　府侍渐，宅争斗腥血雨，甚差闹。\n\n　　---\n\n　　云珩府，妻绝宠，林竟舟郁郁寡欢，属忧：“首辅，今皆恋郎，属引荐奴侍，属唯首瞻，二合，压。”\n\n　　林竟舟宠久，投，采纳属建议，步底智举引狼室，清楚。\n\n　　注排雷：非尊，。构，。",
      "cover": "https://p3-reading-sign.fqnovelpic.com/novel-pic/8f0911e14a0495b9eff6143433db739e~tplv-resize:225:0.image?lk3s=5b7047ff&x-expires=1785393681&x-signature=sT77yUneiS%2F8vshm8Ysw9zL9AS4%3D"
    },
    {
      "rank": 27,
      "title": "浥秋",
      "author": "午夜嗷嗷",
      "bookId": "7633066525179530264",
      "link": "https://fanqienovel.com/page/7633066525179530264",
      "inRead": 35736,
      "wordCount": 257357,
      "desc": "【王妃孟浪王爷】\n【双洁+追妻火葬+】（排雷：非强非爽，虐，忆强取豪夺，非喜勿）\n宋澄秋王府六载，初妾室，侧妃，步步规训周朝贤惠庄王妃。\n宅，操持馈，，侍奉婆，未丝毫差错。\n京贵妇典范，称颂。\n唯宋澄秋约，今限，该离。\n——\n庄王霍浥幼，雨雨，今握兵权，权倾朝野，朝，连銮殿坐，敢忤逆言，唯独宋澄秋栽跟。\n，宋澄秋拒妾。\n二，宋澄秋肯。\n，宋澄秋离。\n——\n离剧：\n宋澄秋清离摆霍浥：“王爷，请吧。”\n霍浥脸黑沉，眉微跳，压抑雨欲盛怒：“恨王段，王离？”\n宋澄秋摇。\n霍浥咬牙：“兄勾引？”\n宋澄秋沉默，懒释。\n霍浥恶狠狠撕碎离：“宋澄秋，休！”\n（概强取豪夺逞，六逸，深沉王爷，王妃脚踹故~）",
      "cover": "https://p3-reading-sign.fqnovelpic.com/novel-pic/p2o911d8b9c3baab4ee7699fba440bfef3b~tplv-resize:225:0.image?lk3s=5b7047ff&x-expires=1785393681&x-signature=j7PxvczAJIwEDRrMA%2F9IcW16MIY%3D"
    },
    {
      "rank": 28,
      "title": "丰腴丫鬟甜香，首辅夜控",
      "author": "卟瑶",
      "bookId": "7661454852752411672",
      "link": "https://fanqienovel.com/page/7661454852752411672",
      "inRead": 49791,
      "wordCount": 118073,
      "desc": "【古言 + 权谋宅斗 + 份升级 + 婚+ 复仇爽 + 双强。】\n苏棠。\n穿丰腴，奶香献首辅陆砚，渣蛊惑，盗取密转投怀抱，终殆尽，沉冰冷湖底。\n刚送陆府，铜镜、段妖娆脸，誓:绝，绝饱饭，绝质秘密。\n翼翼饿，靠预剧偷攒私房钱，算渣跑。\n算漏件——“近、复礼”首辅陆砚，香毫抵抗。\n触，控掩饰厌恶：“伤败俗。”\n二房独，罚抄，视线落墨汁浸湿衣襟，喉滚。\n，仇欺负，陆砚拖半，按腿，巴掌落:“官敢，该该？”\n“啪”脆响，苏棠羞愤欲，贴耳畔低语:“疼吗?疼，、、藏银，官。”\n，私房钱罐，莫妙银票。\n陆砚晚房“查账”，查查查",
      "cover": "https://p3-reading-sign.fqnovelpic.com/novel-pic/p2o6f8bce9158c93a927a569c7c5d2a5fe0~tplv-resize:225:0.image?lk3s=5b7047ff&x-expires=1785393681&x-signature=VDb75kzRRgLERXJXYVl2Q%2BrwY7w%3D"
    },
    {
      "rank": 29,
      "title": "叹缕",
      "author": "冬瓜梨",
      "bookId": "7629335999511792702",
      "link": "https://fanqienovel.com/page/7629335999511792702",
      "inRead": 36132,
      "wordCount": 199013,
      "desc": "谁嫡？谁承宗？\n室嫡，刚嫡，庶压。\n沈照禅兴。\n订傅费氏。\n费氏，娘郭氏婆婆款摆，费氏珠转沈照禅整离。\n娘郭氏肝肠寸断，仿佛换，沈乱。\n沈照禅宫始……紫袍，阶，俯瞰群臣止。\n，伐异，，散尽",
      "cover": "https://p3-reading-sign.fqnovelpic.com/novel-pic/p2o0ef078a4ccc450016bdfa8a4c2b1feb0~tplv-resize:225:0.image?lk3s=5b7047ff&x-expires=1785393681&x-signature=XPRCh%2Bci382HgEOACGqbRPGszZE%3D"
    },
    {
      "rank": 30,
      "title": "！偏执囚禁",
      "author": "斑斓星",
      "bookId": "7651495328209701950",
      "link": "https://fanqienovel.com/page/7651495328209701950",
      "inRead": 32339,
      "wordCount": 156543,
      "desc": "沈昭宁，盯，纯粹倒霉。\n赏宴，京城贵，偏偏挑二青梅竹！\n权势富贵。\n稀罕！\n沈昭宁冒危险病，妃拱需。\n囚禁寝殿，挂画。\n怀，妩媚，楚楚怜，栩栩。\n，根逃掉掌。\n“怎？久，够？”\n沈昭宁猛转，萧云祈站。\n握幅未干透画，画，穿套薄纱红裙。\n“——”\n伸指堵，低凑近耳，低沉蛊惑：\n“夜梦勾孤。\n“孤怎舍？”",
      "cover": "https://p3-reading-sign.fqnovelpic.com/novel-pic/p2oea7a97a5dfd29eabf4797b24323645fc~tplv-resize:225:0.image?lk3s=5b7047ff&x-expires=1785393681&x-signature=8FmMNDw%2FQ1nim8jYnkSmqbjAleQ%3D"
    }
  ]
}